[
  {
    "positions": [
      {
        "protocol": "AaveV3",
        "position_usd": 50000.0,
        "exit_fee_usd": 0.0,
        "net_exit_value_usd": 50000.0,
        "estimated_exit_days": 0.0,
        "can_exit_in_target": true,
        "exit_liquidity_score": 100,
        "exit_label": "INSTANT",
        "market_depth_coverage_pct": 200.0,
        "bottleneck": null,
        "recommendation": "Immediate exit available. Depth covers 200% of position."
      }
    ],
    "instantly_exitable_usd": 50000.0,
    "total_position_usd": 50000.0,
    "liquidity_ratio_pct": 100.0,
    "most_locked": null,
    "average_exit_liquidity_score": 100.0,
    "timestamp": 1784021251.133443
  },
  {
    "positions": [
      {
        "protocol": "Queue",
        "position_usd": 30000.0,
        "exit_fee_usd": 150.0,
        "net_exit_value_usd": 29850.0,
        "estimated_exit_days": 8.0,
        "can_exit_in_target": false,
        "exit_liquidity_score": 30,
        "exit_label": "SLOW",
        "market_depth_coverage_pct": 16.666666666666664,
        "bottleneck": "DAILY_LIMIT",
        "recommendation": "Exit takes 8d (>target 7d). Reduce position or wait."
      }
    ],
    "instantly_exitable_usd": 0,
    "total_position_usd": 30000.0,
    "liquidity_ratio_pct": 0.0,
    "most_locked": "Queue",
    "average_exit_liquidity_score": 30.0,
    "timestamp": 1784021251.1382976
  },
  {
    "positions": [
      {
        "protocol": "Queue",
        "position_usd": 30000.0,
        "exit_fee_usd": 150.0,
        "net_exit_value_usd": 29850.0,
        "estimated_exit_days": 8.0,
        "can_exit_in_target": false,
        "exit_liquidity_score": 30,
        "exit_label": "SLOW",
        "market_depth_coverage_pct": 16.666666666666664,
        "bottleneck": "DAILY_LIMIT",
        "recommendation": "Exit takes 8d (>target 7d). Reduce position or wait."
      }
    ],
    "instantly_exitable_usd": 0,
    "total_position_usd": 30000.0,
    "liquidity_ratio_pct": 0.0,
    "most_locked": "Queue",
    "average_exit_liquidity_score": 30.0,
    "timestamp": 1784021251.1432667
  },
  {
    "positions": [
      {
        "protocol": "Queue",
        "position_usd": 30000.0,
        "exit_fee_usd": 150.0,
        "net_exit_value_usd": 29850.0,
        "estimated_exit_days": 8.0,
        "can_exit_in_target": false,
        "exit_liquidity_score": 30,
        "exit_label": "SLOW",
        "market_depth_coverage_pct": 16.666666666666664,
        "bottleneck": "DAILY_LIMIT",
        "recommendation": "Exit takes 8d (>target 7d). Reduce position or wait."
      }
    ],
    "instantly_exitable_usd": 0,
    "total_position_usd": 30000.0,
    "liquidity_ratio_pct": 0.0,
    "most_locked": "Queue",
    "average_exit_liquidity_score": 30.0,
    "timestamp": 1784021251.1480482
  },
  {
    "positions": [
      {
        "protocol": "Queue",
        "position_usd": 30000.0,
        "exit_fee_usd": 150.0,
        "net_exit_value_usd": 29850.0,
        "estimated_exit_days": 8.0,
        "can_exit_in_target": false,
        "exit_liquidity_score": 30,
        "exit_label": "SLOW",
        "market_depth_coverage_pct": 16.666666666666664,
        "bottleneck": "DAILY_LIMIT",
        "recommendation": "Exit takes 8d (>target 7d). Reduce position or wait."
      }
    ],
    "instantly_exitable_usd": 0,
    "total_position_usd": 30000.0,
    "liquidity_ratio_pct": 0.0,
    "most_locked": "Queue",
    "average_exit_liquidity_score": 30.0,
    "timestamp": 1784021251.1530173
  },
  {
    "positions": [
      {
        "protocol": "Queue",
        "position_usd": 30000.0,
        "exit_fee_usd": 150.0,
        "net_exit_value_usd": 29850.0,
        "estimated_exit_days": 8.0,
        "can_exit_in_target": false,
        "exit_liquidity_score": 30,
        "exit_label": "SLOW",
        "market_depth_coverage_pct": 16.666666666666664,
        "bottleneck": "DAILY_LIMIT",
        "recommendation": "Exit takes 8d (>target 7d). Reduce position or wait."
      }
    ],
    "instantly_exitable_usd": 0,
    "total_position_usd": 30000.0,
    "liquidity_ratio_pct": 0.0,
    "most_locked": "Queue",
    "average_exit_liquidity_score": 30.0,
    "timestamp": 1784021251.1578746
  },
  {
    "positions": [
      {
        "protocol": "X",
        "position_usd": 50000.0,
        "exit_fee_usd": 0.0,
        "net_exit_value_usd": 50000.0,
        "estimated_exit_days": 1.0,
        "can_exit_in_target": true,
        "exit_liquidity_score": 90,
        "exit_label": "FAST",
        "market_depth_coverage_pct": 200.0,
        "bottleneck": "QUEUE",
        "recommendation": "Exit available quickly. Monitor queue size."
      }
    ],
    "instantly_exitable_usd": 0,
    "total_position_usd": 50000.0,
    "liquidity_ratio_pct": 0.0,
    "most_locked": "X",
    "average_exit_liquidity_score": 90.0,
    "timestamp": 1784021251.1612601
  },
  {
    "positions": [
      {
        "protocol": "Aave",
        "position_usd": 50000.0,
        "exit_fee_usd": 0.0,
        "net_exit_value_usd": 50000.0,
        "estimated_exit_days": 0.0,
        "can_exit_in_target": true,
        "exit_liquidity_score": 100,
        "exit_label": "INSTANT",
        "market_depth_coverage_pct": 400.0,
        "bottleneck": null,
        "recommendation": "Immediate exit available. Depth covers 400% of position."
      },
      {
        "protocol": "Maple",
        "position_usd": 30000.0,
        "exit_fee_usd": 0.0,
        "net_exit_value_usd": 30000.0,
        "estimated_exit_days": 90.0,
        "can_exit_in_target": false,
        "exit_liquidity_score": 17,
        "exit_label": "LOCKED",
        "market_depth_coverage_pct": 33.33333333333333,
        "bottleneck": "LOCK_UP",
        "recommendation": "Locked for 90d. Plan around lock expiry."
      },
      {
        "protocol": "Queue",
        "position_usd": 30000.0,
        "exit_fee_usd": 150.0,
        "net_exit_value_usd": 29850.0,
        "estimated_exit_days": 8.0,
        "can_exit_in_target": false,
        "exit_liquidity_score": 30,
        "exit_label": "SLOW",
        "market_depth_coverage_pct": 16.666666666666664,
        "bottleneck": "DAILY_LIMIT",
        "recommendation": "Exit takes 8d (>target 7d). Reduce position or wait."
      }
    ],
    "instantly_exitable_usd": 50000.0,
    "total_position_usd": 110000.0,
    "liquidity_ratio_pct": 45.45454545454545,
    "most_locked": "Maple",
    "average_exit_liquidity_score": 49.0,
    "timestamp": 1784021251.166834
  },
  {
    "positions": [
      {
        "protocol": "Aave",
        "position_usd": 50000.0,
        "exit_fee_usd": 0.0,
        "net_exit_value_usd": 50000.0,
        "estimated_exit_days": 0.0,
        "can_exit_in_target": true,
        "exit_liquidity_score": 100,
        "exit_label": "INSTANT",
        "market_depth_coverage_pct": 400.0,
        "bottleneck": null,
        "recommendation": "Immediate exit available. Depth covers 400% of position."
      },
      {
        "protocol": "Maple",
        "position_usd": 30000.0,
        "exit_fee_usd": 0.0,
        "net_exit_value_usd": 30000.0,
        "estimated_exit_days": 90.0,
        "can_exit_in_target": false,
        "exit_liquidity_score": 17,
        "exit_label": "LOCKED",
        "market_depth_coverage_pct": 33.33333333333333,
        "bottleneck": "LOCK_UP",
        "recommendation": "Locked for 90d. Plan around lock expiry."
      },
      {
        "protocol": "Queue",
        "position_usd": 30000.0,
        "exit_fee_usd": 150.0,
        "net_exit_value_usd": 29850.0,
        "estimated_exit_days": 8.0,
        "can_exit_in_target": false,
        "exit_liquidity_score": 30,
        "exit_label": "SLOW",
        "market_depth_coverage_pct": 16.666666666666664,
        "bottleneck": "DAILY_LIMIT",
        "recommendation": "Exit takes 8d (>target 7d). Reduce position or wait."
      }
    ],
    "instantly_exitable_usd": 50000.0,
    "total_position_usd": 110000.0,
    "liquidity_ratio_pct": 45.45454545454545,
    "most_locked": "Maple",
    "average_exit_liquidity_score": 49.0,
    "timestamp": 1784021251.171708
  },
  {
    "positions": [
      {
        "protocol": "Aave",
        "position_usd": 50000.0,
        "exit_fee_usd": 0.0,
        "net_exit_value_usd": 50000.0,
        "estimated_exit_days": 0.0,
        "can_exit_in_target": true,
        "exit_liquidity_score": 100,
        "exit_label": "INSTANT",
        "market_depth_coverage_pct": 400.0,
        "bottleneck": null,
        "recommendation": "Immediate exit available. Depth covers 400% of position."
      },
      {
        "protocol": "Maple",
        "position_usd": 30000.0,
        "exit_fee_usd": 0.0,
        "net_exit_value_usd": 30000.0,
        "estimated_exit_days": 90.0,
        "can_exit_in_target": false,
        "exit_liquidity_score": 17,
        "exit_label": "LOCKED",
        "market_depth_coverage_pct": 33.33333333333333,
        "bottleneck": "LOCK_UP",
        "recommendation": "Locked for 90d. Plan around lock expiry."
      },
      {
        "protocol": "Queue",
        "position_usd": 30000.0,
        "exit_fee_usd": 150.0,
        "net_exit_value_usd": 29850.0,
        "estimated_exit_days": 8.0,
        "can_exit_in_target": false,
        "exit_liquidity_score": 30,
        "exit_label": "SLOW",
        "market_depth_coverage_pct": 16.666666666666664,
        "bottleneck": "DAILY_LIMIT",
        "recommendation": "Exit takes 8d (>target 7d). Reduce position or wait."
      }
    ],
    "instantly_exitable_usd": 50000.0,
    "total_position_usd": 110000.0,
    "liquidity_ratio_pct": 45.45454545454545,
    "most_locked": "Maple",
    "average_exit_liquidity_score": 49.0,
    "timestamp": 1784021251.1769202
  },
  {
    "positions": [
      {
        "protocol": "Aave",
        "position_usd": 50000.0,
        "exit_fee_usd": 0.0,
        "net_exit_value_usd": 50000.0,
        "estimated_exit_days": 0.0,
        "can_exit_in_target": true,
        "exit_liquidity_score": 100,
        "exit_label": "INSTANT",
        "market_depth_coverage_pct": 400.0,
        "bottleneck": null,
        "recommendation": "Immediate exit available. Depth covers 400% of position."
      },
      {
        "protocol": "Maple",
        "position_usd": 30000.0,
        "exit_fee_usd": 0.0,
        "net_exit_value_usd": 30000.0,
        "estimated_exit_days": 90.0,
        "can_exit_in_target": false,
        "exit_liquidity_score": 17,
        "exit_label": "LOCKED",
        "market_depth_coverage_pct": 33.33333333333333,
        "bottleneck": "LOCK_UP",
        "recommendation": "Locked for 90d. Plan around lock expiry."
      },
      {
        "protocol": "Queue",
        "position_usd": 30000.0,
        "exit_fee_usd": 150.0,
        "net_exit_value_usd": 29850.0,
        "estimated_exit_days": 8.0,
        "can_exit_in_target": false,
        "exit_liquidity_score": 30,
        "exit_label": "SLOW",
        "market_depth_coverage_pct": 16.666666666666664,
        "bottleneck": "DAILY_LIMIT",
        "recommendation": "Exit takes 8d (>target 7d). Reduce position or wait."
      }
    ],
    "instantly_exitable_usd": 50000.0,
    "total_position_usd": 110000.0,
    "liquidity_ratio_pct": 45.45454545454545,
    "most_locked": "Maple",
    "average_exit_liquidity_score": 49.0,
    "timestamp": 1784021251.1818836
  },
  {
    "positions": [
      {
        "protocol": "Aave",
        "position_usd": 50000.0,
        "exit_fee_usd": 0.0,
        "net_exit_value_usd": 50000.0,
        "estimated_exit_days": 0.0,
        "can_exit_in_target": true,
        "exit_liquidity_score": 100,
        "exit_label": "INSTANT",
        "market_depth_coverage_pct": 400.0,
        "bottleneck": null,
        "recommendation": "Immediate exit available. Depth covers 400% of position."
      },
      {
        "protocol": "Maple",
        "position_usd": 30000.0,
        "exit_fee_usd": 0.0,
        "net_exit_value_usd": 30000.0,
        "estimated_exit_days": 90.0,
        "can_exit_in_target": false,
        "exit_liquidity_score": 17,
        "exit_label": "LOCKED",
        "market_depth_coverage_pct": 33.33333333333333,
        "bottleneck": "LOCK_UP",
        "recommendation": "Locked for 90d. Plan around lock expiry."
      },
      {
        "protocol": "Queue",
        "position_usd": 30000.0,
        "exit_fee_usd": 150.0,
        "net_exit_value_usd": 29850.0,
        "estimated_exit_days": 8.0,
        "can_exit_in_target": false,
        "exit_liquidity_score": 30,
        "exit_label": "SLOW",
        "market_depth_coverage_pct": 16.666666666666664,
        "bottleneck": "DAILY_LIMIT",
        "recommendation": "Exit takes 8d (>target 7d). Reduce position or wait."
      }
    ],
    "instantly_exitable_usd": 50000.0,
    "total_position_usd": 110000.0,
    "liquidity_ratio_pct": 45.45454545454545,
    "most_locked": "Maple",
    "average_exit_liquidity_score": 49.0,
    "timestamp": 1784021251.187252
  },
  {
    "positions": [
      {
        "protocol": "Aave",
        "position_usd": 50000.0,
        "exit_fee_usd": 0.0,
        "net_exit_value_usd": 50000.0,
        "estimated_exit_days": 0.0,
        "can_exit_in_target": true,
        "exit_liquidity_score": 100,
        "exit_label": "INSTANT",
        "market_depth_coverage_pct": 400.0,
        "bottleneck": null,
        "recommendation": "Immediate exit available. Depth covers 400% of position."
      },
      {
        "protocol": "Maple",
        "position_usd": 30000.0,
        "exit_fee_usd": 0.0,
        "net_exit_value_usd": 30000.0,
        "estimated_exit_days": 90.0,
        "can_exit_in_target": false,
        "exit_liquidity_score": 17,
        "exit_label": "LOCKED",
        "market_depth_coverage_pct": 33.33333333333333,
        "bottleneck": "LOCK_UP",
        "recommendation": "Locked for 90d. Plan around lock expiry."
      },
      {
        "protocol": "Queue",
        "position_usd": 30000.0,
        "exit_fee_usd": 150.0,
        "net_exit_value_usd": 29850.0,
        "estimated_exit_days": 8.0,
        "can_exit_in_target": false,
        "exit_liquidity_score": 30,
        "exit_label": "SLOW",
        "market_depth_coverage_pct": 16.666666666666664,
        "bottleneck": "DAILY_LIMIT",
        "recommendation": "Exit takes 8d (>target 7d). Reduce position or wait."
      }
    ],
    "instantly_exitable_usd": 50000.0,
    "total_position_usd": 110000.0,
    "liquidity_ratio_pct": 45.45454545454545,
    "most_locked": "Maple",
    "average_exit_liquidity_score": 49.0,
    "timestamp": 1784021251.192399
  },
  {
    "positions": [
      {
        "protocol": "Aave",
        "position_usd": 50000.0,
        "exit_fee_usd": 0.0,
        "net_exit_value_usd": 50000.0,
        "estimated_exit_days": 0.0,
        "can_exit_in_target": true,
        "exit_liquidity_score": 100,
        "exit_label": "INSTANT",
        "market_depth_coverage_pct": 400.0,
        "bottleneck": null,
        "recommendation": "Immediate exit available. Depth covers 400% of position."
      },
      {
        "protocol": "Maple",
        "position_usd": 30000.0,
        "exit_fee_usd": 0.0,
        "net_exit_value_usd": 30000.0,
        "estimated_exit_days": 90.0,
        "can_exit_in_target": false,
        "exit_liquidity_score": 17,
        "exit_label": "LOCKED",
        "market_depth_coverage_pct": 33.33333333333333,
        "bottleneck": "LOCK_UP",
        "recommendation": "Locked for 90d. Plan around lock expiry."
      },
      {
        "protocol": "Queue",
        "position_usd": 30000.0,
        "exit_fee_usd": 150.0,
        "net_exit_value_usd": 29850.0,
        "estimated_exit_days": 8.0,
        "can_exit_in_target": false,
        "exit_liquidity_score": 30,
        "exit_label": "SLOW",
        "market_depth_coverage_pct": 16.666666666666664,
        "bottleneck": "DAILY_LIMIT",
        "recommendation": "Exit takes 8d (>target 7d). Reduce position or wait."
      }
    ],
    "instantly_exitable_usd": 50000.0,
    "total_position_usd": 110000.0,
    "liquidity_ratio_pct": 45.45454545454545,
    "most_locked": "Maple",
    "average_exit_liquidity_score": 49.0,
    "timestamp": 1784021251.1981914
  },
  {
    "positions": [
      {
        "protocol": "AaveV3",
        "position_usd": 50000.0,
        "exit_fee_usd": 0.0,
        "net_exit_value_usd": 50000.0,
        "estimated_exit_days": 0.0,
        "can_exit_in_target": true,
        "exit_liquidity_score": 100,
        "exit_label": "INSTANT",
        "market_depth_coverage_pct": 200.0,
        "bottleneck": null,
        "recommendation": "Immediate exit available. Depth covers 200% of position."
      }
    ],
    "instantly_exitable_usd": 50000.0,
    "total_position_usd": 50000.0,
    "liquidity_ratio_pct": 100.0,
    "most_locked": null,
    "average_exit_liquidity_score": 100.0,
    "timestamp": 1784021251.2036839
  },
  {
    "positions": [
      {
        "protocol": "AaveV3",
        "position_usd": 100000.0,
        "exit_fee_usd": 0.0,
        "net_exit_value_usd": 100000.0,
        "estimated_exit_days": 0.0,
        "can_exit_in_target": true,
        "exit_liquidity_score": 80,
        "exit_label": "INSTANT",
        "market_depth_coverage_pct": 10.0,
        "bottleneck": "MARKET_DEPTH",
        "recommendation": "Immediate exit available. Depth covers 10% of position."
      }
    ],
    "instantly_exitable_usd": 100000.0,
    "total_position_usd": 100000.0,
    "liquidity_ratio_pct": 100.0,
    "most_locked": null,
    "average_exit_liquidity_score": 80.0,
    "timestamp": 1784021251.208859
  },
  {
    "positions": [
      {
        "protocol": "AaveV3",
        "position_usd": 50000.0,
        "exit_fee_usd": 0.0,
        "net_exit_value_usd": 50000.0,
        "estimated_exit_days": 0.0,
        "can_exit_in_target": true,
        "exit_liquidity_score": 95,
        "exit_label": "INSTANT",
        "market_depth_coverage_pct": 100.0,
        "bottleneck": null,
        "recommendation": "Immediate exit available. Depth covers 100% of position."
      }
    ],
    "instantly_exitable_usd": 50000.0,
    "total_position_usd": 50000.0,
    "liquidity_ratio_pct": 100.0,
    "most_locked": null,
    "average_exit_liquidity_score": 95.0,
    "timestamp": 1784021251.214393
  },
  {
    "positions": [
      {
        "protocol": "AaveV3",
        "position_usd": 0.0,
        "exit_fee_usd": 0.0,
        "net_exit_value_usd": 0.0,
        "estimated_exit_days": 0.0,
        "can_exit_in_target": true,
        "exit_liquidity_score": 80,
        "exit_label": "INSTANT",
        "market_depth_coverage_pct": 0.0,
        "bottleneck": "MARKET_DEPTH",
        "recommendation": "Immediate exit available. Depth covers 0% of position."
      }
    ],
    "instantly_exitable_usd": 0.0,
    "total_position_usd": 0.0,
    "liquidity_ratio_pct": 0.0,
    "most_locked": null,
    "average_exit_liquidity_score": 80.0,
    "timestamp": 1784021251.2202353
  },
  {
    "positions": [
      {
        "protocol": "X",
        "position_usd": 50000.0,
        "exit_fee_usd": 0.0,
        "net_exit_value_usd": 50000.0,
        "estimated_exit_days": 10.0,
        "can_exit_in_target": false,
        "exit_liquidity_score": 50,
        "exit_label": "SLOW",
        "market_depth_coverage_pct": 200.0,
        "bottleneck": "DAILY_LIMIT",
        "recommendation": "Exit takes 10d (>target 3d). Reduce position or wait."
      }
    ],
    "instantly_exitable_usd": 0,
    "total_position_usd": 50000.0,
    "liquidity_ratio_pct": 0.0,
    "most_locked": "X",
    "average_exit_liquidity_score": 50.0,
    "timestamp": 1784021251.226125
  },
  {
    "positions": [
      {
        "protocol": "X",
        "position_usd": 50000.0,
        "exit_fee_usd": 0.0,
        "net_exit_value_usd": 50000.0,
        "estimated_exit_days": 10.0,
        "can_exit_in_target": true,
        "exit_liquidity_score": 75,
        "exit_label": "MODERATE",
        "market_depth_coverage_pct": 200.0,
        "bottleneck": "DAILY_LIMIT",
        "recommendation": "1-15d exit window. Queue: 50000 USD ahead."
      }
    ],
    "instantly_exitable_usd": 0,
    "total_position_usd": 50000.0,
    "liquidity_ratio_pct": 0.0,
    "most_locked": "X",
    "average_exit_liquidity_score": 75.0,
    "timestamp": 1784021251.2301378
  },
  {
    "positions": [
      {
        "protocol": "X",
        "position_usd": 50000.0,
        "exit_fee_usd": 0.0,
        "net_exit_value_usd": 50000.0,
        "estimated_exit_days": 10.0,
        "can_exit_in_target": false,
        "exit_liquidity_score": 50,
        "exit_label": "SLOW",
        "market_depth_coverage_pct": 200.0,
        "bottleneck": "DAILY_LIMIT",
        "recommendation": "Exit takes 10d (>target 7d). Reduce position or wait."
      }
    ],
    "instantly_exitable_usd": 0,
    "total_position_usd": 50000.0,
    "liquidity_ratio_pct": 0.0,
    "most_locked": "X",
    "average_exit_liquidity_score": 50.0,
    "timestamp": 1784021251.2358234
  },
  {
    "positions": [
      {
        "protocol": "AaveV3",
        "position_usd": 50000.0,
        "exit_fee_usd": 0.0,
        "net_exit_value_usd": 50000.0,
        "estimated_exit_days": 0.0,
        "can_exit_in_target": true,
        "exit_liquidity_score": 100,
        "exit_label": "INSTANT",
        "market_depth_coverage_pct": 200.0,
        "bottleneck": null,
        "recommendation": "Immediate exit available. Depth covers 200% of position."
      }
    ],
    "instantly_exitable_usd": 50000.0,
    "total_position_usd": 50000.0,
    "liquidity_ratio_pct": 100.0,
    "most_locked": null,
    "average_exit_liquidity_score": 100.0,
    "timestamp": 1784021251.2417524
  },
  {
    "positions": [
      {
        "protocol": "Aave",
        "position_usd": 50000.0,
        "exit_fee_usd": 0.0,
        "net_exit_value_usd": 50000.0,
        "estimated_exit_days": 0.0,
        "can_exit_in_target": true,
        "exit_liquidity_score": 100,
        "exit_label": "INSTANT",
        "market_depth_coverage_pct": 400.0,
        "bottleneck": null,
        "recommendation": "Immediate exit available. Depth covers 400% of position."
      }
    ],
    "instantly_exitable_usd": 50000.0,
    "total_position_usd": 50000.0,
    "liquidity_ratio_pct": 100.0,
    "most_locked": null,
    "average_exit_liquidity_score": 100.0,
    "timestamp": 1784021251.2492075
  },
  {
    "positions": [
      {
        "protocol": "Aave",
        "position_usd": 50000.0,
        "exit_fee_usd": 0.0,
        "net_exit_value_usd": 50000.0,
        "estimated_exit_days": 0.0,
        "can_exit_in_target": true,
        "exit_liquidity_score": 100,
        "exit_label": "INSTANT",
        "market_depth_coverage_pct": 400.0,
        "bottleneck": null,
        "recommendation": "Immediate exit available. Depth covers 400% of position."
      }
    ],
    "instantly_exitable_usd": 50000.0,
    "total_position_usd": 50000.0,
    "liquidity_ratio_pct": 100.0,
    "most_locked": null,
    "average_exit_liquidity_score": 100.0,
    "timestamp": 1784021251.254844
  },
  {
    "positions": [
      {
        "protocol": "Aave",
        "position_usd": 50000.0,
        "exit_fee_usd": 0.0,
        "net_exit_value_usd": 50000.0,
        "estimated_exit_days": 0.0,
        "can_exit_in_target": true,
        "exit_liquidity_score": 100,
        "exit_label": "INSTANT",
        "market_depth_coverage_pct": 400.0,
        "bottleneck": null,
        "recommendation": "Immediate exit available. Depth covers 400% of position."
      }
    ],
    "instantly_exitable_usd": 50000.0,
    "total_position_usd": 50000.0,
    "liquidity_ratio_pct": 100.0,
    "most_locked": null,
    "average_exit_liquidity_score": 100.0,
    "timestamp": 1784021251.2607138
  },
  {
    "positions": [
      {
        "protocol": "Aave",
        "position_usd": 50000.0,
        "exit_fee_usd": 0.0,
        "net_exit_value_usd": 50000.0,
        "estimated_exit_days": 0.0,
        "can_exit_in_target": true,
        "exit_liquidity_score": 100,
        "exit_label": "INSTANT",
        "market_depth_coverage_pct": 400.0,
        "bottleneck": null,
        "recommendation": "Immediate exit available. Depth covers 400% of position."
      }
    ],
    "instantly_exitable_usd": 50000.0,
    "total_position_usd": 50000.0,
    "liquidity_ratio_pct": 100.0,
    "most_locked": null,
    "average_exit_liquidity_score": 100.0,
    "timestamp": 1784021251.2676072
  },
  {
    "positions": [
      {
        "protocol": "Aave",
        "position_usd": 50000.0,
        "exit_fee_usd": 0.0,
        "net_exit_value_usd": 50000.0,
        "estimated_exit_days": 0.0,
        "can_exit_in_target": true,
        "exit_liquidity_score": 100,
        "exit_label": "INSTANT",
        "market_depth_coverage_pct": 400.0,
        "bottleneck": null,
        "recommendation": "Immediate exit available. Depth covers 400% of position."
      }
    ],
    "instantly_exitable_usd": 50000.0,
    "total_position_usd": 50000.0,
    "liquidity_ratio_pct": 100.0,
    "most_locked": null,
    "average_exit_liquidity_score": 100.0,
    "timestamp": 1784021251.2728693
  },
  {
    "positions": [
      {
        "protocol": "Aave",
        "position_usd": 50000.0,
        "exit_fee_usd": 0.0,
        "net_exit_value_usd": 50000.0,
        "estimated_exit_days": 0.0,
        "can_exit_in_target": true,
        "exit_liquidity_score": 100,
        "exit_label": "INSTANT",
        "market_depth_coverage_pct": 400.0,
        "bottleneck": null,
        "recommendation": "Immediate exit available. Depth covers 400% of position."
      }
    ],
    "instantly_exitable_usd": 50000.0,
    "total_position_usd": 50000.0,
    "liquidity_ratio_pct": 100.0,
    "most_locked": null,
    "average_exit_liquidity_score": 100.0,
    "timestamp": 1784021251.2781236
  },
  {
    "positions": [
      {
        "protocol": "A",
        "position_usd": 50000.0,
        "exit_fee_usd": 0.0,
        "net_exit_value_usd": 50000.0,
        "estimated_exit_days": 30.0,
        "can_exit_in_target": false,
        "exit_liquidity_score": 40,
        "exit_label": "LOCKED",
        "market_depth_coverage_pct": 200.0,
        "bottleneck": "LOCK_UP",
        "recommendation": "Locked for 30d. Plan around lock expiry."
      },
      {
        "protocol": "B",
        "position_usd": 50000.0,
        "exit_fee_usd": 0.0,
        "net_exit_value_usd": 50000.0,
        "estimated_exit_days": 60.0,
        "can_exit_in_target": false,
        "exit_liquidity_score": 32,
        "exit_label": "LOCKED",
        "market_depth_coverage_pct": 200.0,
        "bottleneck": "LOCK_UP",
        "recommendation": "Locked for 60d. Plan around lock expiry."
      }
    ],
    "instantly_exitable_usd": 0,
    "total_position_usd": 100000.0,
    "liquidity_ratio_pct": 0.0,
    "most_locked": "B",
    "average_exit_liquidity_score": 36.0,
    "timestamp": 1784021251.3849318
  },
  {
    "positions": [
      {
        "protocol": "X",
        "position_usd": 10000.0,
        "exit_fee_usd": 0.0,
        "net_exit_value_usd": 10000.0,
        "estimated_exit_days": 0.0,
        "can_exit_in_target": true,
        "exit_liquidity_score": 80,
        "exit_label": "INSTANT",
        "market_depth_coverage_pct": 0.0,
        "bottleneck": "MARKET_DEPTH",
        "recommendation": "Immediate exit available. Depth covers 0% of position."
      }
    ],
    "instantly_exitable_usd": 10000.0,
    "total_position_usd": 10000.0,
    "liquidity_ratio_pct": 100.0,
    "most_locked": null,
    "average_exit_liquidity_score": 80.0,
    "timestamp": 1784021251.3908749
  },
  {
    "positions": [
      {
        "protocol": "Short",
        "position_usd": 10000.0,
        "exit_fee_usd": 0.0,
        "net_exit_value_usd": 10000.0,
        "estimated_exit_days": 10.0,
        "can_exit_in_target": false,
        "exit_liquidity_score": 40,
        "exit_label": "LOCKED",
        "market_depth_coverage_pct": 1000.0,
        "bottleneck": "LOCK_UP",
        "recommendation": "Locked for 10d. Plan around lock expiry."
      },
      {
        "protocol": "Long",
        "position_usd": 10000.0,
        "exit_fee_usd": 0.0,
        "net_exit_value_usd": 10000.0,
        "estimated_exit_days": 180.0,
        "can_exit_in_target": false,
        "exit_liquidity_score": 28,
        "exit_label": "LOCKED",
        "market_depth_coverage_pct": 1000.0,
        "bottleneck": "LOCK_UP",
        "recommendation": "Locked for 180d. Plan around lock expiry."
      }
    ],
    "instantly_exitable_usd": 0,
    "total_position_usd": 20000.0,
    "liquidity_ratio_pct": 0.0,
    "most_locked": "Long",
    "average_exit_liquidity_score": 34.0,
    "timestamp": 1784021251.3975716
  },
  {
    "positions": [
      {
        "protocol": "A",
        "position_usd": 30000.0,
        "exit_fee_usd": 0.0,
        "net_exit_value_usd": 30000.0,
        "estimated_exit_days": 0.0,
        "can_exit_in_target": true,
        "exit_liquidity_score": 100,
        "exit_label": "INSTANT",
        "market_depth_coverage_pct": 333.33333333333337,
        "bottleneck": null,
        "recommendation": "Immediate exit available. Depth covers 333% of position."
      },
      {
        "protocol": "B",
        "position_usd": 70000.0,
        "exit_fee_usd": 0.0,
        "net_exit_value_usd": 70000.0,
        "estimated_exit_days": 0.0,
        "can_exit_in_target": true,
        "exit_liquidity_score": 95,
        "exit_label": "INSTANT",
        "market_depth_coverage_pct": 142.85714285714286,
        "bottleneck": null,
        "recommendation": "Immediate exit available. Depth covers 143% of position."
      }
    ],
    "instantly_exitable_usd": 100000.0,
    "total_position_usd": 100000.0,
    "liquidity_ratio_pct": 100.0,
    "most_locked": null,
    "average_exit_liquidity_score": 97.5,
    "timestamp": 1784021251.404487
  },
  {
    "positions": [
      {
        "protocol": "AaveV3",
        "position_usd": 50000.0,
        "exit_fee_usd": 0.0,
        "net_exit_value_usd": 50000.0,
        "estimated_exit_days": 0.0,
        "can_exit_in_target": true,
        "exit_liquidity_score": 100,
        "exit_label": "INSTANT",
        "market_depth_coverage_pct": 200.0,
        "bottleneck": null,
        "recommendation": "Immediate exit available. Depth covers 200% of position."
      }
    ],
    "instantly_exitable_usd": 50000.0,
    "total_position_usd": 50000.0,
    "liquidity_ratio_pct": 100.0,
    "most_locked": null,
    "average_exit_liquidity_score": 100.0,
    "timestamp": 1784021251.409824
  },
  {
    "positions": [
      {
        "protocol": "A",
        "position_usd": 50000.0,
        "exit_fee_usd": 0.0,
        "net_exit_value_usd": 50000.0,
        "estimated_exit_days": 365.0,
        "can_exit_in_target": false,
        "exit_liquidity_score": 25,
        "exit_label": "LOCKED",
        "market_depth_coverage_pct": 200.0,
        "bottleneck": "LOCK_UP",
        "recommendation": "Locked for 365d. Plan around lock expiry."
      },
      {
        "protocol": "B",
        "position_usd": 50000.0,
        "exit_fee_usd": 0.0,
        "net_exit_value_usd": 50000.0,
        "estimated_exit_days": 0.0,
        "can_exit_in_target": true,
        "exit_liquidity_score": 100,
        "exit_label": "INSTANT",
        "market_depth_coverage_pct": 200.0,
        "bottleneck": null,
        "recommendation": "Immediate exit available. Depth covers 200% of position."
      }
    ],
    "instantly_exitable_usd": 50000.0,
    "total_position_usd": 100000.0,
    "liquidity_ratio_pct": 50.0,
    "most_locked": "A",
    "average_exit_liquidity_score": 62.5,
    "timestamp": 1784021251.4154158
  },
  {
    "positions": [
      {
        "protocol": "X",
        "position_usd": 50000.0,
        "exit_fee_usd": 0.0,
        "net_exit_value_usd": 50000.0,
        "estimated_exit_days": 1.0,
        "can_exit_in_target": true,
        "exit_liquidity_score": 90,
        "exit_label": "FAST",
        "market_depth_coverage_pct": 200.0,
        "bottleneck": "QUEUE",
        "recommendation": "Exit available quickly. Monitor queue size."
      }
    ],
    "instantly_exitable_usd": 0,
    "total_position_usd": 50000.0,
    "liquidity_ratio_pct": 0.0,
    "most_locked": "X",
    "average_exit_liquidity_score": 90.0,
    "timestamp": 1784021251.4207659
  },
  {
    "positions": [
      {
        "protocol": "AaveV3",
        "position_usd": 50000.0,
        "exit_fee_usd": 0.0,
        "net_exit_value_usd": 50000.0,
        "estimated_exit_days": 0.0,
        "can_exit_in_target": true,
        "exit_liquidity_score": 100,
        "exit_label": "INSTANT",
        "market_depth_coverage_pct": 200.0,
        "bottleneck": null,
        "recommendation": "Immediate exit available. Depth covers 200% of position."
      }
    ],
    "instantly_exitable_usd": 50000.0,
    "total_position_usd": 50000.0,
    "liquidity_ratio_pct": 100.0,
    "most_locked": null,
    "average_exit_liquidity_score": 100.0,
    "timestamp": 1784021251.4262993
  },
  {
    "positions": [
      {
        "protocol": "AaveV3",
        "position_usd": 0.0,
        "exit_fee_usd": 0.0,
        "net_exit_value_usd": 0.0,
        "estimated_exit_days": 0.0,
        "can_exit_in_target": true,
        "exit_liquidity_score": 80,
        "exit_label": "INSTANT",
        "market_depth_coverage_pct": 0.0,
        "bottleneck": "MARKET_DEPTH",
        "recommendation": "Immediate exit available. Depth covers 0% of position."
      }
    ],
    "instantly_exitable_usd": 0.0,
    "total_position_usd": 0.0,
    "liquidity_ratio_pct": 0.0,
    "most_locked": null,
    "average_exit_liquidity_score": 80.0,
    "timestamp": 1784021251.431559
  },
  {
    "positions": [],
    "instantly_exitable_usd": 0,
    "total_position_usd": 0,
    "liquidity_ratio_pct": 0.0,
    "most_locked": null,
    "average_exit_liquidity_score": 0.0,
    "timestamp": 1784194035.140456
  },
  {
    "positions": [],
    "instantly_exitable_usd": 0,
    "total_position_usd": 0,
    "liquidity_ratio_pct": 0.0,
    "most_locked": null,
    "average_exit_liquidity_score": 0.0,
    "timestamp": 1784194035.146012
  },
  {
    "positions": [],
    "instantly_exitable_usd": 0,
    "total_position_usd": 0,
    "liquidity_ratio_pct": 0.0,
    "most_locked": null,
    "average_exit_liquidity_score": 0.0,
    "timestamp": 1784194035.1514297
  },
  {
    "positions": [],
    "instantly_exitable_usd": 0,
    "total_position_usd": 0,
    "liquidity_ratio_pct": 0.0,
    "most_locked": null,
    "average_exit_liquidity_score": 0.0,
    "timestamp": 1784194035.156594
  },
  {
    "positions": [],
    "instantly_exitable_usd": 0,
    "total_position_usd": 0,
    "liquidity_ratio_pct": 0.0,
    "most_locked": null,
    "average_exit_liquidity_score": 0.0,
    "timestamp": 1784194035.1617162
  },
  {
    "positions": [],
    "instantly_exitable_usd": 0,
    "total_position_usd": 0,
    "liquidity_ratio_pct": 0.0,
    "most_locked": null,
    "average_exit_liquidity_score": 0.0,
    "timestamp": 1784194035.166688
  },
  {
    "positions": [],
    "instantly_exitable_usd": 0,
    "total_position_usd": 0,
    "liquidity_ratio_pct": 0.0,
    "most_locked": null,
    "average_exit_liquidity_score": 0.0,
    "timestamp": 1784194035.1714544
  },
  {
    "positions": [
      {
        "protocol": "Aave",
        "position_usd": 50000.0,
        "exit_fee_usd": 0.0,
        "net_exit_value_usd": 50000.0,
        "estimated_exit_days": 0.0,
        "can_exit_in_target": true,
        "exit_liquidity_score": 100,
        "exit_label": "INSTANT",
        "market_depth_coverage_pct": 400.0,
        "bottleneck": null,
        "recommendation": "Immediate exit available. Depth covers 400% of position."
      }
    ],
    "instantly_exitable_usd": 50000.0,
    "total_position_usd": 50000.0,
    "liquidity_ratio_pct": 100.0,
    "most_locked": null,
    "average_exit_liquidity_score": 100.0,
    "timestamp": 1784194035.1767454
  },
  {
    "positions": [
      {
        "protocol": "Aave",
        "position_usd": 50000.0,
        "exit_fee_usd": 0.0,
        "net_exit_value_usd": 50000.0,
        "estimated_exit_days": 0.0,
        "can_exit_in_target": true,
        "exit_liquidity_score": 100,
        "exit_label": "INSTANT",
        "market_depth_coverage_pct": 400.0,
        "bottleneck": null,
        "recommendation": "Immediate exit available. Depth covers 400% of position."
      }
    ],
    "instantly_exitable_usd": 50000.0,
    "total_position_usd": 50000.0,
    "liquidity_ratio_pct": 100.0,
    "most_locked": null,
    "average_exit_liquidity_score": 100.0,
    "timestamp": 1784194035.181702
  },
  {
    "positions": [
      {
        "protocol": "Aave",
        "position_usd": 50000.0,
        "exit_fee_usd": 0.0,
        "net_exit_value_usd": 50000.0,
        "estimated_exit_days": 0.0,
        "can_exit_in_target": true,
        "exit_liquidity_score": 100,
        "exit_label": "INSTANT",
        "market_depth_coverage_pct": 400.0,
        "bottleneck": null,
        "recommendation": "Immediate exit available. Depth covers 400% of position."
      }
    ],
    "instantly_exitable_usd": 50000.0,
    "total_position_usd": 50000.0,
    "liquidity_ratio_pct": 100.0,
    "most_locked": null,
    "average_exit_liquidity_score": 100.0,
    "timestamp": 1784194035.186705
  },
  {
    "positions": [
      {
        "protocol": "Aave",
        "position_usd": 50000.0,
        "exit_fee_usd": 0.0,
        "net_exit_value_usd": 50000.0,
        "estimated_exit_days": 0.0,
        "can_exit_in_target": true,
        "exit_liquidity_score": 100,
        "exit_label": "INSTANT",
        "market_depth_coverage_pct": 400.0,
        "bottleneck": null,
        "recommendation": "Immediate exit available. Depth covers 400% of position."
      }
    ],
    "instantly_exitable_usd": 50000.0,
    "total_position_usd": 50000.0,
    "liquidity_ratio_pct": 100.0,
    "most_locked": null,
    "average_exit_liquidity_score": 100.0,
    "timestamp": 1784194035.1915016
  },
  {
    "positions": [
      {
        "protocol": "Aave",
        "position_usd": 50000.0,
        "exit_fee_usd": 0.0,
        "net_exit_value_usd": 50000.0,
        "estimated_exit_days": 0.0,
        "can_exit_in_target": true,
        "exit_liquidity_score": 100,
        "exit_label": "INSTANT",
        "market_depth_coverage_pct": 400.0,
        "bottleneck": null,
        "recommendation": "Immediate exit available. Depth covers 400% of position."
      }
    ],
    "instantly_exitable_usd": 50000.0,
    "total_position_usd": 50000.0,
    "liquidity_ratio_pct": 100.0,
    "most_locked": null,
    "average_exit_liquidity_score": 100.0,
    "timestamp": 1784194035.1962698
  },
  {
    "positions": [
      {
        "protocol": "Aave",
        "position_usd": 50000.0,
        "exit_fee_usd": 0.0,
        "net_exit_value_usd": 50000.0,
        "estimated_exit_days": 0.0,
        "can_exit_in_target": true,
        "exit_liquidity_score": 100,
        "exit_label": "INSTANT",
        "market_depth_coverage_pct": 400.0,
        "bottleneck": null,
        "recommendation": "Immediate exit available. Depth covers 400% of position."
      }
    ],
    "instantly_exitable_usd": 50000.0,
    "total_position_usd": 50000.0,
    "liquidity_ratio_pct": 100.0,
    "most_locked": null,
    "average_exit_liquidity_score": 100.0,
    "timestamp": 1784194035.2011092
  },
  {
    "positions": [
      {
        "protocol": "Aave",
        "position_usd": 50000.0,
        "exit_fee_usd": 0.0,
        "net_exit_value_usd": 50000.0,
        "estimated_exit_days": 0.0,
        "can_exit_in_target": true,
        "exit_liquidity_score": 100,
        "exit_label": "INSTANT",
        "market_depth_coverage_pct": 400.0,
        "bottleneck": null,
        "recommendation": "Immediate exit available. Depth covers 400% of position."
      }
    ],
    "instantly_exitable_usd": 50000.0,
    "total_position_usd": 50000.0,
    "liquidity_ratio_pct": 100.0,
    "most_locked": null,
    "average_exit_liquidity_score": 100.0,
    "timestamp": 1784194035.2060473
  },
  {
    "positions": [
      {
        "protocol": "Aave",
        "position_usd": 50000.0,
        "exit_fee_usd": 0.0,
        "net_exit_value_usd": 50000.0,
        "estimated_exit_days": 0.0,
        "can_exit_in_target": true,
        "exit_liquidity_score": 100,
        "exit_label": "INSTANT",
        "market_depth_coverage_pct": 400.0,
        "bottleneck": null,
        "recommendation": "Immediate exit available. Depth covers 400% of position."
      }
    ],
    "instantly_exitable_usd": 50000.0,
    "total_position_usd": 50000.0,
    "liquidity_ratio_pct": 100.0,
    "most_locked": null,
    "average_exit_liquidity_score": 100.0,
    "timestamp": 1784194035.2111464
  },
  {
    "positions": [
      {
        "protocol": "Aave",
        "position_usd": 50000.0,
        "exit_fee_usd": 0.0,
        "net_exit_value_usd": 50000.0,
        "estimated_exit_days": 0.0,
        "can_exit_in_target": true,
        "exit_liquidity_score": 100,
        "exit_label": "INSTANT",
        "market_depth_coverage_pct": 400.0,
        "bottleneck": null,
        "recommendation": "Immediate exit available. Depth covers 400% of position."
      }
    ],
    "instantly_exitable_usd": 50000.0,
    "total_position_usd": 50000.0,
    "liquidity_ratio_pct": 100.0,
    "most_locked": null,
    "average_exit_liquidity_score": 100.0,
    "timestamp": 1784194035.2162519
  },
  {
    "positions": [
      {
        "protocol": "Maple",
        "position_usd": 30000.0,
        "exit_fee_usd": 0.0,
        "net_exit_value_usd": 30000.0,
        "estimated_exit_days": 90.0,
        "can_exit_in_target": false,
        "exit_liquidity_score": 17,
        "exit_label": "LOCKED",
        "market_depth_coverage_pct": 33.33333333333333,
        "bottleneck": "LOCK_UP",
        "recommendation": "Locked for 90d. Plan around lock expiry."
      }
    ],
    "instantly_exitable_usd": 0,
    "total_position_usd": 30000.0,
    "liquidity_ratio_pct": 0.0,
    "most_locked": "Maple",
    "average_exit_liquidity_score": 17.0,
    "timestamp": 1784194035.221202
  },
  {
    "positions": [
      {
        "protocol": "Maple",
        "position_usd": 30000.0,
        "exit_fee_usd": 0.0,
        "net_exit_value_usd": 30000.0,
        "estimated_exit_days": 90.0,
        "can_exit_in_target": false,
        "exit_liquidity_score": 17,
        "exit_label": "LOCKED",
        "market_depth_coverage_pct": 33.33333333333333,
        "bottleneck": "LOCK_UP",
        "recommendation": "Locked for 90d. Plan around lock expiry."
      }
    ],
    "instantly_exitable_usd": 0,
    "total_position_usd": 30000.0,
    "liquidity_ratio_pct": 0.0,
    "most_locked": "Maple",
    "average_exit_liquidity_score": 17.0,
    "timestamp": 1784194035.226152
  },
  {
    "positions": [
      {
        "protocol": "Maple",
        "position_usd": 30000.0,
        "exit_fee_usd": 0.0,
        "net_exit_value_usd": 30000.0,
        "estimated_exit_days": 90.0,
        "can_exit_in_target": false,
        "exit_liquidity_score": 17,
        "exit_label": "LOCKED",
        "market_depth_coverage_pct": 33.33333333333333,
        "bottleneck": "LOCK_UP",
        "recommendation": "Locked for 90d. Plan around lock expiry."
      }
    ],
    "instantly_exitable_usd": 0,
    "total_position_usd": 30000.0,
    "liquidity_ratio_pct": 0.0,
    "most_locked": "Maple",
    "average_exit_liquidity_score": 17.0,
    "timestamp": 1784194035.2308762
  },
  {
    "positions": [
      {
        "protocol": "Maple",
        "position_usd": 30000.0,
        "exit_fee_usd": 0.0,
        "net_exit_value_usd": 30000.0,
        "estimated_exit_days": 90.0,
        "can_exit_in_target": false,
        "exit_liquidity_score": 17,
        "exit_label": "LOCKED",
        "market_depth_coverage_pct": 33.33333333333333,
        "bottleneck": "LOCK_UP",
        "recommendation": "Locked for 90d. Plan around lock expiry."
      }
    ],
    "instantly_exitable_usd": 0,
    "total_position_usd": 30000.0,
    "liquidity_ratio_pct": 0.0,
    "most_locked": "Maple",
    "average_exit_liquidity_score": 17.0,
    "timestamp": 1784194035.2355332
  },
  {
    "positions": [
      {
        "protocol": "Maple",
        "position_usd": 30000.0,
        "exit_fee_usd": 0.0,
        "net_exit_value_usd": 30000.0,
        "estimated_exit_days": 90.0,
        "can_exit_in_target": false,
        "exit_liquidity_score": 17,
        "exit_label": "LOCKED",
        "market_depth_coverage_pct": 33.33333333333333,
        "bottleneck": "LOCK_UP",
        "recommendation": "Locked for 90d. Plan around lock expiry."
      }
    ],
    "instantly_exitable_usd": 0,
    "total_position_usd": 30000.0,
    "liquidity_ratio_pct": 0.0,
    "most_locked": "Maple",
    "average_exit_liquidity_score": 17.0,
    "timestamp": 1784194035.240315
  },
  {
    "positions": [
      {
        "protocol": "Maple",
        "position_usd": 30000.0,
        "exit_fee_usd": 0.0,
        "net_exit_value_usd": 30000.0,
        "estimated_exit_days": 90.0,
        "can_exit_in_target": false,
        "exit_liquidity_score": 17,
        "exit_label": "LOCKED",
        "market_depth_coverage_pct": 33.33333333333333,
        "bottleneck": "LOCK_UP",
        "recommendation": "Locked for 90d. Plan around lock expiry."
      }
    ],
    "instantly_exitable_usd": 0,
    "total_position_usd": 30000.0,
    "liquidity_ratio_pct": 0.0,
    "most_locked": "Maple",
    "average_exit_liquidity_score": 17.0,
    "timestamp": 1784194035.2447731
  },
  {
    "positions": [
      {
        "protocol": "Maple",
        "position_usd": 30000.0,
        "exit_fee_usd": 0.0,
        "net_exit_value_usd": 30000.0,
        "estimated_exit_days": 90.0,
        "can_exit_in_target": false,
        "exit_liquidity_score": 17,
        "exit_label": "LOCKED",
        "market_depth_coverage_pct": 33.33333333333333,
        "bottleneck": "LOCK_UP",
        "recommendation": "Locked for 90d. Plan around lock expiry."
      }
    ],
    "instantly_exitable_usd": 0,
    "total_position_usd": 30000.0,
    "liquidity_ratio_pct": 0.0,
    "most_locked": "Maple",
    "average_exit_liquidity_score": 17.0,
    "timestamp": 1784194035.249524
  },
  {
    "positions": [
      {
        "protocol": "AaveV3",
        "position_usd": 100000.0,
        "exit_fee_usd": 500.0,
        "net_exit_value_usd": 99500.0,
        "estimated_exit_days": 0.0,
        "can_exit_in_target": true,
        "exit_liquidity_score": 95,
        "exit_label": "INSTANT",
        "market_depth_coverage_pct": 100.0,
        "bottleneck": null,
        "recommendation": "Immediate exit available. Depth covers 100% of position."
      }
    ],
    "instantly_exitable_usd": 100000.0,
    "total_position_usd": 100000.0,
    "liquidity_ratio_pct": 100.0,
    "most_locked": null,
    "average_exit_liquidity_score": 95.0,
    "timestamp": 1784194035.254393
  },
  {
    "positions": [
      {
        "protocol": "AaveV3",
        "position_usd": 50000.0,
        "exit_fee_usd": 2500.0,
        "net_exit_value_usd": 47500.0,
        "estimated_exit_days": 0.0,
        "can_exit_in_target": true,
        "exit_liquidity_score": 100,
        "exit_label": "INSTANT",
        "market_depth_coverage_pct": 200.0,
        "bottleneck": null,
        "recommendation": "Immediate exit available. Depth covers 200% of position."
      }
    ],
    "instantly_exitable_usd": 50000.0,
    "total_position_usd": 50000.0,
    "liquidity_ratio_pct": 100.0,
    "most_locked": null,
    "average_exit_liquidity_score": 100.0,
    "timestamp": 1784194035.2591305
  },
  {
    "positions": [
      {
        "protocol": "AaveV3",
        "position_usd": 10000.0,
        "exit_fee_usd": 200.0,
        "net_exit_value_usd": 9800.0,
        "estimated_exit_days": 0.0,
        "can_exit_in_target": true,
        "exit_liquidity_score": 100,
        "exit_label": "INSTANT",
        "market_depth_coverage_pct": 1000.0,
        "bottleneck": null,
        "recommendation": "Immediate exit available. Depth covers 1000% of position."
      }
    ],
    "instantly_exitable_usd": 10000.0,
    "total_position_usd": 10000.0,
    "liquidity_ratio_pct": 100.0,
    "most_locked": null,
    "average_exit_liquidity_score": 100.0,
    "timestamp": 1784194035.2640035
  },
  {
    "positions": [
      {
        "protocol": "AaveV3",
        "position_usd": 50000.0,
        "exit_fee_usd": 0.0,
        "net_exit_value_usd": 50000.0,
        "estimated_exit_days": 0.0,
        "can_exit_in_target": true,
        "exit_liquidity_score": 100,
        "exit_label": "INSTANT",
        "market_depth_coverage_pct": 200.0,
        "bottleneck": null,
        "recommendation": "Immediate exit available. Depth covers 200% of position."
      }
    ],
    "instantly_exitable_usd": 50000.0,
    "total_position_usd": 50000.0,
    "liquidity_ratio_pct": 100.0,
    "most_locked": null,
    "average_exit_liquidity_score": 100.0,
    "timestamp": 1784194035.26874
  },
  {
    "positions": [
      {
        "protocol": "Queue",
        "position_usd": 30000.0,
        "exit_fee_usd": 150.0,
        "net_exit_value_usd": 29850.0,
        "estimated_exit_days": 8.0,
        "can_exit_in_target": false,
        "exit_liquidity_score": 30,
        "exit_label": "SLOW",
        "market_depth_coverage_pct": 16.666666666666664,
        "bottleneck": "DAILY_LIMIT",
        "recommendation": "Exit takes 8d (>target 7d). Reduce position or wait."
      }
    ],
    "instantly_exitable_usd": 0,
    "total_position_usd": 30000.0,
    "liquidity_ratio_pct": 0.0,
    "most_locked": "Queue",
    "average_exit_liquidity_score": 30.0,
    "timestamp": 1784194035.2739534
  },
  {
    "positions": [
      {
        "protocol": "Queue",
        "position_usd": 30000.0,
        "exit_fee_usd": 150.0,
        "net_exit_value_usd": 29850.0,
        "estimated_exit_days": 8.0,
        "can_exit_in_target": false,
        "exit_liquidity_score": 30,
        "exit_label": "SLOW",
        "market_depth_coverage_pct": 16.666666666666664,
        "bottleneck": "DAILY_LIMIT",
        "recommendation": "Exit takes 8d (>target 7d). Reduce position or wait."
      }
    ],
    "instantly_exitable_usd": 0,
    "total_position_usd": 30000.0,
    "liquidity_ratio_pct": 0.0,
    "most_locked": "Queue",
    "average_exit_liquidity_score": 30.0,
    "timestamp": 1784194035.278973
  },
  {
    "positions": [
      {
        "protocol": "Queue",
        "position_usd": 30000.0,
        "exit_fee_usd": 150.0,
        "net_exit_value_usd": 29850.0,
        "estimated_exit_days": 8.0,
        "can_exit_in_target": false,
        "exit_liquidity_score": 30,
        "exit_label": "SLOW",
        "market_depth_coverage_pct": 16.666666666666664,
        "bottleneck": "DAILY_LIMIT",
        "recommendation": "Exit takes 8d (>target 7d). Reduce position or wait."
      }
    ],
    "instantly_exitable_usd": 0,
    "total_position_usd": 30000.0,
    "liquidity_ratio_pct": 0.0,
    "most_locked": "Queue",
    "average_exit_liquidity_score": 30.0,
    "timestamp": 1784194035.2839522
  },
  {
    "positions": [
      {
        "protocol": "Queue",
        "position_usd": 30000.0,
        "exit_fee_usd": 150.0,
        "net_exit_value_usd": 29850.0,
        "estimated_exit_days": 8.0,
        "can_exit_in_target": false,
        "exit_liquidity_score": 30,
        "exit_label": "SLOW",
        "market_depth_coverage_pct": 16.666666666666664,
        "bottleneck": "DAILY_LIMIT",
        "recommendation": "Exit takes 8d (>target 7d). Reduce position or wait."
      }
    ],
    "instantly_exitable_usd": 0,
    "total_position_usd": 30000.0,
    "liquidity_ratio_pct": 0.0,
    "most_locked": "Queue",
    "average_exit_liquidity_score": 30.0,
    "timestamp": 1784194035.2889404
  },
  {
    "positions": [
      {
        "protocol": "Queue",
        "position_usd": 30000.0,
        "exit_fee_usd": 150.0,
        "net_exit_value_usd": 29850.0,
        "estimated_exit_days": 8.0,
        "can_exit_in_target": false,
        "exit_liquidity_score": 30,
        "exit_label": "SLOW",
        "market_depth_coverage_pct": 16.666666666666664,
        "bottleneck": "DAILY_LIMIT",
        "recommendation": "Exit takes 8d (>target 7d). Reduce position or wait."
      }
    ],
    "instantly_exitable_usd": 0,
    "total_position_usd": 30000.0,
    "liquidity_ratio_pct": 0.0,
    "most_locked": "Queue",
    "average_exit_liquidity_score": 30.0,
    "timestamp": 1784194035.2943344
  },
  {
    "positions": [
      {
        "protocol": "X",
        "position_usd": 50000.0,
        "exit_fee_usd": 0.0,
        "net_exit_value_usd": 50000.0,
        "estimated_exit_days": 1.0,
        "can_exit_in_target": true,
        "exit_liquidity_score": 90,
        "exit_label": "FAST",
        "market_depth_coverage_pct": 200.0,
        "bottleneck": "QUEUE",
        "recommendation": "Exit available quickly. Monitor queue size."
      }
    ],
    "instantly_exitable_usd": 0,
    "total_position_usd": 50000.0,
    "liquidity_ratio_pct": 0.0,
    "most_locked": "X",
    "average_exit_liquidity_score": 90.0,
    "timestamp": 1784194035.2979827
  },
  {
    "positions": [
      {
        "protocol": "Aave",
        "position_usd": 50000.0,
        "exit_fee_usd": 0.0,
        "net_exit_value_usd": 50000.0,
        "estimated_exit_days": 0.0,
        "can_exit_in_target": true,
        "exit_liquidity_score": 100,
        "exit_label": "INSTANT",
        "market_depth_coverage_pct": 400.0,
        "bottleneck": null,
        "recommendation": "Immediate exit available. Depth covers 400% of position."
      },
      {
        "protocol": "Maple",
        "position_usd": 30000.0,
        "exit_fee_usd": 0.0,
        "net_exit_value_usd": 30000.0,
        "estimated_exit_days": 90.0,
        "can_exit_in_target": false,
        "exit_liquidity_score": 17,
        "exit_label": "LOCKED",
        "market_depth_coverage_pct": 33.33333333333333,
        "bottleneck": "LOCK_UP",
        "recommendation": "Locked for 90d. Plan around lock expiry."
      },
      {
        "protocol": "Queue",
        "position_usd": 30000.0,
        "exit_fee_usd": 150.0,
        "net_exit_value_usd": 29850.0,
        "estimated_exit_days": 8.0,
        "can_exit_in_target": false,
        "exit_liquidity_score": 30,
        "exit_label": "SLOW",
        "market_depth_coverage_pct": 16.666666666666664,
        "bottleneck": "DAILY_LIMIT",
        "recommendation": "Exit takes 8d (>target 7d). Reduce position or wait."
      }
    ],
    "instantly_exitable_usd": 50000.0,
    "total_position_usd": 110000.0,
    "liquidity_ratio_pct": 45.45454545454545,
    "most_locked": "Maple",
    "average_exit_liquidity_score": 49.0,
    "timestamp": 1784194035.303123
  },
  {
    "positions": [
      {
        "protocol": "Aave",
        "position_usd": 50000.0,
        "exit_fee_usd": 0.0,
        "net_exit_value_usd": 50000.0,
        "estimated_exit_days": 0.0,
        "can_exit_in_target": true,
        "exit_liquidity_score": 100,
        "exit_label": "INSTANT",
        "market_depth_coverage_pct": 400.0,
        "bottleneck": null,
        "recommendation": "Immediate exit available. Depth covers 400% of position."
      },
      {
        "protocol": "Maple",
        "position_usd": 30000.0,
        "exit_fee_usd": 0.0,
        "net_exit_value_usd": 30000.0,
        "estimated_exit_days": 90.0,
        "can_exit_in_target": false,
        "exit_liquidity_score": 17,
        "exit_label": "LOCKED",
        "market_depth_coverage_pct": 33.33333333333333,
        "bottleneck": "LOCK_UP",
        "recommendation": "Locked for 90d. Plan around lock expiry."
      },
      {
        "protocol": "Queue",
        "position_usd": 30000.0,
        "exit_fee_usd": 150.0,
        "net_exit_value_usd": 29850.0,
        "estimated_exit_days": 8.0,
        "can_exit_in_target": false,
        "exit_liquidity_score": 30,
        "exit_label": "SLOW",
        "market_depth_coverage_pct": 16.666666666666664,
        "bottleneck": "DAILY_LIMIT",
        "recommendation": "Exit takes 8d (>target 7d). Reduce position or wait."
      }
    ],
    "instantly_exitable_usd": 50000.0,
    "total_position_usd": 110000.0,
    "liquidity_ratio_pct": 45.45454545454545,
    "most_locked": "Maple",
    "average_exit_liquidity_score": 49.0,
    "timestamp": 1784194035.307997
  },
  {
    "positions": [
      {
        "protocol": "Aave",
        "position_usd": 50000.0,
        "exit_fee_usd": 0.0,
        "net_exit_value_usd": 50000.0,
        "estimated_exit_days": 0.0,
        "can_exit_in_target": true,
        "exit_liquidity_score": 100,
        "exit_label": "INSTANT",
        "market_depth_coverage_pct": 400.0,
        "bottleneck": null,
        "recommendation": "Immediate exit available. Depth covers 400% of position."
      },
      {
        "protocol": "Maple",
        "position_usd": 30000.0,
        "exit_fee_usd": 0.0,
        "net_exit_value_usd": 30000.0,
        "estimated_exit_days": 90.0,
        "can_exit_in_target": false,
        "exit_liquidity_score": 17,
        "exit_label": "LOCKED",
        "market_depth_coverage_pct": 33.33333333333333,
        "bottleneck": "LOCK_UP",
        "recommendation": "Locked for 90d. Plan around lock expiry."
      },
      {
        "protocol": "Queue",
        "position_usd": 30000.0,
        "exit_fee_usd": 150.0,
        "net_exit_value_usd": 29850.0,
        "estimated_exit_days": 8.0,
        "can_exit_in_target": false,
        "exit_liquidity_score": 30,
        "exit_label": "SLOW",
        "market_depth_coverage_pct": 16.666666666666664,
        "bottleneck": "DAILY_LIMIT",
        "recommendation": "Exit takes 8d (>target 7d). Reduce position or wait."
      }
    ],
    "instantly_exitable_usd": 50000.0,
    "total_position_usd": 110000.0,
    "liquidity_ratio_pct": 45.45454545454545,
    "most_locked": "Maple",
    "average_exit_liquidity_score": 49.0,
    "timestamp": 1784194035.3133311
  },
  {
    "positions": [
      {
        "protocol": "Aave",
        "position_usd": 50000.0,
        "exit_fee_usd": 0.0,
        "net_exit_value_usd": 50000.0,
        "estimated_exit_days": 0.0,
        "can_exit_in_target": true,
        "exit_liquidity_score": 100,
        "exit_label": "INSTANT",
        "market_depth_coverage_pct": 400.0,
        "bottleneck": null,
        "recommendation": "Immediate exit available. Depth covers 400% of position."
      },
      {
        "protocol": "Maple",
        "position_usd": 30000.0,
        "exit_fee_usd": 0.0,
        "net_exit_value_usd": 30000.0,
        "estimated_exit_days": 90.0,
        "can_exit_in_target": false,
        "exit_liquidity_score": 17,
        "exit_label": "LOCKED",
        "market_depth_coverage_pct": 33.33333333333333,
        "bottleneck": "LOCK_UP",
        "recommendation": "Locked for 90d. Plan around lock expiry."
      },
      {
        "protocol": "Queue",
        "position_usd": 30000.0,
        "exit_fee_usd": 150.0,
        "net_exit_value_usd": 29850.0,
        "estimated_exit_days": 8.0,
        "can_exit_in_target": false,
        "exit_liquidity_score": 30,
        "exit_label": "SLOW",
        "market_depth_coverage_pct": 16.666666666666664,
        "bottleneck": "DAILY_LIMIT",
        "recommendation": "Exit takes 8d (>target 7d). Reduce position or wait."
      }
    ],
    "instantly_exitable_usd": 50000.0,
    "total_position_usd": 110000.0,
    "liquidity_ratio_pct": 45.45454545454545,
    "most_locked": "Maple",
    "average_exit_liquidity_score": 49.0,
    "timestamp": 1784194035.318158
  },
  {
    "positions": [
      {
        "protocol": "Aave",
        "position_usd": 50000.0,
        "exit_fee_usd": 0.0,
        "net_exit_value_usd": 50000.0,
        "estimated_exit_days": 0.0,
        "can_exit_in_target": true,
        "exit_liquidity_score": 100,
        "exit_label": "INSTANT",
        "market_depth_coverage_pct": 400.0,
        "bottleneck": null,
        "recommendation": "Immediate exit available. Depth covers 400% of position."
      },
      {
        "protocol": "Maple",
        "position_usd": 30000.0,
        "exit_fee_usd": 0.0,
        "net_exit_value_usd": 30000.0,
        "estimated_exit_days": 90.0,
        "can_exit_in_target": false,
        "exit_liquidity_score": 17,
        "exit_label": "LOCKED",
        "market_depth_coverage_pct": 33.33333333333333,
        "bottleneck": "LOCK_UP",
        "recommendation": "Locked for 90d. Plan around lock expiry."
      },
      {
        "protocol": "Queue",
        "position_usd": 30000.0,
        "exit_fee_usd": 150.0,
        "net_exit_value_usd": 29850.0,
        "estimated_exit_days": 8.0,
        "can_exit_in_target": false,
        "exit_liquidity_score": 30,
        "exit_label": "SLOW",
        "market_depth_coverage_pct": 16.666666666666664,
        "bottleneck": "DAILY_LIMIT",
        "recommendation": "Exit takes 8d (>target 7d). Reduce position or wait."
      }
    ],
    "instantly_exitable_usd": 50000.0,
    "total_position_usd": 110000.0,
    "liquidity_ratio_pct": 45.45454545454545,
    "most_locked": "Maple",
    "average_exit_liquidity_score": 49.0,
    "timestamp": 1784194035.3232465
  },
  {
    "positions": [
      {
        "protocol": "Aave",
        "position_usd": 50000.0,
        "exit_fee_usd": 0.0,
        "net_exit_value_usd": 50000.0,
        "estimated_exit_days": 0.0,
        "can_exit_in_target": true,
        "exit_liquidity_score": 100,
        "exit_label": "INSTANT",
        "market_depth_coverage_pct": 400.0,
        "bottleneck": null,
        "recommendation": "Immediate exit available. Depth covers 400% of position."
      },
      {
        "protocol": "Maple",
        "position_usd": 30000.0,
        "exit_fee_usd": 0.0,
        "net_exit_value_usd": 30000.0,
        "estimated_exit_days": 90.0,
        "can_exit_in_target": false,
        "exit_liquidity_score": 17,
        "exit_label": "LOCKED",
        "market_depth_coverage_pct": 33.33333333333333,
        "bottleneck": "LOCK_UP",
        "recommendation": "Locked for 90d. Plan around lock expiry."
      },
      {
        "protocol": "Queue",
        "position_usd": 30000.0,
        "exit_fee_usd": 150.0,
        "net_exit_value_usd": 29850.0,
        "estimated_exit_days": 8.0,
        "can_exit_in_target": false,
        "exit_liquidity_score": 30,
        "exit_label": "SLOW",
        "market_depth_coverage_pct": 16.666666666666664,
        "bottleneck": "DAILY_LIMIT",
        "recommendation": "Exit takes 8d (>target 7d). Reduce position or wait."
      }
    ],
    "instantly_exitable_usd": 50000.0,
    "total_position_usd": 110000.0,
    "liquidity_ratio_pct": 45.45454545454545,
    "most_locked": "Maple",
    "average_exit_liquidity_score": 49.0,
    "timestamp": 1784194035.328457
  },
  {
    "positions": [
      {
        "protocol": "Aave",
        "position_usd": 50000.0,
        "exit_fee_usd": 0.0,
        "net_exit_value_usd": 50000.0,
        "estimated_exit_days": 0.0,
        "can_exit_in_target": true,
        "exit_liquidity_score": 100,
        "exit_label": "INSTANT",
        "market_depth_coverage_pct": 400.0,
        "bottleneck": null,
        "recommendation": "Immediate exit available. Depth covers 400% of position."
      },
      {
        "protocol": "Maple",
        "position_usd": 30000.0,
        "exit_fee_usd": 0.0,
        "net_exit_value_usd": 30000.0,
        "estimated_exit_days": 90.0,
        "can_exit_in_target": false,
        "exit_liquidity_score": 17,
        "exit_label": "LOCKED",
        "market_depth_coverage_pct": 33.33333333333333,
        "bottleneck": "LOCK_UP",
        "recommendation": "Locked for 90d. Plan around lock expiry."
      },
      {
        "protocol": "Queue",
        "position_usd": 30000.0,
        "exit_fee_usd": 150.0,
        "net_exit_value_usd": 29850.0,
        "estimated_exit_days": 8.0,
        "can_exit_in_target": false,
        "exit_liquidity_score": 30,
        "exit_label": "SLOW",
        "market_depth_coverage_pct": 16.666666666666664,
        "bottleneck": "DAILY_LIMIT",
        "recommendation": "Exit takes 8d (>target 7d). Reduce position or wait."
      }
    ],
    "instantly_exitable_usd": 50000.0,
    "total_position_usd": 110000.0,
    "liquidity_ratio_pct": 45.45454545454545,
    "most_locked": "Maple",
    "average_exit_liquidity_score": 49.0,
    "timestamp": 1784194035.3334198
  },
  {
    "positions": [
      {
        "protocol": "AaveV3",
        "position_usd": 50000.0,
        "exit_fee_usd": 0.0,
        "net_exit_value_usd": 50000.0,
        "estimated_exit_days": 0.0,
        "can_exit_in_target": true,
        "exit_liquidity_score": 100,
        "exit_label": "INSTANT",
        "market_depth_coverage_pct": 200.0,
        "bottleneck": null,
        "recommendation": "Immediate exit available. Depth covers 200% of position."
      }
    ],
    "instantly_exitable_usd": 50000.0,
    "total_position_usd": 50000.0,
    "liquidity_ratio_pct": 100.0,
    "most_locked": null,
    "average_exit_liquidity_score": 100.0,
    "timestamp": 1784194035.338322
  },
  {
    "positions": [
      {
        "protocol": "AaveV3",
        "position_usd": 100000.0,
        "exit_fee_usd": 0.0,
        "net_exit_value_usd": 100000.0,
        "estimated_exit_days": 0.0,
        "can_exit_in_target": true,
        "exit_liquidity_score": 80,
        "exit_label": "INSTANT",
        "market_depth_coverage_pct": 10.0,
        "bottleneck": "MARKET_DEPTH",
        "recommendation": "Immediate exit available. Depth covers 10% of position."
      }
    ],
    "instantly_exitable_usd": 100000.0,
    "total_position_usd": 100000.0,
    "liquidity_ratio_pct": 100.0,
    "most_locked": null,
    "average_exit_liquidity_score": 80.0,
    "timestamp": 1784194035.343265
  },
  {
    "positions": [
      {
        "protocol": "AaveV3",
        "position_usd": 50000.0,
        "exit_fee_usd": 0.0,
        "net_exit_value_usd": 50000.0,
        "estimated_exit_days": 0.0,
        "can_exit_in_target": true,
        "exit_liquidity_score": 95,
        "exit_label": "INSTANT",
        "market_depth_coverage_pct": 100.0,
        "bottleneck": null,
        "recommendation": "Immediate exit available. Depth covers 100% of position."
      }
    ],
    "instantly_exitable_usd": 50000.0,
    "total_position_usd": 50000.0,
    "liquidity_ratio_pct": 100.0,
    "most_locked": null,
    "average_exit_liquidity_score": 95.0,
    "timestamp": 1784194035.3482313
  },
  {
    "positions": [
      {
        "protocol": "AaveV3",
        "position_usd": 0.0,
        "exit_fee_usd": 0.0,
        "net_exit_value_usd": 0.0,
        "estimated_exit_days": 0.0,
        "can_exit_in_target": true,
        "exit_liquidity_score": 80,
        "exit_label": "INSTANT",
        "market_depth_coverage_pct": 0.0,
        "bottleneck": "MARKET_DEPTH",
        "recommendation": "Immediate exit available. Depth covers 0% of position."
      }
    ],
    "instantly_exitable_usd": 0.0,
    "total_position_usd": 0.0,
    "liquidity_ratio_pct": 0.0,
    "most_locked": null,
    "average_exit_liquidity_score": 80.0,
    "timestamp": 1784194035.3535974
  },
  {
    "positions": [
      {
        "protocol": "X",
        "position_usd": 50000.0,
        "exit_fee_usd": 0.0,
        "net_exit_value_usd": 50000.0,
        "estimated_exit_days": 10.0,
        "can_exit_in_target": false,
        "exit_liquidity_score": 50,
        "exit_label": "SLOW",
        "market_depth_coverage_pct": 200.0,
        "bottleneck": "DAILY_LIMIT",
        "recommendation": "Exit takes 10d (>target 3d). Reduce position or wait."
      }
    ],
    "instantly_exitable_usd": 0,
    "total_position_usd": 50000.0,
    "liquidity_ratio_pct": 0.0,
    "most_locked": "X",
    "average_exit_liquidity_score": 50.0,
    "timestamp": 1784194035.3590424
  },
  {
    "positions": [
      {
        "protocol": "X",
        "position_usd": 50000.0,
        "exit_fee_usd": 0.0,
        "net_exit_value_usd": 50000.0,
        "estimated_exit_days": 10.0,
        "can_exit_in_target": true,
        "exit_liquidity_score": 75,
        "exit_label": "MODERATE",
        "market_depth_coverage_pct": 200.0,
        "bottleneck": "DAILY_LIMIT",
        "recommendation": "1-15d exit window. Queue: 50000 USD ahead."
      }
    ],
    "instantly_exitable_usd": 0,
    "total_position_usd": 50000.0,
    "liquidity_ratio_pct": 0.0,
    "most_locked": "X",
    "average_exit_liquidity_score": 75.0,
    "timestamp": 1784194035.3628209
  },
  {
    "positions": [
      {
        "protocol": "X",
        "position_usd": 50000.0,
        "exit_fee_usd": 0.0,
        "net_exit_value_usd": 50000.0,
        "estimated_exit_days": 10.0,
        "can_exit_in_target": false,
        "exit_liquidity_score": 50,
        "exit_label": "SLOW",
        "market_depth_coverage_pct": 200.0,
        "bottleneck": "DAILY_LIMIT",
        "recommendation": "Exit takes 10d (>target 7d). Reduce position or wait."
      }
    ],
    "instantly_exitable_usd": 0,
    "total_position_usd": 50000.0,
    "liquidity_ratio_pct": 0.0,
    "most_locked": "X",
    "average_exit_liquidity_score": 50.0,
    "timestamp": 1784194035.3681746
  },
  {
    "positions": [
      {
        "protocol": "AaveV3",
        "position_usd": 50000.0,
        "exit_fee_usd": 0.0,
        "net_exit_value_usd": 50000.0,
        "estimated_exit_days": 0.0,
        "can_exit_in_target": true,
        "exit_liquidity_score": 100,
        "exit_label": "INSTANT",
        "market_depth_coverage_pct": 200.0,
        "bottleneck": null,
        "recommendation": "Immediate exit available. Depth covers 200% of position."
      }
    ],
    "instantly_exitable_usd": 50000.0,
    "total_position_usd": 50000.0,
    "liquidity_ratio_pct": 100.0,
    "most_locked": null,
    "average_exit_liquidity_score": 100.0,
    "timestamp": 1784194035.3737469
  },
  {
    "positions": [
      {
        "protocol": "Aave",
        "position_usd": 50000.0,
        "exit_fee_usd": 0.0,
        "net_exit_value_usd": 50000.0,
        "estimated_exit_days": 0.0,
        "can_exit_in_target": true,
        "exit_liquidity_score": 100,
        "exit_label": "INSTANT",
        "market_depth_coverage_pct": 400.0,
        "bottleneck": null,
        "recommendation": "Immediate exit available. Depth covers 400% of position."
      }
    ],
    "instantly_exitable_usd": 50000.0,
    "total_position_usd": 50000.0,
    "liquidity_ratio_pct": 100.0,
    "most_locked": null,
    "average_exit_liquidity_score": 100.0,
    "timestamp": 1784194035.3790185
  },
  {
    "positions": [
      {
        "protocol": "Aave",
        "position_usd": 50000.0,
        "exit_fee_usd": 0.0,
        "net_exit_value_usd": 50000.0,
        "estimated_exit_days": 0.0,
        "can_exit_in_target": true,
        "exit_liquidity_score": 100,
        "exit_label": "INSTANT",
        "market_depth_coverage_pct": 400.0,
        "bottleneck": null,
        "recommendation": "Immediate exit available. Depth covers 400% of position."
      }
    ],
    "instantly_exitable_usd": 50000.0,
    "total_position_usd": 50000.0,
    "liquidity_ratio_pct": 100.0,
    "most_locked": null,
    "average_exit_liquidity_score": 100.0,
    "timestamp": 1784194035.384434
  },
  {
    "positions": [
      {
        "protocol": "Aave",
        "position_usd": 50000.0,
        "exit_fee_usd": 0.0,
        "net_exit_value_usd": 50000.0,
        "estimated_exit_days": 0.0,
        "can_exit_in_target": true,
        "exit_liquidity_score": 100,
        "exit_label": "INSTANT",
        "market_depth_coverage_pct": 400.0,
        "bottleneck": null,
        "recommendation": "Immediate exit available. Depth covers 400% of position."
      }
    ],
    "instantly_exitable_usd": 50000.0,
    "total_position_usd": 50000.0,
    "liquidity_ratio_pct": 100.0,
    "most_locked": null,
    "average_exit_liquidity_score": 100.0,
    "timestamp": 1784194035.389742
  },
  {
    "positions": [
      {
        "protocol": "Aave",
        "position_usd": 50000.0,
        "exit_fee_usd": 0.0,
        "net_exit_value_usd": 50000.0,
        "estimated_exit_days": 0.0,
        "can_exit_in_target": true,
        "exit_liquidity_score": 100,
        "exit_label": "INSTANT",
        "market_depth_coverage_pct": 400.0,
        "bottleneck": null,
        "recommendation": "Immediate exit available. Depth covers 400% of position."
      }
    ],
    "instantly_exitable_usd": 50000.0,
    "total_position_usd": 50000.0,
    "liquidity_ratio_pct": 100.0,
    "most_locked": null,
    "average_exit_liquidity_score": 100.0,
    "timestamp": 1784194035.394955
  },
  {
    "positions": [
      {
        "protocol": "Aave",
        "position_usd": 50000.0,
        "exit_fee_usd": 0.0,
        "net_exit_value_usd": 50000.0,
        "estimated_exit_days": 0.0,
        "can_exit_in_target": true,
        "exit_liquidity_score": 100,
        "exit_label": "INSTANT",
        "market_depth_coverage_pct": 400.0,
        "bottleneck": null,
        "recommendation": "Immediate exit available. Depth covers 400% of position."
      }
    ],
    "instantly_exitable_usd": 50000.0,
    "total_position_usd": 50000.0,
    "liquidity_ratio_pct": 100.0,
    "most_locked": null,
    "average_exit_liquidity_score": 100.0,
    "timestamp": 1784194035.3998046
  },
  {
    "positions": [
      {
        "protocol": "Aave",
        "position_usd": 50000.0,
        "exit_fee_usd": 0.0,
        "net_exit_value_usd": 50000.0,
        "estimated_exit_days": 0.0,
        "can_exit_in_target": true,
        "exit_liquidity_score": 100,
        "exit_label": "INSTANT",
        "market_depth_coverage_pct": 400.0,
        "bottleneck": null,
        "recommendation": "Immediate exit available. Depth covers 400% of position."
      }
    ],
    "instantly_exitable_usd": 50000.0,
    "total_position_usd": 50000.0,
    "liquidity_ratio_pct": 100.0,
    "most_locked": null,
    "average_exit_liquidity_score": 100.0,
    "timestamp": 1784194035.4267151
  },
  {
    "positions": [
      {
        "protocol": "A",
        "position_usd": 50000.0,
        "exit_fee_usd": 0.0,
        "net_exit_value_usd": 50000.0,
        "estimated_exit_days": 30.0,
        "can_exit_in_target": false,
        "exit_liquidity_score": 40,
        "exit_label": "LOCKED",
        "market_depth_coverage_pct": 200.0,
        "bottleneck": "LOCK_UP",
        "recommendation": "Locked for 30d. Plan around lock expiry."
      },
      {
        "protocol": "B",
        "position_usd": 50000.0,
        "exit_fee_usd": 0.0,
        "net_exit_value_usd": 50000.0,
        "estimated_exit_days": 60.0,
        "can_exit_in_target": false,
        "exit_liquidity_score": 32,
        "exit_label": "LOCKED",
        "market_depth_coverage_pct": 200.0,
        "bottleneck": "LOCK_UP",
        "recommendation": "Locked for 60d. Plan around lock expiry."
      }
    ],
    "instantly_exitable_usd": 0,
    "total_position_usd": 100000.0,
    "liquidity_ratio_pct": 0.0,
    "most_locked": "B",
    "average_exit_liquidity_score": 36.0,
    "timestamp": 1784194035.5457482
  },
  {
    "positions": [
      {
        "protocol": "X",
        "position_usd": 10000.0,
        "exit_fee_usd": 0.0,
        "net_exit_value_usd": 10000.0,
        "estimated_exit_days": 0.0,
        "can_exit_in_target": true,
        "exit_liquidity_score": 80,
        "exit_label": "INSTANT",
        "market_depth_coverage_pct": 0.0,
        "bottleneck": "MARKET_DEPTH",
        "recommendation": "Immediate exit available. Depth covers 0% of position."
      }
    ],
    "instantly_exitable_usd": 10000.0,
    "total_position_usd": 10000.0,
    "liquidity_ratio_pct": 100.0,
    "most_locked": null,
    "average_exit_liquidity_score": 80.0,
    "timestamp": 1784194035.550575
  },
  {
    "positions": [
      {
        "protocol": "Short",
        "position_usd": 10000.0,
        "exit_fee_usd": 0.0,
        "net_exit_value_usd": 10000.0,
        "estimated_exit_days": 10.0,
        "can_exit_in_target": false,
        "exit_liquidity_score": 40,
        "exit_label": "LOCKED",
        "market_depth_coverage_pct": 1000.0,
        "bottleneck": "LOCK_UP",
        "recommendation": "Locked for 10d. Plan around lock expiry."
      },
      {
        "protocol": "Long",
        "position_usd": 10000.0,
        "exit_fee_usd": 0.0,
        "net_exit_value_usd": 10000.0,
        "estimated_exit_days": 180.0,
        "can_exit_in_target": false,
        "exit_liquidity_score": 28,
        "exit_label": "LOCKED",
        "market_depth_coverage_pct": 1000.0,
        "bottleneck": "LOCK_UP",
        "recommendation": "Locked for 180d. Plan around lock expiry."
      }
    ],
    "instantly_exitable_usd": 0,
    "total_position_usd": 20000.0,
    "liquidity_ratio_pct": 0.0,
    "most_locked": "Long",
    "average_exit_liquidity_score": 34.0,
    "timestamp": 1784194035.5552895
  },
  {
    "positions": [
      {
        "protocol": "A",
        "position_usd": 30000.0,
        "exit_fee_usd": 0.0,
        "net_exit_value_usd": 30000.0,
        "estimated_exit_days": 0.0,
        "can_exit_in_target": true,
        "exit_liquidity_score": 100,
        "exit_label": "INSTANT",
        "market_depth_coverage_pct": 333.33333333333337,
        "bottleneck": null,
        "recommendation": "Immediate exit available. Depth covers 333% of position."
      },
      {
        "protocol": "B",
        "position_usd": 70000.0,
        "exit_fee_usd": 0.0,
        "net_exit_value_usd": 70000.0,
        "estimated_exit_days": 0.0,
        "can_exit_in_target": true,
        "exit_liquidity_score": 95,
        "exit_label": "INSTANT",
        "market_depth_coverage_pct": 142.85714285714286,
        "bottleneck": null,
        "recommendation": "Immediate exit available. Depth covers 143% of position."
      }
    ],
    "instantly_exitable_usd": 100000.0,
    "total_position_usd": 100000.0,
    "liquidity_ratio_pct": 100.0,
    "most_locked": null,
    "average_exit_liquidity_score": 97.5,
    "timestamp": 1784194035.5599792
  },
  {
    "positions": [
      {
        "protocol": "AaveV3",
        "position_usd": 50000.0,
        "exit_fee_usd": 0.0,
        "net_exit_value_usd": 50000.0,
        "estimated_exit_days": 0.0,
        "can_exit_in_target": true,
        "exit_liquidity_score": 100,
        "exit_label": "INSTANT",
        "market_depth_coverage_pct": 200.0,
        "bottleneck": null,
        "recommendation": "Immediate exit available. Depth covers 200% of position."
      }
    ],
    "instantly_exitable_usd": 50000.0,
    "total_position_usd": 50000.0,
    "liquidity_ratio_pct": 100.0,
    "most_locked": null,
    "average_exit_liquidity_score": 100.0,
    "timestamp": 1784194035.5650675
  },
  {
    "positions": [
      {
        "protocol": "A",
        "position_usd": 50000.0,
        "exit_fee_usd": 0.0,
        "net_exit_value_usd": 50000.0,
        "estimated_exit_days": 365.0,
        "can_exit_in_target": false,
        "exit_liquidity_score": 25,
        "exit_label": "LOCKED",
        "market_depth_coverage_pct": 200.0,
        "bottleneck": "LOCK_UP",
        "recommendation": "Locked for 365d. Plan around lock expiry."
      },
      {
        "protocol": "B",
        "position_usd": 50000.0,
        "exit_fee_usd": 0.0,
        "net_exit_value_usd": 50000.0,
        "estimated_exit_days": 0.0,
        "can_exit_in_target": true,
        "exit_liquidity_score": 100,
        "exit_label": "INSTANT",
        "market_depth_coverage_pct": 200.0,
        "bottleneck": null,
        "recommendation": "Immediate exit available. Depth covers 200% of position."
      }
    ],
    "instantly_exitable_usd": 50000.0,
    "total_position_usd": 100000.0,
    "liquidity_ratio_pct": 50.0,
    "most_locked": "A",
    "average_exit_liquidity_score": 62.5,
    "timestamp": 1784194035.5697663
  },
  {
    "positions": [
      {
        "protocol": "X",
        "position_usd": 50000.0,
        "exit_fee_usd": 0.0,
        "net_exit_value_usd": 50000.0,
        "estimated_exit_days": 1.0,
        "can_exit_in_target": true,
        "exit_liquidity_score": 90,
        "exit_label": "FAST",
        "market_depth_coverage_pct": 200.0,
        "bottleneck": "QUEUE",
        "recommendation": "Exit available quickly. Monitor queue size."
      }
    ],
    "instantly_exitable_usd": 0,
    "total_position_usd": 50000.0,
    "liquidity_ratio_pct": 0.0,
    "most_locked": "X",
    "average_exit_liquidity_score": 90.0,
    "timestamp": 1784194035.5742397
  },
  {
    "positions": [
      {
        "protocol": "AaveV3",
        "position_usd": 50000.0,
        "exit_fee_usd": 0.0,
        "net_exit_value_usd": 50000.0,
        "estimated_exit_days": 0.0,
        "can_exit_in_target": true,
        "exit_liquidity_score": 100,
        "exit_label": "INSTANT",
        "market_depth_coverage_pct": 200.0,
        "bottleneck": null,
        "recommendation": "Immediate exit available. Depth covers 200% of position."
      }
    ],
    "instantly_exitable_usd": 50000.0,
    "total_position_usd": 50000.0,
    "liquidity_ratio_pct": 100.0,
    "most_locked": null,
    "average_exit_liquidity_score": 100.0,
    "timestamp": 1784194035.5792124
  },
  {
    "positions": [
      {
        "protocol": "AaveV3",
        "position_usd": 0.0,
        "exit_fee_usd": 0.0,
        "net_exit_value_usd": 0.0,
        "estimated_exit_days": 0.0,
        "can_exit_in_target": true,
        "exit_liquidity_score": 80,
        "exit_label": "INSTANT",
        "market_depth_coverage_pct": 0.0,
        "bottleneck": "MARKET_DEPTH",
        "recommendation": "Immediate exit available. Depth covers 0% of position."
      }
    ],
    "instantly_exitable_usd": 0.0,
    "total_position_usd": 0.0,
    "liquidity_ratio_pct": 0.0,
    "most_locked": null,
    "average_exit_liquidity_score": 80.0,
    "timestamp": 1784194035.5837572
  }
]