[
  {
    "name": "UNKNOWN",
    "total_apr_pct": 0.0,
    "liquid_apr_pct": 0.0,
    "reward_apr_pct": 0.0,
    "lockup_days": 0.0,
    "discount_rate_pct": 15.0,
    "annual_vol_pct": 0.0,
    "early_exit_penalty_pct": 0.0,
    "liquid_unlock_fraction": 0.0,
    "data_quality_ok": true,
    "reward_share_of_apr_pct": 0.0,
    "lockup_discount_factor": 1.0,
    "realisable_reward_apr_pct": 0.0,
    "lockup_adjusted_apr_pct": 0.0,
    "headline_vs_realisable_gap_pct": 0.0,
    "paper_yield_share_pct": 0.0,
    "reward_realisability_score": 0.0,
    "classification": "DEEPLY_LOCKED",
    "grade": "F",
    "flags": [
      "INSUFFICIENT_DATA"
    ],
    "recommendations": [
      "Insufficient data: no APR/lockup signal or data marked unreliable. Cannot assess reward-lockup discount for this position."
    ],
    "timestamp": 1783931459.2806635
  },
  {
    "name": "UNKNOWN",
    "total_apr_pct": 0.0,
    "liquid_apr_pct": 0.0,
    "reward_apr_pct": 0.0,
    "lockup_days": 0.0,
    "discount_rate_pct": 15.0,
    "annual_vol_pct": 0.0,
    "early_exit_penalty_pct": 0.0,
    "liquid_unlock_fraction": 0.0,
    "data_quality_ok": true,
    "reward_share_of_apr_pct": 0.0,
    "lockup_discount_factor": 1.0,
    "realisable_reward_apr_pct": 0.0,
    "lockup_adjusted_apr_pct": 0.0,
    "headline_vs_realisable_gap_pct": 0.0,
    "paper_yield_share_pct": 0.0,
    "reward_realisability_score": 0.0,
    "classification": "DEEPLY_LOCKED",
    "grade": "F",
    "flags": [
      "INSUFFICIENT_DATA"
    ],
    "recommendations": [
      "Insufficient data: no APR/lockup signal or data marked unreliable. Cannot assess reward-lockup discount for this position."
    ],
    "timestamp": 1783931459.592794
  },
  {
    "name": "UNKNOWN",
    "total_apr_pct": 0.0,
    "liquid_apr_pct": 0.0,
    "reward_apr_pct": 0.0,
    "lockup_days": 0.0,
    "discount_rate_pct": 15.0,
    "annual_vol_pct": 0.0,
    "early_exit_penalty_pct": 0.0,
    "liquid_unlock_fraction": 0.0,
    "data_quality_ok": true,
    "reward_share_of_apr_pct": 0.0,
    "lockup_discount_factor": 1.0,
    "realisable_reward_apr_pct": 0.0,
    "lockup_adjusted_apr_pct": 0.0,
    "headline_vs_realisable_gap_pct": 0.0,
    "paper_yield_share_pct": 0.0,
    "reward_realisability_score": 0.0,
    "classification": "DEEPLY_LOCKED",
    "grade": "F",
    "flags": [
      "INSUFFICIENT_DATA"
    ],
    "recommendations": [
      "Insufficient data: no APR/lockup signal or data marked unreliable. Cannot assess reward-lockup discount for this position."
    ],
    "timestamp": 1783931459.730096
  },
  {
    "name": "UNKNOWN",
    "total_apr_pct": 0.0,
    "liquid_apr_pct": 0.0,
    "reward_apr_pct": 0.0,
    "lockup_days": 0.0,
    "discount_rate_pct": 15.0,
    "annual_vol_pct": 0.0,
    "early_exit_penalty_pct": 0.0,
    "liquid_unlock_fraction": 0.0,
    "data_quality_ok": true,
    "reward_share_of_apr_pct": 0.0,
    "lockup_discount_factor": 1.0,
    "realisable_reward_apr_pct": 0.0,
    "lockup_adjusted_apr_pct": 0.0,
    "headline_vs_realisable_gap_pct": 0.0,
    "paper_yield_share_pct": 0.0,
    "reward_realisability_score": 0.0,
    "classification": "DEEPLY_LOCKED",
    "grade": "F",
    "flags": [
      "INSUFFICIENT_DATA"
    ],
    "recommendations": [
      "Insufficient data: no APR/lockup signal or data marked unreliable. Cannot assess reward-lockup discount for this position."
    ],
    "timestamp": 1783931459.9930563
  },
  {
    "name": "UNKNOWN",
    "total_apr_pct": 0.0,
    "liquid_apr_pct": 0.0,
    "reward_apr_pct": 0.0,
    "lockup_days": 0.0,
    "discount_rate_pct": 15.0,
    "annual_vol_pct": 0.0,
    "early_exit_penalty_pct": 0.0,
    "liquid_unlock_fraction": 0.0,
    "data_quality_ok": true,
    "reward_share_of_apr_pct": 0.0,
    "lockup_discount_factor": 1.0,
    "realisable_reward_apr_pct": 0.0,
    "lockup_adjusted_apr_pct": 0.0,
    "headline_vs_realisable_gap_pct": 0.0,
    "paper_yield_share_pct": 0.0,
    "reward_realisability_score": 0.0,
    "classification": "DEEPLY_LOCKED",
    "grade": "F",
    "flags": [
      "INSUFFICIENT_DATA"
    ],
    "recommendations": [
      "Insufficient data: no APR/lockup signal or data marked unreliable. Cannot assess reward-lockup discount for this position."
    ],
    "timestamp": 1783931460.1360347
  },
  {
    "name": "UNKNOWN",
    "total_apr_pct": 0.0,
    "liquid_apr_pct": 0.0,
    "reward_apr_pct": 0.0,
    "lockup_days": 0.0,
    "discount_rate_pct": 15.0,
    "annual_vol_pct": 0.0,
    "early_exit_penalty_pct": 0.0,
    "liquid_unlock_fraction": 0.0,
    "data_quality_ok": true,
    "reward_share_of_apr_pct": 0.0,
    "lockup_discount_factor": 1.0,
    "realisable_reward_apr_pct": 0.0,
    "lockup_adjusted_apr_pct": 0.0,
    "headline_vs_realisable_gap_pct": 0.0,
    "paper_yield_share_pct": 0.0,
    "reward_realisability_score": 0.0,
    "classification": "DEEPLY_LOCKED",
    "grade": "F",
    "flags": [
      "INSUFFICIENT_DATA"
    ],
    "recommendations": [
      "Insufficient data: no APR/lockup signal or data marked unreliable. Cannot assess reward-lockup discount for this position."
    ],
    "timestamp": 1783931460.4055448
  },
  {
    "name": "UNKNOWN",
    "total_apr_pct": 0.0,
    "liquid_apr_pct": 0.0,
    "reward_apr_pct": 0.0,
    "lockup_days": 0.0,
    "discount_rate_pct": 15.0,
    "annual_vol_pct": 0.0,
    "early_exit_penalty_pct": 0.0,
    "liquid_unlock_fraction": 0.0,
    "data_quality_ok": true,
    "reward_share_of_apr_pct": 0.0,
    "lockup_discount_factor": 1.0,
    "realisable_reward_apr_pct": 0.0,
    "lockup_adjusted_apr_pct": 0.0,
    "headline_vs_realisable_gap_pct": 0.0,
    "paper_yield_share_pct": 0.0,
    "reward_realisability_score": 0.0,
    "classification": "DEEPLY_LOCKED",
    "grade": "F",
    "flags": [
      "INSUFFICIENT_DATA"
    ],
    "recommendations": [
      "Insufficient data: no APR/lockup signal or data marked unreliable. Cannot assess reward-lockup discount for this position."
    ],
    "timestamp": 1783931460.853959
  },
  {
    "name": "UNKNOWN",
    "total_apr_pct": 0.0,
    "liquid_apr_pct": 0.0,
    "reward_apr_pct": 0.0,
    "lockup_days": 0.0,
    "discount_rate_pct": 15.0,
    "annual_vol_pct": 0.0,
    "early_exit_penalty_pct": 0.0,
    "liquid_unlock_fraction": 0.0,
    "data_quality_ok": true,
    "reward_share_of_apr_pct": 0.0,
    "lockup_discount_factor": 1.0,
    "realisable_reward_apr_pct": 0.0,
    "lockup_adjusted_apr_pct": 0.0,
    "headline_vs_realisable_gap_pct": 0.0,
    "paper_yield_share_pct": 0.0,
    "reward_realisability_score": 0.0,
    "classification": "DEEPLY_LOCKED",
    "grade": "F",
    "flags": [
      "INSUFFICIENT_DATA"
    ],
    "recommendations": [
      "Insufficient data: no APR/lockup signal or data marked unreliable. Cannot assess reward-lockup discount for this position."
    ],
    "timestamp": 1783931461.2938573
  },
  {
    "name": "UNKNOWN",
    "total_apr_pct": 0.0,
    "liquid_apr_pct": 0.0,
    "reward_apr_pct": 0.0,
    "lockup_days": 0.0,
    "discount_rate_pct": 15.0,
    "annual_vol_pct": 0.0,
    "early_exit_penalty_pct": 0.0,
    "liquid_unlock_fraction": 0.0,
    "data_quality_ok": true,
    "reward_share_of_apr_pct": 0.0,
    "lockup_discount_factor": 1.0,
    "realisable_reward_apr_pct": 0.0,
    "lockup_adjusted_apr_pct": 0.0,
    "headline_vs_realisable_gap_pct": 0.0,
    "paper_yield_share_pct": 0.0,
    "reward_realisability_score": 0.0,
    "classification": "DEEPLY_LOCKED",
    "grade": "F",
    "flags": [
      "INSUFFICIENT_DATA"
    ],
    "recommendations": [
      "Insufficient data: no APR/lockup signal or data marked unreliable. Cannot assess reward-lockup discount for this position."
    ],
    "timestamp": 1783931463.3762083
  },
  {
    "name": "UNKNOWN",
    "total_apr_pct": 0.0,
    "liquid_apr_pct": 0.0,
    "reward_apr_pct": 0.0,
    "lockup_days": 0.0,
    "discount_rate_pct": 15.0,
    "annual_vol_pct": 0.0,
    "early_exit_penalty_pct": 0.0,
    "liquid_unlock_fraction": 0.0,
    "data_quality_ok": true,
    "reward_share_of_apr_pct": 0.0,
    "lockup_discount_factor": 1.0,
    "realisable_reward_apr_pct": 0.0,
    "lockup_adjusted_apr_pct": 0.0,
    "headline_vs_realisable_gap_pct": 0.0,
    "paper_yield_share_pct": 0.0,
    "reward_realisability_score": 0.0,
    "classification": "DEEPLY_LOCKED",
    "grade": "F",
    "flags": [
      "INSUFFICIENT_DATA"
    ],
    "recommendations": [
      "Insufficient data: no APR/lockup signal or data marked unreliable. Cannot assess reward-lockup discount for this position."
    ],
    "timestamp": 1783931463.849639
  },
  {
    "name": "UNKNOWN",
    "total_apr_pct": 0.0,
    "liquid_apr_pct": 0.0,
    "reward_apr_pct": 0.0,
    "lockup_days": 0.0,
    "discount_rate_pct": 15.0,
    "annual_vol_pct": 0.0,
    "early_exit_penalty_pct": 0.0,
    "liquid_unlock_fraction": 0.0,
    "data_quality_ok": true,
    "reward_share_of_apr_pct": 0.0,
    "lockup_discount_factor": 1.0,
    "realisable_reward_apr_pct": 0.0,
    "lockup_adjusted_apr_pct": 0.0,
    "headline_vs_realisable_gap_pct": 0.0,
    "paper_yield_share_pct": 0.0,
    "reward_realisability_score": 0.0,
    "classification": "DEEPLY_LOCKED",
    "grade": "F",
    "flags": [
      "INSUFFICIENT_DATA"
    ],
    "recommendations": [
      "Insufficient data: no APR/lockup signal or data marked unreliable. Cannot assess reward-lockup discount for this position."
    ],
    "timestamp": 1783931464.2220008
  },
  {
    "name": "UNKNOWN",
    "total_apr_pct": 0.0,
    "liquid_apr_pct": 0.0,
    "reward_apr_pct": 0.0,
    "lockup_days": 0.0,
    "discount_rate_pct": 15.0,
    "annual_vol_pct": 0.0,
    "early_exit_penalty_pct": 0.0,
    "liquid_unlock_fraction": 0.0,
    "data_quality_ok": true,
    "reward_share_of_apr_pct": 0.0,
    "lockup_discount_factor": 1.0,
    "realisable_reward_apr_pct": 0.0,
    "lockup_adjusted_apr_pct": 0.0,
    "headline_vs_realisable_gap_pct": 0.0,
    "paper_yield_share_pct": 0.0,
    "reward_realisability_score": 0.0,
    "classification": "DEEPLY_LOCKED",
    "grade": "F",
    "flags": [
      "INSUFFICIENT_DATA"
    ],
    "recommendations": [
      "Insufficient data: no APR/lockup signal or data marked unreliable. Cannot assess reward-lockup discount for this position."
    ],
    "timestamp": 1783931464.296887
  },
  {
    "name": "UNKNOWN",
    "total_apr_pct": 0.0,
    "liquid_apr_pct": 0.0,
    "reward_apr_pct": 0.0,
    "lockup_days": 0.0,
    "discount_rate_pct": 15.0,
    "annual_vol_pct": 0.0,
    "early_exit_penalty_pct": 0.0,
    "liquid_unlock_fraction": 0.0,
    "data_quality_ok": true,
    "reward_share_of_apr_pct": 0.0,
    "lockup_discount_factor": 1.0,
    "realisable_reward_apr_pct": 0.0,
    "lockup_adjusted_apr_pct": 0.0,
    "headline_vs_realisable_gap_pct": 0.0,
    "paper_yield_share_pct": 0.0,
    "reward_realisability_score": 0.0,
    "classification": "DEEPLY_LOCKED",
    "grade": "F",
    "flags": [
      "INSUFFICIENT_DATA"
    ],
    "recommendations": [
      "Insufficient data: no APR/lockup signal or data marked unreliable. Cannot assess reward-lockup discount for this position."
    ],
    "timestamp": 1783931464.6936011
  },
  {
    "name": "UNKNOWN",
    "total_apr_pct": 0.0,
    "liquid_apr_pct": 0.0,
    "reward_apr_pct": 0.0,
    "lockup_days": 0.0,
    "discount_rate_pct": 15.0,
    "annual_vol_pct": 0.0,
    "early_exit_penalty_pct": 0.0,
    "liquid_unlock_fraction": 0.0,
    "data_quality_ok": true,
    "reward_share_of_apr_pct": 0.0,
    "lockup_discount_factor": 1.0,
    "realisable_reward_apr_pct": 0.0,
    "lockup_adjusted_apr_pct": 0.0,
    "headline_vs_realisable_gap_pct": 0.0,
    "paper_yield_share_pct": 0.0,
    "reward_realisability_score": 0.0,
    "classification": "DEEPLY_LOCKED",
    "grade": "F",
    "flags": [
      "INSUFFICIENT_DATA"
    ],
    "recommendations": [
      "Insufficient data: no APR/lockup signal or data marked unreliable. Cannot assess reward-lockup discount for this position."
    ],
    "timestamp": 1783931465.135338
  },
  {
    "name": "UNKNOWN",
    "total_apr_pct": 0.0,
    "liquid_apr_pct": 0.0,
    "reward_apr_pct": 0.0,
    "lockup_days": 0.0,
    "discount_rate_pct": 15.0,
    "annual_vol_pct": 0.0,
    "early_exit_penalty_pct": 0.0,
    "liquid_unlock_fraction": 0.0,
    "data_quality_ok": true,
    "reward_share_of_apr_pct": 0.0,
    "lockup_discount_factor": 1.0,
    "realisable_reward_apr_pct": 0.0,
    "lockup_adjusted_apr_pct": 0.0,
    "headline_vs_realisable_gap_pct": 0.0,
    "paper_yield_share_pct": 0.0,
    "reward_realisability_score": 0.0,
    "classification": "DEEPLY_LOCKED",
    "grade": "F",
    "flags": [
      "INSUFFICIENT_DATA"
    ],
    "recommendations": [
      "Insufficient data: no APR/lockup signal or data marked unreliable. Cannot assess reward-lockup discount for this position."
    ],
    "timestamp": 1783931465.364464
  },
  {
    "name": "UNKNOWN",
    "total_apr_pct": 0.0,
    "liquid_apr_pct": 0.0,
    "reward_apr_pct": 0.0,
    "lockup_days": 0.0,
    "discount_rate_pct": 15.0,
    "annual_vol_pct": 0.0,
    "early_exit_penalty_pct": 0.0,
    "liquid_unlock_fraction": 0.0,
    "data_quality_ok": true,
    "reward_share_of_apr_pct": 0.0,
    "lockup_discount_factor": 1.0,
    "realisable_reward_apr_pct": 0.0,
    "lockup_adjusted_apr_pct": 0.0,
    "headline_vs_realisable_gap_pct": 0.0,
    "paper_yield_share_pct": 0.0,
    "reward_realisability_score": 0.0,
    "classification": "DEEPLY_LOCKED",
    "grade": "F",
    "flags": [
      "INSUFFICIENT_DATA"
    ],
    "recommendations": [
      "Insufficient data: no APR/lockup signal or data marked unreliable. Cannot assess reward-lockup discount for this position."
    ],
    "timestamp": 1783931465.597259
  },
  {
    "name": "UNKNOWN",
    "total_apr_pct": 0.0,
    "liquid_apr_pct": 0.0,
    "reward_apr_pct": 0.0,
    "lockup_days": 0.0,
    "discount_rate_pct": 15.0,
    "annual_vol_pct": 0.0,
    "early_exit_penalty_pct": 0.0,
    "liquid_unlock_fraction": 0.0,
    "data_quality_ok": true,
    "reward_share_of_apr_pct": 0.0,
    "lockup_discount_factor": 1.0,
    "realisable_reward_apr_pct": 0.0,
    "lockup_adjusted_apr_pct": 0.0,
    "headline_vs_realisable_gap_pct": 0.0,
    "paper_yield_share_pct": 0.0,
    "reward_realisability_score": 0.0,
    "classification": "DEEPLY_LOCKED",
    "grade": "F",
    "flags": [
      "INSUFFICIENT_DATA"
    ],
    "recommendations": [
      "Insufficient data: no APR/lockup signal or data marked unreliable. Cannot assess reward-lockup discount for this position."
    ],
    "timestamp": 1783931465.8085806
  },
  {
    "name": "UNKNOWN",
    "total_apr_pct": 0.0,
    "liquid_apr_pct": 0.0,
    "reward_apr_pct": 0.0,
    "lockup_days": 0.0,
    "discount_rate_pct": 15.0,
    "annual_vol_pct": 0.0,
    "early_exit_penalty_pct": 0.0,
    "liquid_unlock_fraction": 0.0,
    "data_quality_ok": true,
    "reward_share_of_apr_pct": 0.0,
    "lockup_discount_factor": 1.0,
    "realisable_reward_apr_pct": 0.0,
    "lockup_adjusted_apr_pct": 0.0,
    "headline_vs_realisable_gap_pct": 0.0,
    "paper_yield_share_pct": 0.0,
    "reward_realisability_score": 0.0,
    "classification": "DEEPLY_LOCKED",
    "grade": "F",
    "flags": [
      "INSUFFICIENT_DATA"
    ],
    "recommendations": [
      "Insufficient data: no APR/lockup signal or data marked unreliable. Cannot assess reward-lockup discount for this position."
    ],
    "timestamp": 1783931466.0533063
  },
  {
    "name": "UNKNOWN",
    "total_apr_pct": 0.0,
    "liquid_apr_pct": 0.0,
    "reward_apr_pct": 0.0,
    "lockup_days": 0.0,
    "discount_rate_pct": 15.0,
    "annual_vol_pct": 0.0,
    "early_exit_penalty_pct": 0.0,
    "liquid_unlock_fraction": 0.0,
    "data_quality_ok": true,
    "reward_share_of_apr_pct": 0.0,
    "lockup_discount_factor": 1.0,
    "realisable_reward_apr_pct": 0.0,
    "lockup_adjusted_apr_pct": 0.0,
    "headline_vs_realisable_gap_pct": 0.0,
    "paper_yield_share_pct": 0.0,
    "reward_realisability_score": 0.0,
    "classification": "DEEPLY_LOCKED",
    "grade": "F",
    "flags": [
      "INSUFFICIENT_DATA"
    ],
    "recommendations": [
      "Insufficient data: no APR/lockup signal or data marked unreliable. Cannot assess reward-lockup discount for this position."
    ],
    "timestamp": 1783931466.2776527
  },
  {
    "name": "UNKNOWN",
    "total_apr_pct": 0.0,
    "liquid_apr_pct": 0.0,
    "reward_apr_pct": 0.0,
    "lockup_days": 0.0,
    "discount_rate_pct": 15.0,
    "annual_vol_pct": 0.0,
    "early_exit_penalty_pct": 0.0,
    "liquid_unlock_fraction": 0.0,
    "data_quality_ok": true,
    "reward_share_of_apr_pct": 0.0,
    "lockup_discount_factor": 1.0,
    "realisable_reward_apr_pct": 0.0,
    "lockup_adjusted_apr_pct": 0.0,
    "headline_vs_realisable_gap_pct": 0.0,
    "paper_yield_share_pct": 0.0,
    "reward_realisability_score": 0.0,
    "classification": "DEEPLY_LOCKED",
    "grade": "F",
    "flags": [
      "INSUFFICIENT_DATA"
    ],
    "recommendations": [
      "Insufficient data: no APR/lockup signal or data marked unreliable. Cannot assess reward-lockup discount for this position."
    ],
    "timestamp": 1783931466.510471
  },
  {
    "name": "UNKNOWN",
    "total_apr_pct": 0.0,
    "liquid_apr_pct": 0.0,
    "reward_apr_pct": 0.0,
    "lockup_days": 0.0,
    "discount_rate_pct": 15.0,
    "annual_vol_pct": 0.0,
    "early_exit_penalty_pct": 0.0,
    "liquid_unlock_fraction": 0.0,
    "data_quality_ok": true,
    "reward_share_of_apr_pct": 0.0,
    "lockup_discount_factor": 1.0,
    "realisable_reward_apr_pct": 0.0,
    "lockup_adjusted_apr_pct": 0.0,
    "headline_vs_realisable_gap_pct": 0.0,
    "paper_yield_share_pct": 0.0,
    "reward_realisability_score": 0.0,
    "classification": "DEEPLY_LOCKED",
    "grade": "F",
    "flags": [
      "INSUFFICIENT_DATA"
    ],
    "recommendations": [
      "Insufficient data: no APR/lockup signal or data marked unreliable. Cannot assess reward-lockup discount for this position."
    ],
    "timestamp": 1783931466.7053413
  },
  {
    "name": "UNKNOWN",
    "total_apr_pct": 0.0,
    "liquid_apr_pct": 0.0,
    "reward_apr_pct": 0.0,
    "lockup_days": 0.0,
    "discount_rate_pct": 15.0,
    "annual_vol_pct": 0.0,
    "early_exit_penalty_pct": 0.0,
    "liquid_unlock_fraction": 0.0,
    "data_quality_ok": true,
    "reward_share_of_apr_pct": 0.0,
    "lockup_discount_factor": 1.0,
    "realisable_reward_apr_pct": 0.0,
    "lockup_adjusted_apr_pct": 0.0,
    "headline_vs_realisable_gap_pct": 0.0,
    "paper_yield_share_pct": 0.0,
    "reward_realisability_score": 0.0,
    "classification": "DEEPLY_LOCKED",
    "grade": "F",
    "flags": [
      "INSUFFICIENT_DATA"
    ],
    "recommendations": [
      "Insufficient data: no APR/lockup signal or data marked unreliable. Cannot assess reward-lockup discount for this position."
    ],
    "timestamp": 1783931466.9192595
  },
  {
    "name": "UNKNOWN",
    "total_apr_pct": 0.0,
    "liquid_apr_pct": 0.0,
    "reward_apr_pct": 0.0,
    "lockup_days": 0.0,
    "discount_rate_pct": 15.0,
    "annual_vol_pct": 0.0,
    "early_exit_penalty_pct": 0.0,
    "liquid_unlock_fraction": 0.0,
    "data_quality_ok": true,
    "reward_share_of_apr_pct": 0.0,
    "lockup_discount_factor": 1.0,
    "realisable_reward_apr_pct": 0.0,
    "lockup_adjusted_apr_pct": 0.0,
    "headline_vs_realisable_gap_pct": 0.0,
    "paper_yield_share_pct": 0.0,
    "reward_realisability_score": 0.0,
    "classification": "DEEPLY_LOCKED",
    "grade": "F",
    "flags": [
      "INSUFFICIENT_DATA"
    ],
    "recommendations": [
      "Insufficient data: no APR/lockup signal or data marked unreliable. Cannot assess reward-lockup discount for this position."
    ],
    "timestamp": 1783931467.1323957
  },
  {
    "name": "UNKNOWN",
    "total_apr_pct": 0.0,
    "liquid_apr_pct": 0.0,
    "reward_apr_pct": 0.0,
    "lockup_days": 0.0,
    "discount_rate_pct": 15.0,
    "annual_vol_pct": 0.0,
    "early_exit_penalty_pct": 0.0,
    "liquid_unlock_fraction": 0.0,
    "data_quality_ok": true,
    "reward_share_of_apr_pct": 0.0,
    "lockup_discount_factor": 1.0,
    "realisable_reward_apr_pct": 0.0,
    "lockup_adjusted_apr_pct": 0.0,
    "headline_vs_realisable_gap_pct": 0.0,
    "paper_yield_share_pct": 0.0,
    "reward_realisability_score": 0.0,
    "classification": "DEEPLY_LOCKED",
    "grade": "F",
    "flags": [
      "INSUFFICIENT_DATA"
    ],
    "recommendations": [
      "Insufficient data: no APR/lockup signal or data marked unreliable. Cannot assess reward-lockup discount for this position."
    ],
    "timestamp": 1783931467.3533654
  },
  {
    "name": "UNKNOWN",
    "total_apr_pct": 0.0,
    "liquid_apr_pct": 0.0,
    "reward_apr_pct": 0.0,
    "lockup_days": 0.0,
    "discount_rate_pct": 15.0,
    "annual_vol_pct": 0.0,
    "early_exit_penalty_pct": 0.0,
    "liquid_unlock_fraction": 0.0,
    "data_quality_ok": true,
    "reward_share_of_apr_pct": 0.0,
    "lockup_discount_factor": 1.0,
    "realisable_reward_apr_pct": 0.0,
    "lockup_adjusted_apr_pct": 0.0,
    "headline_vs_realisable_gap_pct": 0.0,
    "paper_yield_share_pct": 0.0,
    "reward_realisability_score": 0.0,
    "classification": "DEEPLY_LOCKED",
    "grade": "F",
    "flags": [
      "INSUFFICIENT_DATA"
    ],
    "recommendations": [
      "Insufficient data: no APR/lockup signal or data marked unreliable. Cannot assess reward-lockup discount for this position."
    ],
    "timestamp": 1783931470.3642116
  },
  {
    "name": "UNKNOWN",
    "total_apr_pct": 0.0,
    "liquid_apr_pct": 0.0,
    "reward_apr_pct": 0.0,
    "lockup_days": 0.0,
    "discount_rate_pct": 15.0,
    "annual_vol_pct": 0.0,
    "early_exit_penalty_pct": 0.0,
    "liquid_unlock_fraction": 0.0,
    "data_quality_ok": true,
    "reward_share_of_apr_pct": 0.0,
    "lockup_discount_factor": 1.0,
    "realisable_reward_apr_pct": 0.0,
    "lockup_adjusted_apr_pct": 0.0,
    "headline_vs_realisable_gap_pct": 0.0,
    "paper_yield_share_pct": 0.0,
    "reward_realisability_score": 0.0,
    "classification": "DEEPLY_LOCKED",
    "grade": "F",
    "flags": [
      "INSUFFICIENT_DATA"
    ],
    "recommendations": [
      "Insufficient data: no APR/lockup signal or data marked unreliable. Cannot assess reward-lockup discount for this position."
    ],
    "timestamp": 1783931470.6625733
  },
  {
    "name": "UNKNOWN",
    "total_apr_pct": 0.0,
    "liquid_apr_pct": 0.0,
    "reward_apr_pct": 0.0,
    "lockup_days": 0.0,
    "discount_rate_pct": 15.0,
    "annual_vol_pct": 0.0,
    "early_exit_penalty_pct": 0.0,
    "liquid_unlock_fraction": 0.0,
    "data_quality_ok": true,
    "reward_share_of_apr_pct": 0.0,
    "lockup_discount_factor": 1.0,
    "realisable_reward_apr_pct": 0.0,
    "lockup_adjusted_apr_pct": 0.0,
    "headline_vs_realisable_gap_pct": 0.0,
    "paper_yield_share_pct": 0.0,
    "reward_realisability_score": 0.0,
    "classification": "DEEPLY_LOCKED",
    "grade": "F",
    "flags": [
      "INSUFFICIENT_DATA"
    ],
    "recommendations": [
      "Insufficient data: no APR/lockup signal or data marked unreliable. Cannot assess reward-lockup discount for this position."
    ],
    "timestamp": 1783931470.8436208
  },
  {
    "name": "UNKNOWN",
    "total_apr_pct": 0.0,
    "liquid_apr_pct": 0.0,
    "reward_apr_pct": 0.0,
    "lockup_days": 0.0,
    "discount_rate_pct": 15.0,
    "annual_vol_pct": 0.0,
    "early_exit_penalty_pct": 0.0,
    "liquid_unlock_fraction": 0.0,
    "data_quality_ok": true,
    "reward_share_of_apr_pct": 0.0,
    "lockup_discount_factor": 1.0,
    "realisable_reward_apr_pct": 0.0,
    "lockup_adjusted_apr_pct": 0.0,
    "headline_vs_realisable_gap_pct": 0.0,
    "paper_yield_share_pct": 0.0,
    "reward_realisability_score": 0.0,
    "classification": "DEEPLY_LOCKED",
    "grade": "F",
    "flags": [
      "INSUFFICIENT_DATA"
    ],
    "recommendations": [
      "Insufficient data: no APR/lockup signal or data marked unreliable. Cannot assess reward-lockup discount for this position."
    ],
    "timestamp": 1783931471.1515877
  },
  {
    "name": "UNKNOWN",
    "total_apr_pct": 0.0,
    "liquid_apr_pct": 0.0,
    "reward_apr_pct": 0.0,
    "lockup_days": 0.0,
    "discount_rate_pct": 15.0,
    "annual_vol_pct": 0.0,
    "early_exit_penalty_pct": 0.0,
    "liquid_unlock_fraction": 0.0,
    "data_quality_ok": true,
    "reward_share_of_apr_pct": 0.0,
    "lockup_discount_factor": 1.0,
    "realisable_reward_apr_pct": 0.0,
    "lockup_adjusted_apr_pct": 0.0,
    "headline_vs_realisable_gap_pct": 0.0,
    "paper_yield_share_pct": 0.0,
    "reward_realisability_score": 0.0,
    "classification": "DEEPLY_LOCKED",
    "grade": "F",
    "flags": [
      "INSUFFICIENT_DATA"
    ],
    "recommendations": [
      "Insufficient data: no APR/lockup signal or data marked unreliable. Cannot assess reward-lockup discount for this position."
    ],
    "timestamp": 1783931471.3206358
  },
  {
    "name": "UNKNOWN",
    "total_apr_pct": 0.0,
    "liquid_apr_pct": 0.0,
    "reward_apr_pct": 0.0,
    "lockup_days": 0.0,
    "discount_rate_pct": 15.0,
    "annual_vol_pct": 0.0,
    "early_exit_penalty_pct": 0.0,
    "liquid_unlock_fraction": 0.0,
    "data_quality_ok": true,
    "reward_share_of_apr_pct": 0.0,
    "lockup_discount_factor": 1.0,
    "realisable_reward_apr_pct": 0.0,
    "lockup_adjusted_apr_pct": 0.0,
    "headline_vs_realisable_gap_pct": 0.0,
    "paper_yield_share_pct": 0.0,
    "reward_realisability_score": 0.0,
    "classification": "DEEPLY_LOCKED",
    "grade": "F",
    "flags": [
      "INSUFFICIENT_DATA"
    ],
    "recommendations": [
      "Insufficient data: no APR/lockup signal or data marked unreliable. Cannot assess reward-lockup discount for this position."
    ],
    "timestamp": 1783931471.6034775
  },
  {
    "name": "UNKNOWN",
    "total_apr_pct": 0.0,
    "liquid_apr_pct": 0.0,
    "reward_apr_pct": 0.0,
    "lockup_days": 0.0,
    "discount_rate_pct": 15.0,
    "annual_vol_pct": 0.0,
    "early_exit_penalty_pct": 0.0,
    "liquid_unlock_fraction": 0.0,
    "data_quality_ok": true,
    "reward_share_of_apr_pct": 0.0,
    "lockup_discount_factor": 1.0,
    "realisable_reward_apr_pct": 0.0,
    "lockup_adjusted_apr_pct": 0.0,
    "headline_vs_realisable_gap_pct": 0.0,
    "paper_yield_share_pct": 0.0,
    "reward_realisability_score": 0.0,
    "classification": "DEEPLY_LOCKED",
    "grade": "F",
    "flags": [
      "INSUFFICIENT_DATA"
    ],
    "recommendations": [
      "Insufficient data: no APR/lockup signal or data marked unreliable. Cannot assess reward-lockup discount for this position."
    ],
    "timestamp": 1783931471.7700143
  },
  {
    "name": "UNKNOWN",
    "total_apr_pct": 0.0,
    "liquid_apr_pct": 0.0,
    "reward_apr_pct": 0.0,
    "lockup_days": 0.0,
    "discount_rate_pct": 15.0,
    "annual_vol_pct": 0.0,
    "early_exit_penalty_pct": 0.0,
    "liquid_unlock_fraction": 0.0,
    "data_quality_ok": true,
    "reward_share_of_apr_pct": 0.0,
    "lockup_discount_factor": 1.0,
    "realisable_reward_apr_pct": 0.0,
    "lockup_adjusted_apr_pct": 0.0,
    "headline_vs_realisable_gap_pct": 0.0,
    "paper_yield_share_pct": 0.0,
    "reward_realisability_score": 0.0,
    "classification": "DEEPLY_LOCKED",
    "grade": "F",
    "flags": [
      "INSUFFICIENT_DATA"
    ],
    "recommendations": [
      "Insufficient data: no APR/lockup signal or data marked unreliable. Cannot assess reward-lockup discount for this position."
    ],
    "timestamp": 1783931472.0471518
  },
  {
    "name": "UNKNOWN",
    "total_apr_pct": 0.0,
    "liquid_apr_pct": 0.0,
    "reward_apr_pct": 0.0,
    "lockup_days": 0.0,
    "discount_rate_pct": 15.0,
    "annual_vol_pct": 0.0,
    "early_exit_penalty_pct": 0.0,
    "liquid_unlock_fraction": 0.0,
    "data_quality_ok": true,
    "reward_share_of_apr_pct": 0.0,
    "lockup_discount_factor": 1.0,
    "realisable_reward_apr_pct": 0.0,
    "lockup_adjusted_apr_pct": 0.0,
    "headline_vs_realisable_gap_pct": 0.0,
    "paper_yield_share_pct": 0.0,
    "reward_realisability_score": 0.0,
    "classification": "DEEPLY_LOCKED",
    "grade": "F",
    "flags": [
      "INSUFFICIENT_DATA"
    ],
    "recommendations": [
      "Insufficient data: no APR/lockup signal or data marked unreliable. Cannot assess reward-lockup discount for this position."
    ],
    "timestamp": 1783931472.2482238
  },
  {
    "name": "UNKNOWN",
    "total_apr_pct": 0.0,
    "liquid_apr_pct": 0.0,
    "reward_apr_pct": 0.0,
    "lockup_days": 0.0,
    "discount_rate_pct": 15.0,
    "annual_vol_pct": 0.0,
    "early_exit_penalty_pct": 0.0,
    "liquid_unlock_fraction": 0.0,
    "data_quality_ok": true,
    "reward_share_of_apr_pct": 0.0,
    "lockup_discount_factor": 1.0,
    "realisable_reward_apr_pct": 0.0,
    "lockup_adjusted_apr_pct": 0.0,
    "headline_vs_realisable_gap_pct": 0.0,
    "paper_yield_share_pct": 0.0,
    "reward_realisability_score": 0.0,
    "classification": "DEEPLY_LOCKED",
    "grade": "F",
    "flags": [
      "INSUFFICIENT_DATA"
    ],
    "recommendations": [
      "Insufficient data: no APR/lockup signal or data marked unreliable. Cannot assess reward-lockup discount for this position."
    ],
    "timestamp": 1783931472.5502863
  },
  {
    "name": "UNKNOWN",
    "total_apr_pct": 0.0,
    "liquid_apr_pct": 0.0,
    "reward_apr_pct": 0.0,
    "lockup_days": 0.0,
    "discount_rate_pct": 15.0,
    "annual_vol_pct": 0.0,
    "early_exit_penalty_pct": 0.0,
    "liquid_unlock_fraction": 0.0,
    "data_quality_ok": true,
    "reward_share_of_apr_pct": 0.0,
    "lockup_discount_factor": 1.0,
    "realisable_reward_apr_pct": 0.0,
    "lockup_adjusted_apr_pct": 0.0,
    "headline_vs_realisable_gap_pct": 0.0,
    "paper_yield_share_pct": 0.0,
    "reward_realisability_score": 0.0,
    "classification": "DEEPLY_LOCKED",
    "grade": "F",
    "flags": [
      "INSUFFICIENT_DATA"
    ],
    "recommendations": [
      "Insufficient data: no APR/lockup signal or data marked unreliable. Cannot assess reward-lockup discount for this position."
    ],
    "timestamp": 1783931472.7710114
  },
  {
    "name": "UNKNOWN",
    "total_apr_pct": 0.0,
    "liquid_apr_pct": 0.0,
    "reward_apr_pct": 0.0,
    "lockup_days": 0.0,
    "discount_rate_pct": 15.0,
    "annual_vol_pct": 0.0,
    "early_exit_penalty_pct": 0.0,
    "liquid_unlock_fraction": 0.0,
    "data_quality_ok": true,
    "reward_share_of_apr_pct": 0.0,
    "lockup_discount_factor": 1.0,
    "realisable_reward_apr_pct": 0.0,
    "lockup_adjusted_apr_pct": 0.0,
    "headline_vs_realisable_gap_pct": 0.0,
    "paper_yield_share_pct": 0.0,
    "reward_realisability_score": 0.0,
    "classification": "DEEPLY_LOCKED",
    "grade": "F",
    "flags": [
      "INSUFFICIENT_DATA"
    ],
    "recommendations": [
      "Insufficient data: no APR/lockup signal or data marked unreliable. Cannot assess reward-lockup discount for this position."
    ],
    "timestamp": 1783931473.0878315
  },
  {
    "name": "UNKNOWN",
    "total_apr_pct": 0.0,
    "liquid_apr_pct": 0.0,
    "reward_apr_pct": 0.0,
    "lockup_days": 0.0,
    "discount_rate_pct": 15.0,
    "annual_vol_pct": 0.0,
    "early_exit_penalty_pct": 0.0,
    "liquid_unlock_fraction": 0.0,
    "data_quality_ok": true,
    "reward_share_of_apr_pct": 0.0,
    "lockup_discount_factor": 1.0,
    "realisable_reward_apr_pct": 0.0,
    "lockup_adjusted_apr_pct": 0.0,
    "headline_vs_realisable_gap_pct": 0.0,
    "paper_yield_share_pct": 0.0,
    "reward_realisability_score": 0.0,
    "classification": "DEEPLY_LOCKED",
    "grade": "F",
    "flags": [
      "INSUFFICIENT_DATA"
    ],
    "recommendations": [
      "Insufficient data: no APR/lockup signal or data marked unreliable. Cannot assess reward-lockup discount for this position."
    ],
    "timestamp": 1783931473.3140063
  },
  {
    "name": "UNKNOWN",
    "total_apr_pct": 0.0,
    "liquid_apr_pct": 0.0,
    "reward_apr_pct": 0.0,
    "lockup_days": 0.0,
    "discount_rate_pct": 15.0,
    "annual_vol_pct": 0.0,
    "early_exit_penalty_pct": 0.0,
    "liquid_unlock_fraction": 0.0,
    "data_quality_ok": true,
    "reward_share_of_apr_pct": 0.0,
    "lockup_discount_factor": 1.0,
    "realisable_reward_apr_pct": 0.0,
    "lockup_adjusted_apr_pct": 0.0,
    "headline_vs_realisable_gap_pct": 0.0,
    "paper_yield_share_pct": 0.0,
    "reward_realisability_score": 0.0,
    "classification": "DEEPLY_LOCKED",
    "grade": "F",
    "flags": [
      "INSUFFICIENT_DATA"
    ],
    "recommendations": [
      "Insufficient data: no APR/lockup signal or data marked unreliable. Cannot assess reward-lockup discount for this position."
    ],
    "timestamp": 1783931473.5973396
  },
  {
    "name": "UNKNOWN",
    "total_apr_pct": 0.0,
    "liquid_apr_pct": 0.0,
    "reward_apr_pct": 0.0,
    "lockup_days": 0.0,
    "discount_rate_pct": 15.0,
    "annual_vol_pct": 0.0,
    "early_exit_penalty_pct": 0.0,
    "liquid_unlock_fraction": 0.0,
    "data_quality_ok": true,
    "reward_share_of_apr_pct": 0.0,
    "lockup_discount_factor": 1.0,
    "realisable_reward_apr_pct": 0.0,
    "lockup_adjusted_apr_pct": 0.0,
    "headline_vs_realisable_gap_pct": 0.0,
    "paper_yield_share_pct": 0.0,
    "reward_realisability_score": 0.0,
    "classification": "DEEPLY_LOCKED",
    "grade": "F",
    "flags": [
      "INSUFFICIENT_DATA"
    ],
    "recommendations": [
      "Insufficient data: no APR/lockup signal or data marked unreliable. Cannot assess reward-lockup discount for this position."
    ],
    "timestamp": 1783931473.784076
  },
  {
    "name": "UNKNOWN",
    "total_apr_pct": 0.0,
    "liquid_apr_pct": 0.0,
    "reward_apr_pct": 0.0,
    "lockup_days": 0.0,
    "discount_rate_pct": 15.0,
    "annual_vol_pct": 0.0,
    "early_exit_penalty_pct": 0.0,
    "liquid_unlock_fraction": 0.0,
    "data_quality_ok": true,
    "reward_share_of_apr_pct": 0.0,
    "lockup_discount_factor": 1.0,
    "realisable_reward_apr_pct": 0.0,
    "lockup_adjusted_apr_pct": 0.0,
    "headline_vs_realisable_gap_pct": 0.0,
    "paper_yield_share_pct": 0.0,
    "reward_realisability_score": 0.0,
    "classification": "DEEPLY_LOCKED",
    "grade": "F",
    "flags": [
      "INSUFFICIENT_DATA"
    ],
    "recommendations": [
      "Insufficient data: no APR/lockup signal or data marked unreliable. Cannot assess reward-lockup discount for this position."
    ],
    "timestamp": 1783931474.0708025
  },
  {
    "name": "UNKNOWN",
    "total_apr_pct": 0.0,
    "liquid_apr_pct": 0.0,
    "reward_apr_pct": 0.0,
    "lockup_days": 0.0,
    "discount_rate_pct": 15.0,
    "annual_vol_pct": 0.0,
    "early_exit_penalty_pct": 0.0,
    "liquid_unlock_fraction": 0.0,
    "data_quality_ok": true,
    "reward_share_of_apr_pct": 0.0,
    "lockup_discount_factor": 1.0,
    "realisable_reward_apr_pct": 0.0,
    "lockup_adjusted_apr_pct": 0.0,
    "headline_vs_realisable_gap_pct": 0.0,
    "paper_yield_share_pct": 0.0,
    "reward_realisability_score": 0.0,
    "classification": "DEEPLY_LOCKED",
    "grade": "F",
    "flags": [
      "INSUFFICIENT_DATA"
    ],
    "recommendations": [
      "Insufficient data: no APR/lockup signal or data marked unreliable. Cannot assess reward-lockup discount for this position."
    ],
    "timestamp": 1783931476.725532
  },
  {
    "name": "UNKNOWN",
    "total_apr_pct": 0.0,
    "liquid_apr_pct": 0.0,
    "reward_apr_pct": 0.0,
    "lockup_days": 0.0,
    "discount_rate_pct": 15.0,
    "annual_vol_pct": 0.0,
    "early_exit_penalty_pct": 0.0,
    "liquid_unlock_fraction": 0.0,
    "data_quality_ok": true,
    "reward_share_of_apr_pct": 0.0,
    "lockup_discount_factor": 1.0,
    "realisable_reward_apr_pct": 0.0,
    "lockup_adjusted_apr_pct": 0.0,
    "headline_vs_realisable_gap_pct": 0.0,
    "paper_yield_share_pct": 0.0,
    "reward_realisability_score": 0.0,
    "classification": "DEEPLY_LOCKED",
    "grade": "F",
    "flags": [
      "INSUFFICIENT_DATA"
    ],
    "recommendations": [
      "Insufficient data: no APR/lockup signal or data marked unreliable. Cannot assess reward-lockup discount for this position."
    ],
    "timestamp": 1783931476.850657
  },
  {
    "name": "UNKNOWN",
    "total_apr_pct": 0.0,
    "liquid_apr_pct": 0.0,
    "reward_apr_pct": 0.0,
    "lockup_days": 0.0,
    "discount_rate_pct": 15.0,
    "annual_vol_pct": 0.0,
    "early_exit_penalty_pct": 0.0,
    "liquid_unlock_fraction": 0.0,
    "data_quality_ok": true,
    "reward_share_of_apr_pct": 0.0,
    "lockup_discount_factor": 1.0,
    "realisable_reward_apr_pct": 0.0,
    "lockup_adjusted_apr_pct": 0.0,
    "headline_vs_realisable_gap_pct": 0.0,
    "paper_yield_share_pct": 0.0,
    "reward_realisability_score": 0.0,
    "classification": "DEEPLY_LOCKED",
    "grade": "F",
    "flags": [
      "INSUFFICIENT_DATA"
    ],
    "recommendations": [
      "Insufficient data: no APR/lockup signal or data marked unreliable. Cannot assess reward-lockup discount for this position."
    ],
    "timestamp": 1783931477.2286806
  },
  {
    "name": "UNKNOWN",
    "total_apr_pct": 0.0,
    "liquid_apr_pct": 0.0,
    "reward_apr_pct": 0.0,
    "lockup_days": 0.0,
    "discount_rate_pct": 15.0,
    "annual_vol_pct": 0.0,
    "early_exit_penalty_pct": 0.0,
    "liquid_unlock_fraction": 0.0,
    "data_quality_ok": true,
    "reward_share_of_apr_pct": 0.0,
    "lockup_discount_factor": 1.0,
    "realisable_reward_apr_pct": 0.0,
    "lockup_adjusted_apr_pct": 0.0,
    "headline_vs_realisable_gap_pct": 0.0,
    "paper_yield_share_pct": 0.0,
    "reward_realisability_score": 0.0,
    "classification": "DEEPLY_LOCKED",
    "grade": "F",
    "flags": [
      "INSUFFICIENT_DATA"
    ],
    "recommendations": [
      "Insufficient data: no APR/lockup signal or data marked unreliable. Cannot assess reward-lockup discount for this position."
    ],
    "timestamp": 1783931477.34054
  },
  {
    "name": "UNKNOWN",
    "total_apr_pct": 0.0,
    "liquid_apr_pct": 0.0,
    "reward_apr_pct": 0.0,
    "lockup_days": 0.0,
    "discount_rate_pct": 15.0,
    "annual_vol_pct": 0.0,
    "early_exit_penalty_pct": 0.0,
    "liquid_unlock_fraction": 0.0,
    "data_quality_ok": true,
    "reward_share_of_apr_pct": 0.0,
    "lockup_discount_factor": 1.0,
    "realisable_reward_apr_pct": 0.0,
    "lockup_adjusted_apr_pct": 0.0,
    "headline_vs_realisable_gap_pct": 0.0,
    "paper_yield_share_pct": 0.0,
    "reward_realisability_score": 0.0,
    "classification": "DEEPLY_LOCKED",
    "grade": "F",
    "flags": [
      "INSUFFICIENT_DATA"
    ],
    "recommendations": [
      "Insufficient data: no APR/lockup signal or data marked unreliable. Cannot assess reward-lockup discount for this position."
    ],
    "timestamp": 1783931477.707057
  },
  {
    "name": "UNKNOWN",
    "total_apr_pct": 0.0,
    "liquid_apr_pct": 0.0,
    "reward_apr_pct": 0.0,
    "lockup_days": 0.0,
    "discount_rate_pct": 15.0,
    "annual_vol_pct": 0.0,
    "early_exit_penalty_pct": 0.0,
    "liquid_unlock_fraction": 0.0,
    "data_quality_ok": true,
    "reward_share_of_apr_pct": 0.0,
    "lockup_discount_factor": 1.0,
    "realisable_reward_apr_pct": 0.0,
    "lockup_adjusted_apr_pct": 0.0,
    "headline_vs_realisable_gap_pct": 0.0,
    "paper_yield_share_pct": 0.0,
    "reward_realisability_score": 0.0,
    "classification": "DEEPLY_LOCKED",
    "grade": "F",
    "flags": [
      "INSUFFICIENT_DATA"
    ],
    "recommendations": [
      "Insufficient data: no APR/lockup signal or data marked unreliable. Cannot assess reward-lockup discount for this position."
    ],
    "timestamp": 1783931477.8055546
  },
  {
    "name": "UNKNOWN",
    "total_apr_pct": 0.0,
    "liquid_apr_pct": 0.0,
    "reward_apr_pct": 0.0,
    "lockup_days": 0.0,
    "discount_rate_pct": 15.0,
    "annual_vol_pct": 0.0,
    "early_exit_penalty_pct": 0.0,
    "liquid_unlock_fraction": 0.0,
    "data_quality_ok": true,
    "reward_share_of_apr_pct": 0.0,
    "lockup_discount_factor": 1.0,
    "realisable_reward_apr_pct": 0.0,
    "lockup_adjusted_apr_pct": 0.0,
    "headline_vs_realisable_gap_pct": 0.0,
    "paper_yield_share_pct": 0.0,
    "reward_realisability_score": 0.0,
    "classification": "DEEPLY_LOCKED",
    "grade": "F",
    "flags": [
      "INSUFFICIENT_DATA"
    ],
    "recommendations": [
      "Insufficient data: no APR/lockup signal or data marked unreliable. Cannot assess reward-lockup discount for this position."
    ],
    "timestamp": 1783931478.1775758
  },
  {
    "name": "UNKNOWN",
    "total_apr_pct": 0.0,
    "liquid_apr_pct": 0.0,
    "reward_apr_pct": 0.0,
    "lockup_days": 0.0,
    "discount_rate_pct": 15.0,
    "annual_vol_pct": 0.0,
    "early_exit_penalty_pct": 0.0,
    "liquid_unlock_fraction": 0.0,
    "data_quality_ok": true,
    "reward_share_of_apr_pct": 0.0,
    "lockup_discount_factor": 1.0,
    "realisable_reward_apr_pct": 0.0,
    "lockup_adjusted_apr_pct": 0.0,
    "headline_vs_realisable_gap_pct": 0.0,
    "paper_yield_share_pct": 0.0,
    "reward_realisability_score": 0.0,
    "classification": "DEEPLY_LOCKED",
    "grade": "F",
    "flags": [
      "INSUFFICIENT_DATA"
    ],
    "recommendations": [
      "Insufficient data: no APR/lockup signal or data marked unreliable. Cannot assess reward-lockup discount for this position."
    ],
    "timestamp": 1783931478.2697785
  },
  {
    "name": "UNKNOWN",
    "total_apr_pct": 0.0,
    "liquid_apr_pct": 0.0,
    "reward_apr_pct": 0.0,
    "lockup_days": 0.0,
    "discount_rate_pct": 15.0,
    "annual_vol_pct": 0.0,
    "early_exit_penalty_pct": 0.0,
    "liquid_unlock_fraction": 0.0,
    "data_quality_ok": true,
    "reward_share_of_apr_pct": 0.0,
    "lockup_discount_factor": 1.0,
    "realisable_reward_apr_pct": 0.0,
    "lockup_adjusted_apr_pct": 0.0,
    "headline_vs_realisable_gap_pct": 0.0,
    "paper_yield_share_pct": 0.0,
    "reward_realisability_score": 0.0,
    "classification": "DEEPLY_LOCKED",
    "grade": "F",
    "flags": [
      "INSUFFICIENT_DATA"
    ],
    "recommendations": [
      "Insufficient data: no APR/lockup signal or data marked unreliable. Cannot assess reward-lockup discount for this position."
    ],
    "timestamp": 1783931478.6364093
  },
  {
    "name": "UNKNOWN",
    "total_apr_pct": 0.0,
    "liquid_apr_pct": 0.0,
    "reward_apr_pct": 0.0,
    "lockup_days": 0.0,
    "discount_rate_pct": 15.0,
    "annual_vol_pct": 0.0,
    "early_exit_penalty_pct": 0.0,
    "liquid_unlock_fraction": 0.0,
    "data_quality_ok": true,
    "reward_share_of_apr_pct": 0.0,
    "lockup_discount_factor": 1.0,
    "realisable_reward_apr_pct": 0.0,
    "lockup_adjusted_apr_pct": 0.0,
    "headline_vs_realisable_gap_pct": 0.0,
    "paper_yield_share_pct": 0.0,
    "reward_realisability_score": 0.0,
    "classification": "DEEPLY_LOCKED",
    "grade": "F",
    "flags": [
      "INSUFFICIENT_DATA"
    ],
    "recommendations": [
      "Insufficient data: no APR/lockup signal or data marked unreliable. Cannot assess reward-lockup discount for this position."
    ],
    "timestamp": 1783931478.7271419
  },
  {
    "name": "UNKNOWN",
    "total_apr_pct": 0.0,
    "liquid_apr_pct": 0.0,
    "reward_apr_pct": 0.0,
    "lockup_days": 0.0,
    "discount_rate_pct": 15.0,
    "annual_vol_pct": 0.0,
    "early_exit_penalty_pct": 0.0,
    "liquid_unlock_fraction": 0.0,
    "data_quality_ok": true,
    "reward_share_of_apr_pct": 0.0,
    "lockup_discount_factor": 1.0,
    "realisable_reward_apr_pct": 0.0,
    "lockup_adjusted_apr_pct": 0.0,
    "headline_vs_realisable_gap_pct": 0.0,
    "paper_yield_share_pct": 0.0,
    "reward_realisability_score": 0.0,
    "classification": "DEEPLY_LOCKED",
    "grade": "F",
    "flags": [
      "INSUFFICIENT_DATA"
    ],
    "recommendations": [
      "Insufficient data: no APR/lockup signal or data marked unreliable. Cannot assess reward-lockup discount for this position."
    ],
    "timestamp": 1783931479.1219885
  },
  {
    "name": "UNKNOWN",
    "total_apr_pct": 0.0,
    "liquid_apr_pct": 0.0,
    "reward_apr_pct": 0.0,
    "lockup_days": 0.0,
    "discount_rate_pct": 15.0,
    "annual_vol_pct": 0.0,
    "early_exit_penalty_pct": 0.0,
    "liquid_unlock_fraction": 0.0,
    "data_quality_ok": true,
    "reward_share_of_apr_pct": 0.0,
    "lockup_discount_factor": 1.0,
    "realisable_reward_apr_pct": 0.0,
    "lockup_adjusted_apr_pct": 0.0,
    "headline_vs_realisable_gap_pct": 0.0,
    "paper_yield_share_pct": 0.0,
    "reward_realisability_score": 0.0,
    "classification": "DEEPLY_LOCKED",
    "grade": "F",
    "flags": [
      "INSUFFICIENT_DATA"
    ],
    "recommendations": [
      "Insufficient data: no APR/lockup signal or data marked unreliable. Cannot assess reward-lockup discount for this position."
    ],
    "timestamp": 1783931479.2004762
  },
  {
    "name": "UNKNOWN",
    "total_apr_pct": 0.0,
    "liquid_apr_pct": 0.0,
    "reward_apr_pct": 0.0,
    "lockup_days": 0.0,
    "discount_rate_pct": 15.0,
    "annual_vol_pct": 0.0,
    "early_exit_penalty_pct": 0.0,
    "liquid_unlock_fraction": 0.0,
    "data_quality_ok": true,
    "reward_share_of_apr_pct": 0.0,
    "lockup_discount_factor": 1.0,
    "realisable_reward_apr_pct": 0.0,
    "lockup_adjusted_apr_pct": 0.0,
    "headline_vs_realisable_gap_pct": 0.0,
    "paper_yield_share_pct": 0.0,
    "reward_realisability_score": 0.0,
    "classification": "DEEPLY_LOCKED",
    "grade": "F",
    "flags": [
      "INSUFFICIENT_DATA"
    ],
    "recommendations": [
      "Insufficient data: no APR/lockup signal or data marked unreliable. Cannot assess reward-lockup discount for this position."
    ],
    "timestamp": 1783931479.5749323
  },
  {
    "name": "UNKNOWN",
    "total_apr_pct": 0.0,
    "liquid_apr_pct": 0.0,
    "reward_apr_pct": 0.0,
    "lockup_days": 0.0,
    "discount_rate_pct": 15.0,
    "annual_vol_pct": 0.0,
    "early_exit_penalty_pct": 0.0,
    "liquid_unlock_fraction": 0.0,
    "data_quality_ok": true,
    "reward_share_of_apr_pct": 0.0,
    "lockup_discount_factor": 1.0,
    "realisable_reward_apr_pct": 0.0,
    "lockup_adjusted_apr_pct": 0.0,
    "headline_vs_realisable_gap_pct": 0.0,
    "paper_yield_share_pct": 0.0,
    "reward_realisability_score": 0.0,
    "classification": "DEEPLY_LOCKED",
    "grade": "F",
    "flags": [
      "INSUFFICIENT_DATA"
    ],
    "recommendations": [
      "Insufficient data: no APR/lockup signal or data marked unreliable. Cannot assess reward-lockup discount for this position."
    ],
    "timestamp": 1783931479.6485481
  },
  {
    "name": "UNKNOWN",
    "total_apr_pct": 0.0,
    "liquid_apr_pct": 0.0,
    "reward_apr_pct": 0.0,
    "lockup_days": 0.0,
    "discount_rate_pct": 15.0,
    "annual_vol_pct": 0.0,
    "early_exit_penalty_pct": 0.0,
    "liquid_unlock_fraction": 0.0,
    "data_quality_ok": true,
    "reward_share_of_apr_pct": 0.0,
    "lockup_discount_factor": 1.0,
    "realisable_reward_apr_pct": 0.0,
    "lockup_adjusted_apr_pct": 0.0,
    "headline_vs_realisable_gap_pct": 0.0,
    "paper_yield_share_pct": 0.0,
    "reward_realisability_score": 0.0,
    "classification": "DEEPLY_LOCKED",
    "grade": "F",
    "flags": [
      "INSUFFICIENT_DATA"
    ],
    "recommendations": [
      "Insufficient data: no APR/lockup signal or data marked unreliable. Cannot assess reward-lockup discount for this position."
    ],
    "timestamp": 1783931480.0307693
  },
  {
    "name": "UNKNOWN",
    "total_apr_pct": 0.0,
    "liquid_apr_pct": 0.0,
    "reward_apr_pct": 0.0,
    "lockup_days": 0.0,
    "discount_rate_pct": 15.0,
    "annual_vol_pct": 0.0,
    "early_exit_penalty_pct": 0.0,
    "liquid_unlock_fraction": 0.0,
    "data_quality_ok": true,
    "reward_share_of_apr_pct": 0.0,
    "lockup_discount_factor": 1.0,
    "realisable_reward_apr_pct": 0.0,
    "lockup_adjusted_apr_pct": 0.0,
    "headline_vs_realisable_gap_pct": 0.0,
    "paper_yield_share_pct": 0.0,
    "reward_realisability_score": 0.0,
    "classification": "DEEPLY_LOCKED",
    "grade": "F",
    "flags": [
      "INSUFFICIENT_DATA"
    ],
    "recommendations": [
      "Insufficient data: no APR/lockup signal or data marked unreliable. Cannot assess reward-lockup discount for this position."
    ],
    "timestamp": 1783931480.1066546
  },
  {
    "name": "UNKNOWN",
    "total_apr_pct": 0.0,
    "liquid_apr_pct": 0.0,
    "reward_apr_pct": 0.0,
    "lockup_days": 0.0,
    "discount_rate_pct": 15.0,
    "annual_vol_pct": 0.0,
    "early_exit_penalty_pct": 0.0,
    "liquid_unlock_fraction": 0.0,
    "data_quality_ok": true,
    "reward_share_of_apr_pct": 0.0,
    "lockup_discount_factor": 1.0,
    "realisable_reward_apr_pct": 0.0,
    "lockup_adjusted_apr_pct": 0.0,
    "headline_vs_realisable_gap_pct": 0.0,
    "paper_yield_share_pct": 0.0,
    "reward_realisability_score": 0.0,
    "classification": "DEEPLY_LOCKED",
    "grade": "F",
    "flags": [
      "INSUFFICIENT_DATA"
    ],
    "recommendations": [
      "Insufficient data: no APR/lockup signal or data marked unreliable. Cannot assess reward-lockup discount for this position."
    ],
    "timestamp": 1783931482.7989533
  },
  {
    "name": "UNKNOWN",
    "total_apr_pct": 0.0,
    "liquid_apr_pct": 0.0,
    "reward_apr_pct": 0.0,
    "lockup_days": 0.0,
    "discount_rate_pct": 15.0,
    "annual_vol_pct": 0.0,
    "early_exit_penalty_pct": 0.0,
    "liquid_unlock_fraction": 0.0,
    "data_quality_ok": true,
    "reward_share_of_apr_pct": 0.0,
    "lockup_discount_factor": 1.0,
    "realisable_reward_apr_pct": 0.0,
    "lockup_adjusted_apr_pct": 0.0,
    "headline_vs_realisable_gap_pct": 0.0,
    "paper_yield_share_pct": 0.0,
    "reward_realisability_score": 0.0,
    "classification": "DEEPLY_LOCKED",
    "grade": "F",
    "flags": [
      "INSUFFICIENT_DATA"
    ],
    "recommendations": [
      "Insufficient data: no APR/lockup signal or data marked unreliable. Cannot assess reward-lockup discount for this position."
    ],
    "timestamp": 1783931482.8349154
  },
  {
    "name": "UNKNOWN",
    "total_apr_pct": 0.0,
    "liquid_apr_pct": 0.0,
    "reward_apr_pct": 0.0,
    "lockup_days": 0.0,
    "discount_rate_pct": 15.0,
    "annual_vol_pct": 0.0,
    "early_exit_penalty_pct": 0.0,
    "liquid_unlock_fraction": 0.0,
    "data_quality_ok": true,
    "reward_share_of_apr_pct": 0.0,
    "lockup_discount_factor": 1.0,
    "realisable_reward_apr_pct": 0.0,
    "lockup_adjusted_apr_pct": 0.0,
    "headline_vs_realisable_gap_pct": 0.0,
    "paper_yield_share_pct": 0.0,
    "reward_realisability_score": 0.0,
    "classification": "DEEPLY_LOCKED",
    "grade": "F",
    "flags": [
      "INSUFFICIENT_DATA"
    ],
    "recommendations": [
      "Insufficient data: no APR/lockup signal or data marked unreliable. Cannot assess reward-lockup discount for this position."
    ],
    "timestamp": 1783931483.1761835
  },
  {
    "name": "UNKNOWN",
    "total_apr_pct": 0.0,
    "liquid_apr_pct": 0.0,
    "reward_apr_pct": 0.0,
    "lockup_days": 0.0,
    "discount_rate_pct": 15.0,
    "annual_vol_pct": 0.0,
    "early_exit_penalty_pct": 0.0,
    "liquid_unlock_fraction": 0.0,
    "data_quality_ok": true,
    "reward_share_of_apr_pct": 0.0,
    "lockup_discount_factor": 1.0,
    "realisable_reward_apr_pct": 0.0,
    "lockup_adjusted_apr_pct": 0.0,
    "headline_vs_realisable_gap_pct": 0.0,
    "paper_yield_share_pct": 0.0,
    "reward_realisability_score": 0.0,
    "classification": "DEEPLY_LOCKED",
    "grade": "F",
    "flags": [
      "INSUFFICIENT_DATA"
    ],
    "recommendations": [
      "Insufficient data: no APR/lockup signal or data marked unreliable. Cannot assess reward-lockup discount for this position."
    ],
    "timestamp": 1783931483.217095
  },
  {
    "name": "UNKNOWN",
    "total_apr_pct": 0.0,
    "liquid_apr_pct": 0.0,
    "reward_apr_pct": 0.0,
    "lockup_days": 0.0,
    "discount_rate_pct": 15.0,
    "annual_vol_pct": 0.0,
    "early_exit_penalty_pct": 0.0,
    "liquid_unlock_fraction": 0.0,
    "data_quality_ok": true,
    "reward_share_of_apr_pct": 0.0,
    "lockup_discount_factor": 1.0,
    "realisable_reward_apr_pct": 0.0,
    "lockup_adjusted_apr_pct": 0.0,
    "headline_vs_realisable_gap_pct": 0.0,
    "paper_yield_share_pct": 0.0,
    "reward_realisability_score": 0.0,
    "classification": "DEEPLY_LOCKED",
    "grade": "F",
    "flags": [
      "INSUFFICIENT_DATA"
    ],
    "recommendations": [
      "Insufficient data: no APR/lockup signal or data marked unreliable. Cannot assess reward-lockup discount for this position."
    ],
    "timestamp": 1783931483.5802717
  },
  {
    "name": "UNKNOWN",
    "total_apr_pct": 0.0,
    "liquid_apr_pct": 0.0,
    "reward_apr_pct": 0.0,
    "lockup_days": 0.0,
    "discount_rate_pct": 15.0,
    "annual_vol_pct": 0.0,
    "early_exit_penalty_pct": 0.0,
    "liquid_unlock_fraction": 0.0,
    "data_quality_ok": true,
    "reward_share_of_apr_pct": 0.0,
    "lockup_discount_factor": 1.0,
    "realisable_reward_apr_pct": 0.0,
    "lockup_adjusted_apr_pct": 0.0,
    "headline_vs_realisable_gap_pct": 0.0,
    "paper_yield_share_pct": 0.0,
    "reward_realisability_score": 0.0,
    "classification": "DEEPLY_LOCKED",
    "grade": "F",
    "flags": [
      "INSUFFICIENT_DATA"
    ],
    "recommendations": [
      "Insufficient data: no APR/lockup signal or data marked unreliable. Cannot assess reward-lockup discount for this position."
    ],
    "timestamp": 1783931483.601486
  },
  {
    "name": "UNKNOWN",
    "total_apr_pct": 0.0,
    "liquid_apr_pct": 0.0,
    "reward_apr_pct": 0.0,
    "lockup_days": 0.0,
    "discount_rate_pct": 15.0,
    "annual_vol_pct": 0.0,
    "early_exit_penalty_pct": 0.0,
    "liquid_unlock_fraction": 0.0,
    "data_quality_ok": true,
    "reward_share_of_apr_pct": 0.0,
    "lockup_discount_factor": 1.0,
    "realisable_reward_apr_pct": 0.0,
    "lockup_adjusted_apr_pct": 0.0,
    "headline_vs_realisable_gap_pct": 0.0,
    "paper_yield_share_pct": 0.0,
    "reward_realisability_score": 0.0,
    "classification": "DEEPLY_LOCKED",
    "grade": "F",
    "flags": [
      "INSUFFICIENT_DATA"
    ],
    "recommendations": [
      "Insufficient data: no APR/lockup signal or data marked unreliable. Cannot assess reward-lockup discount for this position."
    ],
    "timestamp": 1783931483.99041
  },
  {
    "name": "UNKNOWN",
    "total_apr_pct": 0.0,
    "liquid_apr_pct": 0.0,
    "reward_apr_pct": 0.0,
    "lockup_days": 0.0,
    "discount_rate_pct": 15.0,
    "annual_vol_pct": 0.0,
    "early_exit_penalty_pct": 0.0,
    "liquid_unlock_fraction": 0.0,
    "data_quality_ok": true,
    "reward_share_of_apr_pct": 0.0,
    "lockup_discount_factor": 1.0,
    "realisable_reward_apr_pct": 0.0,
    "lockup_adjusted_apr_pct": 0.0,
    "headline_vs_realisable_gap_pct": 0.0,
    "paper_yield_share_pct": 0.0,
    "reward_realisability_score": 0.0,
    "classification": "DEEPLY_LOCKED",
    "grade": "F",
    "flags": [
      "INSUFFICIENT_DATA"
    ],
    "recommendations": [
      "Insufficient data: no APR/lockup signal or data marked unreliable. Cannot assess reward-lockup discount for this position."
    ],
    "timestamp": 1783931484.017177
  },
  {
    "name": "UNKNOWN",
    "total_apr_pct": 0.0,
    "liquid_apr_pct": 0.0,
    "reward_apr_pct": 0.0,
    "lockup_days": 0.0,
    "discount_rate_pct": 15.0,
    "annual_vol_pct": 0.0,
    "early_exit_penalty_pct": 0.0,
    "liquid_unlock_fraction": 0.0,
    "data_quality_ok": true,
    "reward_share_of_apr_pct": 0.0,
    "lockup_discount_factor": 1.0,
    "realisable_reward_apr_pct": 0.0,
    "lockup_adjusted_apr_pct": 0.0,
    "headline_vs_realisable_gap_pct": 0.0,
    "paper_yield_share_pct": 0.0,
    "reward_realisability_score": 0.0,
    "classification": "DEEPLY_LOCKED",
    "grade": "F",
    "flags": [
      "INSUFFICIENT_DATA"
    ],
    "recommendations": [
      "Insufficient data: no APR/lockup signal or data marked unreliable. Cannot assess reward-lockup discount for this position."
    ],
    "timestamp": 1783931484.4058654
  },
  {
    "name": "UNKNOWN",
    "total_apr_pct": 0.0,
    "liquid_apr_pct": 0.0,
    "reward_apr_pct": 0.0,
    "lockup_days": 0.0,
    "discount_rate_pct": 15.0,
    "annual_vol_pct": 0.0,
    "early_exit_penalty_pct": 0.0,
    "liquid_unlock_fraction": 0.0,
    "data_quality_ok": true,
    "reward_share_of_apr_pct": 0.0,
    "lockup_discount_factor": 1.0,
    "realisable_reward_apr_pct": 0.0,
    "lockup_adjusted_apr_pct": 0.0,
    "headline_vs_realisable_gap_pct": 0.0,
    "paper_yield_share_pct": 0.0,
    "reward_realisability_score": 0.0,
    "classification": "DEEPLY_LOCKED",
    "grade": "F",
    "flags": [
      "INSUFFICIENT_DATA"
    ],
    "recommendations": [
      "Insufficient data: no APR/lockup signal or data marked unreliable. Cannot assess reward-lockup discount for this position."
    ],
    "timestamp": 1783931484.8102884
  },
  {
    "name": "UNKNOWN",
    "total_apr_pct": 0.0,
    "liquid_apr_pct": 0.0,
    "reward_apr_pct": 0.0,
    "lockup_days": 0.0,
    "discount_rate_pct": 15.0,
    "annual_vol_pct": 0.0,
    "early_exit_penalty_pct": 0.0,
    "liquid_unlock_fraction": 0.0,
    "data_quality_ok": true,
    "reward_share_of_apr_pct": 0.0,
    "lockup_discount_factor": 1.0,
    "realisable_reward_apr_pct": 0.0,
    "lockup_adjusted_apr_pct": 0.0,
    "headline_vs_realisable_gap_pct": 0.0,
    "paper_yield_share_pct": 0.0,
    "reward_realisability_score": 0.0,
    "classification": "DEEPLY_LOCKED",
    "grade": "F",
    "flags": [
      "INSUFFICIENT_DATA"
    ],
    "recommendations": [
      "Insufficient data: no APR/lockup signal or data marked unreliable. Cannot assess reward-lockup discount for this position."
    ],
    "timestamp": 1783931485.2392898
  },
  {
    "name": "UNKNOWN",
    "total_apr_pct": 0.0,
    "liquid_apr_pct": 0.0,
    "reward_apr_pct": 0.0,
    "lockup_days": 0.0,
    "discount_rate_pct": 15.0,
    "annual_vol_pct": 0.0,
    "early_exit_penalty_pct": 0.0,
    "liquid_unlock_fraction": 0.0,
    "data_quality_ok": true,
    "reward_share_of_apr_pct": 0.0,
    "lockup_discount_factor": 1.0,
    "realisable_reward_apr_pct": 0.0,
    "lockup_adjusted_apr_pct": 0.0,
    "headline_vs_realisable_gap_pct": 0.0,
    "paper_yield_share_pct": 0.0,
    "reward_realisability_score": 0.0,
    "classification": "DEEPLY_LOCKED",
    "grade": "F",
    "flags": [
      "INSUFFICIENT_DATA"
    ],
    "recommendations": [
      "Insufficient data: no APR/lockup signal or data marked unreliable. Cannot assess reward-lockup discount for this position."
    ],
    "timestamp": 1783931485.4855247
  },
  {
    "name": "UNKNOWN",
    "total_apr_pct": 0.0,
    "liquid_apr_pct": 0.0,
    "reward_apr_pct": 0.0,
    "lockup_days": 0.0,
    "discount_rate_pct": 15.0,
    "annual_vol_pct": 0.0,
    "early_exit_penalty_pct": 0.0,
    "liquid_unlock_fraction": 0.0,
    "data_quality_ok": true,
    "reward_share_of_apr_pct": 0.0,
    "lockup_discount_factor": 1.0,
    "realisable_reward_apr_pct": 0.0,
    "lockup_adjusted_apr_pct": 0.0,
    "headline_vs_realisable_gap_pct": 0.0,
    "paper_yield_share_pct": 0.0,
    "reward_realisability_score": 0.0,
    "classification": "DEEPLY_LOCKED",
    "grade": "F",
    "flags": [
      "INSUFFICIENT_DATA"
    ],
    "recommendations": [
      "Insufficient data: no APR/lockup signal or data marked unreliable. Cannot assess reward-lockup discount for this position."
    ],
    "timestamp": 1783931485.6400962
  },
  {
    "name": "UNKNOWN",
    "total_apr_pct": 0.0,
    "liquid_apr_pct": 0.0,
    "reward_apr_pct": 0.0,
    "lockup_days": 0.0,
    "discount_rate_pct": 15.0,
    "annual_vol_pct": 0.0,
    "early_exit_penalty_pct": 0.0,
    "liquid_unlock_fraction": 0.0,
    "data_quality_ok": true,
    "reward_share_of_apr_pct": 0.0,
    "lockup_discount_factor": 1.0,
    "realisable_reward_apr_pct": 0.0,
    "lockup_adjusted_apr_pct": 0.0,
    "headline_vs_realisable_gap_pct": 0.0,
    "paper_yield_share_pct": 0.0,
    "reward_realisability_score": 0.0,
    "classification": "DEEPLY_LOCKED",
    "grade": "F",
    "flags": [
      "INSUFFICIENT_DATA"
    ],
    "recommendations": [
      "Insufficient data: no APR/lockup signal or data marked unreliable. Cannot assess reward-lockup discount for this position."
    ],
    "timestamp": 1783931485.8846319
  },
  {
    "name": "UNKNOWN",
    "total_apr_pct": 0.0,
    "liquid_apr_pct": 0.0,
    "reward_apr_pct": 0.0,
    "lockup_days": 0.0,
    "discount_rate_pct": 15.0,
    "annual_vol_pct": 0.0,
    "early_exit_penalty_pct": 0.0,
    "liquid_unlock_fraction": 0.0,
    "data_quality_ok": true,
    "reward_share_of_apr_pct": 0.0,
    "lockup_discount_factor": 1.0,
    "realisable_reward_apr_pct": 0.0,
    "lockup_adjusted_apr_pct": 0.0,
    "headline_vs_realisable_gap_pct": 0.0,
    "paper_yield_share_pct": 0.0,
    "reward_realisability_score": 0.0,
    "classification": "DEEPLY_LOCKED",
    "grade": "F",
    "flags": [
      "INSUFFICIENT_DATA"
    ],
    "recommendations": [
      "Insufficient data: no APR/lockup signal or data marked unreliable. Cannot assess reward-lockup discount for this position."
    ],
    "timestamp": 1783931486.3306918
  },
  {
    "name": "UNKNOWN",
    "total_apr_pct": 0.0,
    "liquid_apr_pct": 0.0,
    "reward_apr_pct": 0.0,
    "lockup_days": 0.0,
    "discount_rate_pct": 15.0,
    "annual_vol_pct": 0.0,
    "early_exit_penalty_pct": 0.0,
    "liquid_unlock_fraction": 0.0,
    "data_quality_ok": true,
    "reward_share_of_apr_pct": 0.0,
    "lockup_discount_factor": 1.0,
    "realisable_reward_apr_pct": 0.0,
    "lockup_adjusted_apr_pct": 0.0,
    "headline_vs_realisable_gap_pct": 0.0,
    "paper_yield_share_pct": 0.0,
    "reward_realisability_score": 0.0,
    "classification": "DEEPLY_LOCKED",
    "grade": "F",
    "flags": [
      "INSUFFICIENT_DATA"
    ],
    "recommendations": [
      "Insufficient data: no APR/lockup signal or data marked unreliable. Cannot assess reward-lockup discount for this position."
    ],
    "timestamp": 1783931489.2146258
  },
  {
    "name": "UNKNOWN",
    "total_apr_pct": 0.0,
    "liquid_apr_pct": 0.0,
    "reward_apr_pct": 0.0,
    "lockup_days": 0.0,
    "discount_rate_pct": 15.0,
    "annual_vol_pct": 0.0,
    "early_exit_penalty_pct": 0.0,
    "liquid_unlock_fraction": 0.0,
    "data_quality_ok": true,
    "reward_share_of_apr_pct": 0.0,
    "lockup_discount_factor": 1.0,
    "realisable_reward_apr_pct": 0.0,
    "lockup_adjusted_apr_pct": 0.0,
    "headline_vs_realisable_gap_pct": 0.0,
    "paper_yield_share_pct": 0.0,
    "reward_realisability_score": 0.0,
    "classification": "DEEPLY_LOCKED",
    "grade": "F",
    "flags": [
      "INSUFFICIENT_DATA"
    ],
    "recommendations": [
      "Insufficient data: no APR/lockup signal or data marked unreliable. Cannot assess reward-lockup discount for this position."
    ],
    "timestamp": 1783931489.3690214
  },
  {
    "name": "UNKNOWN",
    "total_apr_pct": 0.0,
    "liquid_apr_pct": 0.0,
    "reward_apr_pct": 0.0,
    "lockup_days": 0.0,
    "discount_rate_pct": 15.0,
    "annual_vol_pct": 0.0,
    "early_exit_penalty_pct": 0.0,
    "liquid_unlock_fraction": 0.0,
    "data_quality_ok": true,
    "reward_share_of_apr_pct": 0.0,
    "lockup_discount_factor": 1.0,
    "realisable_reward_apr_pct": 0.0,
    "lockup_adjusted_apr_pct": 0.0,
    "headline_vs_realisable_gap_pct": 0.0,
    "paper_yield_share_pct": 0.0,
    "reward_realisability_score": 0.0,
    "classification": "DEEPLY_LOCKED",
    "grade": "F",
    "flags": [
      "INSUFFICIENT_DATA"
    ],
    "recommendations": [
      "Insufficient data: no APR/lockup signal or data marked unreliable. Cannot assess reward-lockup discount for this position."
    ],
    "timestamp": 1783931489.6049721
  },
  {
    "name": "UNKNOWN",
    "total_apr_pct": 0.0,
    "liquid_apr_pct": 0.0,
    "reward_apr_pct": 0.0,
    "lockup_days": 0.0,
    "discount_rate_pct": 15.0,
    "annual_vol_pct": 0.0,
    "early_exit_penalty_pct": 0.0,
    "liquid_unlock_fraction": 0.0,
    "data_quality_ok": true,
    "reward_share_of_apr_pct": 0.0,
    "lockup_discount_factor": 1.0,
    "realisable_reward_apr_pct": 0.0,
    "lockup_adjusted_apr_pct": 0.0,
    "headline_vs_realisable_gap_pct": 0.0,
    "paper_yield_share_pct": 0.0,
    "reward_realisability_score": 0.0,
    "classification": "DEEPLY_LOCKED",
    "grade": "F",
    "flags": [
      "INSUFFICIENT_DATA"
    ],
    "recommendations": [
      "Insufficient data: no APR/lockup signal or data marked unreliable. Cannot assess reward-lockup discount for this position."
    ],
    "timestamp": 1783931489.749162
  },
  {
    "name": "UNKNOWN",
    "total_apr_pct": 0.0,
    "liquid_apr_pct": 0.0,
    "reward_apr_pct": 0.0,
    "lockup_days": 0.0,
    "discount_rate_pct": 15.0,
    "annual_vol_pct": 0.0,
    "early_exit_penalty_pct": 0.0,
    "liquid_unlock_fraction": 0.0,
    "data_quality_ok": true,
    "reward_share_of_apr_pct": 0.0,
    "lockup_discount_factor": 1.0,
    "realisable_reward_apr_pct": 0.0,
    "lockup_adjusted_apr_pct": 0.0,
    "headline_vs_realisable_gap_pct": 0.0,
    "paper_yield_share_pct": 0.0,
    "reward_realisability_score": 0.0,
    "classification": "DEEPLY_LOCKED",
    "grade": "F",
    "flags": [
      "INSUFFICIENT_DATA"
    ],
    "recommendations": [
      "Insufficient data: no APR/lockup signal or data marked unreliable. Cannot assess reward-lockup discount for this position."
    ],
    "timestamp": 1783931489.993596
  },
  {
    "name": "UNKNOWN",
    "total_apr_pct": 0.0,
    "liquid_apr_pct": 0.0,
    "reward_apr_pct": 0.0,
    "lockup_days": 0.0,
    "discount_rate_pct": 15.0,
    "annual_vol_pct": 0.0,
    "early_exit_penalty_pct": 0.0,
    "liquid_unlock_fraction": 0.0,
    "data_quality_ok": true,
    "reward_share_of_apr_pct": 0.0,
    "lockup_discount_factor": 1.0,
    "realisable_reward_apr_pct": 0.0,
    "lockup_adjusted_apr_pct": 0.0,
    "headline_vs_realisable_gap_pct": 0.0,
    "paper_yield_share_pct": 0.0,
    "reward_realisability_score": 0.0,
    "classification": "DEEPLY_LOCKED",
    "grade": "F",
    "flags": [
      "INSUFFICIENT_DATA"
    ],
    "recommendations": [
      "Insufficient data: no APR/lockup signal or data marked unreliable. Cannot assess reward-lockup discount for this position."
    ],
    "timestamp": 1783931490.1444385
  },
  {
    "name": "UNKNOWN",
    "total_apr_pct": 0.0,
    "liquid_apr_pct": 0.0,
    "reward_apr_pct": 0.0,
    "lockup_days": 0.0,
    "discount_rate_pct": 15.0,
    "annual_vol_pct": 0.0,
    "early_exit_penalty_pct": 0.0,
    "liquid_unlock_fraction": 0.0,
    "data_quality_ok": true,
    "reward_share_of_apr_pct": 0.0,
    "lockup_discount_factor": 1.0,
    "realisable_reward_apr_pct": 0.0,
    "lockup_adjusted_apr_pct": 0.0,
    "headline_vs_realisable_gap_pct": 0.0,
    "paper_yield_share_pct": 0.0,
    "reward_realisability_score": 0.0,
    "classification": "DEEPLY_LOCKED",
    "grade": "F",
    "flags": [
      "INSUFFICIENT_DATA"
    ],
    "recommendations": [
      "Insufficient data: no APR/lockup signal or data marked unreliable. Cannot assess reward-lockup discount for this position."
    ],
    "timestamp": 1783931490.3911614
  },
  {
    "name": "UNKNOWN",
    "total_apr_pct": 0.0,
    "liquid_apr_pct": 0.0,
    "reward_apr_pct": 0.0,
    "lockup_days": 0.0,
    "discount_rate_pct": 15.0,
    "annual_vol_pct": 0.0,
    "early_exit_penalty_pct": 0.0,
    "liquid_unlock_fraction": 0.0,
    "data_quality_ok": true,
    "reward_share_of_apr_pct": 0.0,
    "lockup_discount_factor": 1.0,
    "realisable_reward_apr_pct": 0.0,
    "lockup_adjusted_apr_pct": 0.0,
    "headline_vs_realisable_gap_pct": 0.0,
    "paper_yield_share_pct": 0.0,
    "reward_realisability_score": 0.0,
    "classification": "DEEPLY_LOCKED",
    "grade": "F",
    "flags": [
      "INSUFFICIENT_DATA"
    ],
    "recommendations": [
      "Insufficient data: no APR/lockup signal or data marked unreliable. Cannot assess reward-lockup discount for this position."
    ],
    "timestamp": 1783931490.533001
  },
  {
    "name": "UNKNOWN",
    "total_apr_pct": 0.0,
    "liquid_apr_pct": 0.0,
    "reward_apr_pct": 0.0,
    "lockup_days": 0.0,
    "discount_rate_pct": 15.0,
    "annual_vol_pct": 0.0,
    "early_exit_penalty_pct": 0.0,
    "liquid_unlock_fraction": 0.0,
    "data_quality_ok": true,
    "reward_share_of_apr_pct": 0.0,
    "lockup_discount_factor": 1.0,
    "realisable_reward_apr_pct": 0.0,
    "lockup_adjusted_apr_pct": 0.0,
    "headline_vs_realisable_gap_pct": 0.0,
    "paper_yield_share_pct": 0.0,
    "reward_realisability_score": 0.0,
    "classification": "DEEPLY_LOCKED",
    "grade": "F",
    "flags": [
      "INSUFFICIENT_DATA"
    ],
    "recommendations": [
      "Insufficient data: no APR/lockup signal or data marked unreliable. Cannot assess reward-lockup discount for this position."
    ],
    "timestamp": 1783931490.7741146
  },
  {
    "name": "UNKNOWN",
    "total_apr_pct": 0.0,
    "liquid_apr_pct": 0.0,
    "reward_apr_pct": 0.0,
    "lockup_days": 0.0,
    "discount_rate_pct": 15.0,
    "annual_vol_pct": 0.0,
    "early_exit_penalty_pct": 0.0,
    "liquid_unlock_fraction": 0.0,
    "data_quality_ok": true,
    "reward_share_of_apr_pct": 0.0,
    "lockup_discount_factor": 1.0,
    "realisable_reward_apr_pct": 0.0,
    "lockup_adjusted_apr_pct": 0.0,
    "headline_vs_realisable_gap_pct": 0.0,
    "paper_yield_share_pct": 0.0,
    "reward_realisability_score": 0.0,
    "classification": "DEEPLY_LOCKED",
    "grade": "F",
    "flags": [
      "INSUFFICIENT_DATA"
    ],
    "recommendations": [
      "Insufficient data: no APR/lockup signal or data marked unreliable. Cannot assess reward-lockup discount for this position."
    ],
    "timestamp": 1783931490.9167378
  },
  {
    "name": "UNKNOWN",
    "total_apr_pct": 0.0,
    "liquid_apr_pct": 0.0,
    "reward_apr_pct": 0.0,
    "lockup_days": 0.0,
    "discount_rate_pct": 15.0,
    "annual_vol_pct": 0.0,
    "early_exit_penalty_pct": 0.0,
    "liquid_unlock_fraction": 0.0,
    "data_quality_ok": true,
    "reward_share_of_apr_pct": 0.0,
    "lockup_discount_factor": 1.0,
    "realisable_reward_apr_pct": 0.0,
    "lockup_adjusted_apr_pct": 0.0,
    "headline_vs_realisable_gap_pct": 0.0,
    "paper_yield_share_pct": 0.0,
    "reward_realisability_score": 0.0,
    "classification": "DEEPLY_LOCKED",
    "grade": "F",
    "flags": [
      "INSUFFICIENT_DATA"
    ],
    "recommendations": [
      "Insufficient data: no APR/lockup signal or data marked unreliable. Cannot assess reward-lockup discount for this position."
    ],
    "timestamp": 1783931491.1653767
  },
  {
    "name": "UNKNOWN",
    "total_apr_pct": 0.0,
    "liquid_apr_pct": 0.0,
    "reward_apr_pct": 0.0,
    "lockup_days": 0.0,
    "discount_rate_pct": 15.0,
    "annual_vol_pct": 0.0,
    "early_exit_penalty_pct": 0.0,
    "liquid_unlock_fraction": 0.0,
    "data_quality_ok": true,
    "reward_share_of_apr_pct": 0.0,
    "lockup_discount_factor": 1.0,
    "realisable_reward_apr_pct": 0.0,
    "lockup_adjusted_apr_pct": 0.0,
    "headline_vs_realisable_gap_pct": 0.0,
    "paper_yield_share_pct": 0.0,
    "reward_realisability_score": 0.0,
    "classification": "DEEPLY_LOCKED",
    "grade": "F",
    "flags": [
      "INSUFFICIENT_DATA"
    ],
    "recommendations": [
      "Insufficient data: no APR/lockup signal or data marked unreliable. Cannot assess reward-lockup discount for this position."
    ],
    "timestamp": 1783931491.3259811
  },
  {
    "name": "UNKNOWN",
    "total_apr_pct": 0.0,
    "liquid_apr_pct": 0.0,
    "reward_apr_pct": 0.0,
    "lockup_days": 0.0,
    "discount_rate_pct": 15.0,
    "annual_vol_pct": 0.0,
    "early_exit_penalty_pct": 0.0,
    "liquid_unlock_fraction": 0.0,
    "data_quality_ok": true,
    "reward_share_of_apr_pct": 0.0,
    "lockup_discount_factor": 1.0,
    "realisable_reward_apr_pct": 0.0,
    "lockup_adjusted_apr_pct": 0.0,
    "headline_vs_realisable_gap_pct": 0.0,
    "paper_yield_share_pct": 0.0,
    "reward_realisability_score": 0.0,
    "classification": "DEEPLY_LOCKED",
    "grade": "F",
    "flags": [
      "INSUFFICIENT_DATA"
    ],
    "recommendations": [
      "Insufficient data: no APR/lockup signal or data marked unreliable. Cannot assess reward-lockup discount for this position."
    ],
    "timestamp": 1783931491.55962
  },
  {
    "name": "UNKNOWN",
    "total_apr_pct": 0.0,
    "liquid_apr_pct": 0.0,
    "reward_apr_pct": 0.0,
    "lockup_days": 0.0,
    "discount_rate_pct": 15.0,
    "annual_vol_pct": 0.0,
    "early_exit_penalty_pct": 0.0,
    "liquid_unlock_fraction": 0.0,
    "data_quality_ok": true,
    "reward_share_of_apr_pct": 0.0,
    "lockup_discount_factor": 1.0,
    "realisable_reward_apr_pct": 0.0,
    "lockup_adjusted_apr_pct": 0.0,
    "headline_vs_realisable_gap_pct": 0.0,
    "paper_yield_share_pct": 0.0,
    "reward_realisability_score": 0.0,
    "classification": "DEEPLY_LOCKED",
    "grade": "F",
    "flags": [
      "INSUFFICIENT_DATA"
    ],
    "recommendations": [
      "Insufficient data: no APR/lockup signal or data marked unreliable. Cannot assess reward-lockup discount for this position."
    ],
    "timestamp": 1783931491.7046704
  },
  {
    "name": "UNKNOWN",
    "total_apr_pct": 0.0,
    "liquid_apr_pct": 0.0,
    "reward_apr_pct": 0.0,
    "lockup_days": 0.0,
    "discount_rate_pct": 15.0,
    "annual_vol_pct": 0.0,
    "early_exit_penalty_pct": 0.0,
    "liquid_unlock_fraction": 0.0,
    "data_quality_ok": true,
    "reward_share_of_apr_pct": 0.0,
    "lockup_discount_factor": 1.0,
    "realisable_reward_apr_pct": 0.0,
    "lockup_adjusted_apr_pct": 0.0,
    "headline_vs_realisable_gap_pct": 0.0,
    "paper_yield_share_pct": 0.0,
    "reward_realisability_score": 0.0,
    "classification": "DEEPLY_LOCKED",
    "grade": "F",
    "flags": [
      "INSUFFICIENT_DATA"
    ],
    "recommendations": [
      "Insufficient data: no APR/lockup signal or data marked unreliable. Cannot assess reward-lockup discount for this position."
    ],
    "timestamp": 1783931491.9594061
  },
  {
    "name": "UNKNOWN",
    "total_apr_pct": 0.0,
    "liquid_apr_pct": 0.0,
    "reward_apr_pct": 0.0,
    "lockup_days": 0.0,
    "discount_rate_pct": 15.0,
    "annual_vol_pct": 0.0,
    "early_exit_penalty_pct": 0.0,
    "liquid_unlock_fraction": 0.0,
    "data_quality_ok": true,
    "reward_share_of_apr_pct": 0.0,
    "lockup_discount_factor": 1.0,
    "realisable_reward_apr_pct": 0.0,
    "lockup_adjusted_apr_pct": 0.0,
    "headline_vs_realisable_gap_pct": 0.0,
    "paper_yield_share_pct": 0.0,
    "reward_realisability_score": 0.0,
    "classification": "DEEPLY_LOCKED",
    "grade": "F",
    "flags": [
      "INSUFFICIENT_DATA"
    ],
    "recommendations": [
      "Insufficient data: no APR/lockup signal or data marked unreliable. Cannot assess reward-lockup discount for this position."
    ],
    "timestamp": 1783931492.095948
  },
  {
    "name": "UNKNOWN",
    "total_apr_pct": 0.0,
    "liquid_apr_pct": 0.0,
    "reward_apr_pct": 0.0,
    "lockup_days": 0.0,
    "discount_rate_pct": 15.0,
    "annual_vol_pct": 0.0,
    "early_exit_penalty_pct": 0.0,
    "liquid_unlock_fraction": 0.0,
    "data_quality_ok": true,
    "reward_share_of_apr_pct": 0.0,
    "lockup_discount_factor": 1.0,
    "realisable_reward_apr_pct": 0.0,
    "lockup_adjusted_apr_pct": 0.0,
    "headline_vs_realisable_gap_pct": 0.0,
    "paper_yield_share_pct": 0.0,
    "reward_realisability_score": 0.0,
    "classification": "DEEPLY_LOCKED",
    "grade": "F",
    "flags": [
      "INSUFFICIENT_DATA"
    ],
    "recommendations": [
      "Insufficient data: no APR/lockup signal or data marked unreliable. Cannot assess reward-lockup discount for this position."
    ],
    "timestamp": 1783931494.7981057
  },
  {
    "name": "UNKNOWN",
    "total_apr_pct": 0.0,
    "liquid_apr_pct": 0.0,
    "reward_apr_pct": 0.0,
    "lockup_days": 0.0,
    "discount_rate_pct": 15.0,
    "annual_vol_pct": 0.0,
    "early_exit_penalty_pct": 0.0,
    "liquid_unlock_fraction": 0.0,
    "data_quality_ok": true,
    "reward_share_of_apr_pct": 0.0,
    "lockup_discount_factor": 1.0,
    "realisable_reward_apr_pct": 0.0,
    "lockup_adjusted_apr_pct": 0.0,
    "headline_vs_realisable_gap_pct": 0.0,
    "paper_yield_share_pct": 0.0,
    "reward_realisability_score": 0.0,
    "classification": "DEEPLY_LOCKED",
    "grade": "F",
    "flags": [
      "INSUFFICIENT_DATA"
    ],
    "recommendations": [
      "Insufficient data: no APR/lockup signal or data marked unreliable. Cannot assess reward-lockup discount for this position."
    ],
    "timestamp": 1783931495.159956
  },
  {
    "name": "UNKNOWN",
    "total_apr_pct": 0.0,
    "liquid_apr_pct": 0.0,
    "reward_apr_pct": 0.0,
    "lockup_days": 0.0,
    "discount_rate_pct": 15.0,
    "annual_vol_pct": 0.0,
    "early_exit_penalty_pct": 0.0,
    "liquid_unlock_fraction": 0.0,
    "data_quality_ok": true,
    "reward_share_of_apr_pct": 0.0,
    "lockup_discount_factor": 1.0,
    "realisable_reward_apr_pct": 0.0,
    "lockup_adjusted_apr_pct": 0.0,
    "headline_vs_realisable_gap_pct": 0.0,
    "paper_yield_share_pct": 0.0,
    "reward_realisability_score": 0.0,
    "classification": "DEEPLY_LOCKED",
    "grade": "F",
    "flags": [
      "INSUFFICIENT_DATA"
    ],
    "recommendations": [
      "Insufficient data: no APR/lockup signal or data marked unreliable. Cannot assess reward-lockup discount for this position."
    ],
    "timestamp": 1783931495.3026972
  },
  {
    "name": "UNKNOWN",
    "total_apr_pct": 0.0,
    "liquid_apr_pct": 0.0,
    "reward_apr_pct": 0.0,
    "lockup_days": 0.0,
    "discount_rate_pct": 15.0,
    "annual_vol_pct": 0.0,
    "early_exit_penalty_pct": 0.0,
    "liquid_unlock_fraction": 0.0,
    "data_quality_ok": true,
    "reward_share_of_apr_pct": 0.0,
    "lockup_discount_factor": 1.0,
    "realisable_reward_apr_pct": 0.0,
    "lockup_adjusted_apr_pct": 0.0,
    "headline_vs_realisable_gap_pct": 0.0,
    "paper_yield_share_pct": 0.0,
    "reward_realisability_score": 0.0,
    "classification": "DEEPLY_LOCKED",
    "grade": "F",
    "flags": [
      "INSUFFICIENT_DATA"
    ],
    "recommendations": [
      "Insufficient data: no APR/lockup signal or data marked unreliable. Cannot assess reward-lockup discount for this position."
    ],
    "timestamp": 1783931495.6223714
  },
  {
    "name": "UNKNOWN",
    "total_apr_pct": 0.0,
    "liquid_apr_pct": 0.0,
    "reward_apr_pct": 0.0,
    "lockup_days": 0.0,
    "discount_rate_pct": 15.0,
    "annual_vol_pct": 0.0,
    "early_exit_penalty_pct": 0.0,
    "liquid_unlock_fraction": 0.0,
    "data_quality_ok": true,
    "reward_share_of_apr_pct": 0.0,
    "lockup_discount_factor": 1.0,
    "realisable_reward_apr_pct": 0.0,
    "lockup_adjusted_apr_pct": 0.0,
    "headline_vs_realisable_gap_pct": 0.0,
    "paper_yield_share_pct": 0.0,
    "reward_realisability_score": 0.0,
    "classification": "DEEPLY_LOCKED",
    "grade": "F",
    "flags": [
      "INSUFFICIENT_DATA"
    ],
    "recommendations": [
      "Insufficient data: no APR/lockup signal or data marked unreliable. Cannot assess reward-lockup discount for this position."
    ],
    "timestamp": 1783931495.7425463
  },
  {
    "name": "UNKNOWN",
    "total_apr_pct": 0.0,
    "liquid_apr_pct": 0.0,
    "reward_apr_pct": 0.0,
    "lockup_days": 0.0,
    "discount_rate_pct": 15.0,
    "annual_vol_pct": 0.0,
    "early_exit_penalty_pct": 0.0,
    "liquid_unlock_fraction": 0.0,
    "data_quality_ok": true,
    "reward_share_of_apr_pct": 0.0,
    "lockup_discount_factor": 1.0,
    "realisable_reward_apr_pct": 0.0,
    "lockup_adjusted_apr_pct": 0.0,
    "headline_vs_realisable_gap_pct": 0.0,
    "paper_yield_share_pct": 0.0,
    "reward_realisability_score": 0.0,
    "classification": "DEEPLY_LOCKED",
    "grade": "F",
    "flags": [
      "INSUFFICIENT_DATA"
    ],
    "recommendations": [
      "Insufficient data: no APR/lockup signal or data marked unreliable. Cannot assess reward-lockup discount for this position."
    ],
    "timestamp": 1783931496.092999
  },
  {
    "name": "UNKNOWN",
    "total_apr_pct": 0.0,
    "liquid_apr_pct": 0.0,
    "reward_apr_pct": 0.0,
    "lockup_days": 0.0,
    "discount_rate_pct": 15.0,
    "annual_vol_pct": 0.0,
    "early_exit_penalty_pct": 0.0,
    "liquid_unlock_fraction": 0.0,
    "data_quality_ok": true,
    "reward_share_of_apr_pct": 0.0,
    "lockup_discount_factor": 1.0,
    "realisable_reward_apr_pct": 0.0,
    "lockup_adjusted_apr_pct": 0.0,
    "headline_vs_realisable_gap_pct": 0.0,
    "paper_yield_share_pct": 0.0,
    "reward_realisability_score": 0.0,
    "classification": "DEEPLY_LOCKED",
    "grade": "F",
    "flags": [
      "INSUFFICIENT_DATA"
    ],
    "recommendations": [
      "Insufficient data: no APR/lockup signal or data marked unreliable. Cannot assess reward-lockup discount for this position."
    ],
    "timestamp": 1783931496.1897502
  },
  {
    "name": "UNKNOWN",
    "total_apr_pct": 0.0,
    "liquid_apr_pct": 0.0,
    "reward_apr_pct": 0.0,
    "lockup_days": 0.0,
    "discount_rate_pct": 15.0,
    "annual_vol_pct": 0.0,
    "early_exit_penalty_pct": 0.0,
    "liquid_unlock_fraction": 0.0,
    "data_quality_ok": true,
    "reward_share_of_apr_pct": 0.0,
    "lockup_discount_factor": 1.0,
    "realisable_reward_apr_pct": 0.0,
    "lockup_adjusted_apr_pct": 0.0,
    "headline_vs_realisable_gap_pct": 0.0,
    "paper_yield_share_pct": 0.0,
    "reward_realisability_score": 0.0,
    "classification": "DEEPLY_LOCKED",
    "grade": "F",
    "flags": [
      "INSUFFICIENT_DATA"
    ],
    "recommendations": [
      "Insufficient data: no APR/lockup signal or data marked unreliable. Cannot assess reward-lockup discount for this position."
    ],
    "timestamp": 1783931496.5455985
  },
  {
    "name": "UNKNOWN",
    "total_apr_pct": 0.0,
    "liquid_apr_pct": 0.0,
    "reward_apr_pct": 0.0,
    "lockup_days": 0.0,
    "discount_rate_pct": 15.0,
    "annual_vol_pct": 0.0,
    "early_exit_penalty_pct": 0.0,
    "liquid_unlock_fraction": 0.0,
    "data_quality_ok": true,
    "reward_share_of_apr_pct": 0.0,
    "lockup_discount_factor": 1.0,
    "realisable_reward_apr_pct": 0.0,
    "lockup_adjusted_apr_pct": 0.0,
    "headline_vs_realisable_gap_pct": 0.0,
    "paper_yield_share_pct": 0.0,
    "reward_realisability_score": 0.0,
    "classification": "DEEPLY_LOCKED",
    "grade": "F",
    "flags": [
      "INSUFFICIENT_DATA"
    ],
    "recommendations": [
      "Insufficient data: no APR/lockup signal or data marked unreliable. Cannot assess reward-lockup discount for this position."
    ],
    "timestamp": 1783931496.6578336
  },
  {
    "name": "UNKNOWN",
    "total_apr_pct": 0.0,
    "liquid_apr_pct": 0.0,
    "reward_apr_pct": 0.0,
    "lockup_days": 0.0,
    "discount_rate_pct": 15.0,
    "annual_vol_pct": 0.0,
    "early_exit_penalty_pct": 0.0,
    "liquid_unlock_fraction": 0.0,
    "data_quality_ok": true,
    "reward_share_of_apr_pct": 0.0,
    "lockup_discount_factor": 1.0,
    "realisable_reward_apr_pct": 0.0,
    "lockup_adjusted_apr_pct": 0.0,
    "headline_vs_realisable_gap_pct": 0.0,
    "paper_yield_share_pct": 0.0,
    "reward_realisability_score": 0.0,
    "classification": "DEEPLY_LOCKED",
    "grade": "F",
    "flags": [
      "INSUFFICIENT_DATA"
    ],
    "recommendations": [
      "Insufficient data: no APR/lockup signal or data marked unreliable. Cannot assess reward-lockup discount for this position."
    ],
    "timestamp": 1783931496.989648
  },
  {
    "name": "UNKNOWN",
    "total_apr_pct": 0.0,
    "liquid_apr_pct": 0.0,
    "reward_apr_pct": 0.0,
    "lockup_days": 0.0,
    "discount_rate_pct": 15.0,
    "annual_vol_pct": 0.0,
    "early_exit_penalty_pct": 0.0,
    "liquid_unlock_fraction": 0.0,
    "data_quality_ok": true,
    "reward_share_of_apr_pct": 0.0,
    "lockup_discount_factor": 1.0,
    "realisable_reward_apr_pct": 0.0,
    "lockup_adjusted_apr_pct": 0.0,
    "headline_vs_realisable_gap_pct": 0.0,
    "paper_yield_share_pct": 0.0,
    "reward_realisability_score": 0.0,
    "classification": "DEEPLY_LOCKED",
    "grade": "F",
    "flags": [
      "INSUFFICIENT_DATA"
    ],
    "recommendations": [
      "Insufficient data: no APR/lockup signal or data marked unreliable. Cannot assess reward-lockup discount for this position."
    ],
    "timestamp": 1783931497.136756
  },
  {
    "name": "UNKNOWN",
    "total_apr_pct": 0.0,
    "liquid_apr_pct": 0.0,
    "reward_apr_pct": 0.0,
    "lockup_days": 0.0,
    "discount_rate_pct": 15.0,
    "annual_vol_pct": 0.0,
    "early_exit_penalty_pct": 0.0,
    "liquid_unlock_fraction": 0.0,
    "data_quality_ok": true,
    "reward_share_of_apr_pct": 0.0,
    "lockup_discount_factor": 1.0,
    "realisable_reward_apr_pct": 0.0,
    "lockup_adjusted_apr_pct": 0.0,
    "headline_vs_realisable_gap_pct": 0.0,
    "paper_yield_share_pct": 0.0,
    "reward_realisability_score": 0.0,
    "classification": "DEEPLY_LOCKED",
    "grade": "F",
    "flags": [
      "INSUFFICIENT_DATA"
    ],
    "recommendations": [
      "Insufficient data: no APR/lockup signal or data marked unreliable. Cannot assess reward-lockup discount for this position."
    ],
    "timestamp": 1783931497.5064807
  },
  {
    "name": "UNKNOWN",
    "total_apr_pct": 0.0,
    "liquid_apr_pct": 0.0,
    "reward_apr_pct": 0.0,
    "lockup_days": 0.0,
    "discount_rate_pct": 15.0,
    "annual_vol_pct": 0.0,
    "early_exit_penalty_pct": 0.0,
    "liquid_unlock_fraction": 0.0,
    "data_quality_ok": true,
    "reward_share_of_apr_pct": 0.0,
    "lockup_discount_factor": 1.0,
    "realisable_reward_apr_pct": 0.0,
    "lockup_adjusted_apr_pct": 0.0,
    "headline_vs_realisable_gap_pct": 0.0,
    "paper_yield_share_pct": 0.0,
    "reward_realisability_score": 0.0,
    "classification": "DEEPLY_LOCKED",
    "grade": "F",
    "flags": [
      "INSUFFICIENT_DATA"
    ],
    "recommendations": [
      "Insufficient data: no APR/lockup signal or data marked unreliable. Cannot assess reward-lockup discount for this position."
    ],
    "timestamp": 1783931497.6237435
  }
]