[
  {
    "yield_source_name": "UNKNOWN",
    "dependency_chain": [],
    "max_chain_depth": 0,
    "effective_depth": 0,
    "total_failure_probability_pct": 0.0,
    "weakest_link": {},
    "chain_centralization_score": 0.0,
    "effective_yield_risk_multiplier": 1.0,
    "label": "ATOMIC_YIELD",
    "recommendations": [
      "Yield source has no external dependencies. Structural risk is minimal \u2014 only smart-contract risk applies."
    ],
    "timestamp": 1784622742.2601073
  },
  {
    "yield_source_name": "UNKNOWN",
    "dependency_chain": [],
    "max_chain_depth": 0,
    "effective_depth": 0,
    "total_failure_probability_pct": 0.0,
    "weakest_link": {},
    "chain_centralization_score": 0.0,
    "effective_yield_risk_multiplier": 1.0,
    "label": "ATOMIC_YIELD",
    "recommendations": [
      "Yield source has no external dependencies. Structural risk is minimal \u2014 only smart-contract risk applies."
    ],
    "timestamp": 1784622742.626759
  },
  {
    "yield_source_name": "UNKNOWN",
    "dependency_chain": [],
    "max_chain_depth": 0,
    "effective_depth": 0,
    "total_failure_probability_pct": 0.0,
    "weakest_link": {},
    "chain_centralization_score": 0.0,
    "effective_yield_risk_multiplier": 1.0,
    "label": "ATOMIC_YIELD",
    "recommendations": [
      "Yield source has no external dependencies. Structural risk is minimal \u2014 only smart-contract risk applies."
    ],
    "timestamp": 1784622745.7318456
  },
  {
    "yield_source_name": "UNKNOWN",
    "dependency_chain": [],
    "max_chain_depth": 0,
    "effective_depth": 0,
    "total_failure_probability_pct": 0.0,
    "weakest_link": {},
    "chain_centralization_score": 0.0,
    "effective_yield_risk_multiplier": 1.0,
    "label": "ATOMIC_YIELD",
    "recommendations": [
      "Yield source has no external dependencies. Structural risk is minimal \u2014 only smart-contract risk applies."
    ],
    "timestamp": 1784622746.1172523
  },
  {
    "yield_source_name": "UNKNOWN",
    "dependency_chain": [],
    "max_chain_depth": 0,
    "effective_depth": 0,
    "total_failure_probability_pct": 0.0,
    "weakest_link": {},
    "chain_centralization_score": 0.0,
    "effective_yield_risk_multiplier": 1.0,
    "label": "ATOMIC_YIELD",
    "recommendations": [
      "Yield source has no external dependencies. Structural risk is minimal \u2014 only smart-contract risk applies."
    ],
    "timestamp": 1784622746.4910736
  },
  {
    "yield_source_name": "UNKNOWN",
    "dependency_chain": [],
    "max_chain_depth": 0,
    "effective_depth": 0,
    "total_failure_probability_pct": 0.0,
    "weakest_link": {},
    "chain_centralization_score": 0.0,
    "effective_yield_risk_multiplier": 1.0,
    "label": "ATOMIC_YIELD",
    "recommendations": [
      "Yield source has no external dependencies. Structural risk is minimal \u2014 only smart-contract risk applies."
    ],
    "timestamp": 1784622746.9322774
  },
  {
    "yield_source_name": "UNKNOWN",
    "dependency_chain": [],
    "max_chain_depth": 0,
    "effective_depth": 0,
    "total_failure_probability_pct": 0.0,
    "weakest_link": {},
    "chain_centralization_score": 0.0,
    "effective_yield_risk_multiplier": 1.0,
    "label": "ATOMIC_YIELD",
    "recommendations": [
      "Yield source has no external dependencies. Structural risk is minimal \u2014 only smart-contract risk applies."
    ],
    "timestamp": 1784622747.3113937
  },
  {
    "yield_source_name": "UNKNOWN",
    "dependency_chain": [],
    "max_chain_depth": 0,
    "effective_depth": 0,
    "total_failure_probability_pct": 0.0,
    "weakest_link": {},
    "chain_centralization_score": 0.0,
    "effective_yield_risk_multiplier": 1.0,
    "label": "ATOMIC_YIELD",
    "recommendations": [
      "Yield source has no external dependencies. Structural risk is minimal \u2014 only smart-contract risk applies."
    ],
    "timestamp": 1784622747.6811025
  },
  {
    "yield_source_name": "UNKNOWN",
    "dependency_chain": [],
    "max_chain_depth": 0,
    "effective_depth": 0,
    "total_failure_probability_pct": 0.0,
    "weakest_link": {},
    "chain_centralization_score": 0.0,
    "effective_yield_risk_multiplier": 1.0,
    "label": "ATOMIC_YIELD",
    "recommendations": [
      "Yield source has no external dependencies. Structural risk is minimal \u2014 only smart-contract risk applies."
    ],
    "timestamp": 1784622748.0498166
  },
  {
    "yield_source_name": "UNKNOWN",
    "dependency_chain": [],
    "max_chain_depth": 0,
    "effective_depth": 0,
    "total_failure_probability_pct": 0.0,
    "weakest_link": {},
    "chain_centralization_score": 0.0,
    "effective_yield_risk_multiplier": 1.0,
    "label": "ATOMIC_YIELD",
    "recommendations": [
      "Yield source has no external dependencies. Structural risk is minimal \u2014 only smart-contract risk applies."
    ],
    "timestamp": 1784622748.4075942
  },
  {
    "yield_source_name": "UNKNOWN",
    "dependency_chain": [],
    "max_chain_depth": 0,
    "effective_depth": 0,
    "total_failure_probability_pct": 0.0,
    "weakest_link": {},
    "chain_centralization_score": 0.0,
    "effective_yield_risk_multiplier": 1.0,
    "label": "ATOMIC_YIELD",
    "recommendations": [
      "Yield source has no external dependencies. Structural risk is minimal \u2014 only smart-contract risk applies."
    ],
    "timestamp": 1784622751.379838
  },
  {
    "yield_source_name": "UNKNOWN",
    "dependency_chain": [],
    "max_chain_depth": 0,
    "effective_depth": 0,
    "total_failure_probability_pct": 0.0,
    "weakest_link": {},
    "chain_centralization_score": 0.0,
    "effective_yield_risk_multiplier": 1.0,
    "label": "ATOMIC_YIELD",
    "recommendations": [
      "Yield source has no external dependencies. Structural risk is minimal \u2014 only smart-contract risk applies."
    ],
    "timestamp": 1784622751.7432199
  },
  {
    "yield_source_name": "UNKNOWN",
    "dependency_chain": [],
    "max_chain_depth": 0,
    "effective_depth": 0,
    "total_failure_probability_pct": 0.0,
    "weakest_link": {},
    "chain_centralization_score": 0.0,
    "effective_yield_risk_multiplier": 1.0,
    "label": "ATOMIC_YIELD",
    "recommendations": [
      "Yield source has no external dependencies. Structural risk is minimal \u2014 only smart-contract risk applies."
    ],
    "timestamp": 1784622752.1378918
  },
  {
    "yield_source_name": "UNKNOWN",
    "dependency_chain": [],
    "max_chain_depth": 0,
    "effective_depth": 0,
    "total_failure_probability_pct": 0.0,
    "weakest_link": {},
    "chain_centralization_score": 0.0,
    "effective_yield_risk_multiplier": 1.0,
    "label": "ATOMIC_YIELD",
    "recommendations": [
      "Yield source has no external dependencies. Structural risk is minimal \u2014 only smart-contract risk applies."
    ],
    "timestamp": 1784622752.526337
  },
  {
    "yield_source_name": "UNKNOWN",
    "dependency_chain": [],
    "max_chain_depth": 0,
    "effective_depth": 0,
    "total_failure_probability_pct": 0.0,
    "weakest_link": {},
    "chain_centralization_score": 0.0,
    "effective_yield_risk_multiplier": 1.0,
    "label": "ATOMIC_YIELD",
    "recommendations": [
      "Yield source has no external dependencies. Structural risk is minimal \u2014 only smart-contract risk applies."
    ],
    "timestamp": 1784622752.9599757
  },
  {
    "yield_source_name": "UNKNOWN",
    "dependency_chain": [],
    "max_chain_depth": 0,
    "effective_depth": 0,
    "total_failure_probability_pct": 0.0,
    "weakest_link": {},
    "chain_centralization_score": 0.0,
    "effective_yield_risk_multiplier": 1.0,
    "label": "ATOMIC_YIELD",
    "recommendations": [
      "Yield source has no external dependencies. Structural risk is minimal \u2014 only smart-contract risk applies."
    ],
    "timestamp": 1784622753.3323846
  },
  {
    "yield_source_name": "UNKNOWN",
    "dependency_chain": [],
    "max_chain_depth": 0,
    "effective_depth": 0,
    "total_failure_probability_pct": 0.0,
    "weakest_link": {},
    "chain_centralization_score": 0.0,
    "effective_yield_risk_multiplier": 1.0,
    "label": "ATOMIC_YIELD",
    "recommendations": [
      "Yield source has no external dependencies. Structural risk is minimal \u2014 only smart-contract risk applies."
    ],
    "timestamp": 1784622753.7040653
  },
  {
    "yield_source_name": "UNKNOWN",
    "dependency_chain": [],
    "max_chain_depth": 0,
    "effective_depth": 0,
    "total_failure_probability_pct": 0.0,
    "weakest_link": {},
    "chain_centralization_score": 0.0,
    "effective_yield_risk_multiplier": 1.0,
    "label": "ATOMIC_YIELD",
    "recommendations": [
      "Yield source has no external dependencies. Structural risk is minimal \u2014 only smart-contract risk applies."
    ],
    "timestamp": 1784622754.0788534
  },
  {
    "yield_source_name": "UNKNOWN",
    "dependency_chain": [],
    "max_chain_depth": 0,
    "effective_depth": 0,
    "total_failure_probability_pct": 0.0,
    "weakest_link": {},
    "chain_centralization_score": 0.0,
    "effective_yield_risk_multiplier": 1.0,
    "label": "ATOMIC_YIELD",
    "recommendations": [
      "Yield source has no external dependencies. Structural risk is minimal \u2014 only smart-contract risk applies."
    ],
    "timestamp": 1784622757.4728687
  },
  {
    "yield_source_name": "UNKNOWN",
    "dependency_chain": [],
    "max_chain_depth": 0,
    "effective_depth": 0,
    "total_failure_probability_pct": 0.0,
    "weakest_link": {},
    "chain_centralization_score": 0.0,
    "effective_yield_risk_multiplier": 1.0,
    "label": "ATOMIC_YIELD",
    "recommendations": [
      "Yield source has no external dependencies. Structural risk is minimal \u2014 only smart-contract risk applies."
    ],
    "timestamp": 1784622757.8305516
  },
  {
    "yield_source_name": "UNKNOWN",
    "dependency_chain": [],
    "max_chain_depth": 0,
    "effective_depth": 0,
    "total_failure_probability_pct": 0.0,
    "weakest_link": {},
    "chain_centralization_score": 0.0,
    "effective_yield_risk_multiplier": 1.0,
    "label": "ATOMIC_YIELD",
    "recommendations": [
      "Yield source has no external dependencies. Structural risk is minimal \u2014 only smart-contract risk applies."
    ],
    "timestamp": 1784622762.1021993
  },
  {
    "yield_source_name": "UNKNOWN",
    "dependency_chain": [],
    "max_chain_depth": 0,
    "effective_depth": 0,
    "total_failure_probability_pct": 0.0,
    "weakest_link": {},
    "chain_centralization_score": 0.0,
    "effective_yield_risk_multiplier": 1.0,
    "label": "ATOMIC_YIELD",
    "recommendations": [
      "Yield source has no external dependencies. Structural risk is minimal \u2014 only smart-contract risk applies."
    ],
    "timestamp": 1784622762.4797304
  },
  {
    "yield_source_name": "UNKNOWN",
    "dependency_chain": [],
    "max_chain_depth": 0,
    "effective_depth": 0,
    "total_failure_probability_pct": 0.0,
    "weakest_link": {},
    "chain_centralization_score": 0.0,
    "effective_yield_risk_multiplier": 1.0,
    "label": "ATOMIC_YIELD",
    "recommendations": [
      "Yield source has no external dependencies. Structural risk is minimal \u2014 only smart-contract risk applies."
    ],
    "timestamp": 1784622762.8774922
  },
  {
    "yield_source_name": "UNKNOWN",
    "dependency_chain": [],
    "max_chain_depth": 0,
    "effective_depth": 0,
    "total_failure_probability_pct": 0.0,
    "weakest_link": {},
    "chain_centralization_score": 0.0,
    "effective_yield_risk_multiplier": 1.0,
    "label": "ATOMIC_YIELD",
    "recommendations": [
      "Yield source has no external dependencies. Structural risk is minimal \u2014 only smart-contract risk applies."
    ],
    "timestamp": 1784622763.2534516
  },
  {
    "yield_source_name": "UNKNOWN",
    "dependency_chain": [],
    "max_chain_depth": 0,
    "effective_depth": 0,
    "total_failure_probability_pct": 0.0,
    "weakest_link": {},
    "chain_centralization_score": 0.0,
    "effective_yield_risk_multiplier": 1.0,
    "label": "ATOMIC_YIELD",
    "recommendations": [
      "Yield source has no external dependencies. Structural risk is minimal \u2014 only smart-contract risk applies."
    ],
    "timestamp": 1784622763.59288
  },
  {
    "yield_source_name": "UNKNOWN",
    "dependency_chain": [],
    "max_chain_depth": 0,
    "effective_depth": 0,
    "total_failure_probability_pct": 0.0,
    "weakest_link": {},
    "chain_centralization_score": 0.0,
    "effective_yield_risk_multiplier": 1.0,
    "label": "ATOMIC_YIELD",
    "recommendations": [
      "Yield source has no external dependencies. Structural risk is minimal \u2014 only smart-contract risk applies."
    ],
    "timestamp": 1784622763.9542634
  },
  {
    "yield_source_name": "UNKNOWN",
    "dependency_chain": [],
    "max_chain_depth": 0,
    "effective_depth": 0,
    "total_failure_probability_pct": 0.0,
    "weakest_link": {},
    "chain_centralization_score": 0.0,
    "effective_yield_risk_multiplier": 1.0,
    "label": "ATOMIC_YIELD",
    "recommendations": [
      "Yield source has no external dependencies. Structural risk is minimal \u2014 only smart-contract risk applies."
    ],
    "timestamp": 1784622767.079801
  },
  {
    "yield_source_name": "UNKNOWN",
    "dependency_chain": [],
    "max_chain_depth": 0,
    "effective_depth": 0,
    "total_failure_probability_pct": 0.0,
    "weakest_link": {},
    "chain_centralization_score": 0.0,
    "effective_yield_risk_multiplier": 1.0,
    "label": "ATOMIC_YIELD",
    "recommendations": [
      "Yield source has no external dependencies. Structural risk is minimal \u2014 only smart-contract risk applies."
    ],
    "timestamp": 1784622767.6566174
  },
  {
    "yield_source_name": "UNKNOWN",
    "dependency_chain": [],
    "max_chain_depth": 0,
    "effective_depth": 0,
    "total_failure_probability_pct": 0.0,
    "weakest_link": {},
    "chain_centralization_score": 0.0,
    "effective_yield_risk_multiplier": 1.0,
    "label": "ATOMIC_YIELD",
    "recommendations": [
      "Yield source has no external dependencies. Structural risk is minimal \u2014 only smart-contract risk applies."
    ],
    "timestamp": 1784622768.0730977
  },
  {
    "yield_source_name": "UNKNOWN",
    "dependency_chain": [],
    "max_chain_depth": 0,
    "effective_depth": 0,
    "total_failure_probability_pct": 0.0,
    "weakest_link": {},
    "chain_centralization_score": 0.0,
    "effective_yield_risk_multiplier": 1.0,
    "label": "ATOMIC_YIELD",
    "recommendations": [
      "Yield source has no external dependencies. Structural risk is minimal \u2014 only smart-contract risk applies."
    ],
    "timestamp": 1784622768.4643357
  },
  {
    "yield_source_name": "UNKNOWN",
    "dependency_chain": [],
    "max_chain_depth": 0,
    "effective_depth": 0,
    "total_failure_probability_pct": 0.0,
    "weakest_link": {},
    "chain_centralization_score": 0.0,
    "effective_yield_risk_multiplier": 1.0,
    "label": "ATOMIC_YIELD",
    "recommendations": [
      "Yield source has no external dependencies. Structural risk is minimal \u2014 only smart-contract risk applies."
    ],
    "timestamp": 1784622768.9037645
  },
  {
    "yield_source_name": "UNKNOWN",
    "dependency_chain": [],
    "max_chain_depth": 0,
    "effective_depth": 0,
    "total_failure_probability_pct": 0.0,
    "weakest_link": {},
    "chain_centralization_score": 0.0,
    "effective_yield_risk_multiplier": 1.0,
    "label": "ATOMIC_YIELD",
    "recommendations": [
      "Yield source has no external dependencies. Structural risk is minimal \u2014 only smart-contract risk applies."
    ],
    "timestamp": 1784622769.271758
  },
  {
    "yield_source_name": "UNKNOWN",
    "dependency_chain": [],
    "max_chain_depth": 0,
    "effective_depth": 0,
    "total_failure_probability_pct": 0.0,
    "weakest_link": {},
    "chain_centralization_score": 0.0,
    "effective_yield_risk_multiplier": 1.0,
    "label": "ATOMIC_YIELD",
    "recommendations": [
      "Yield source has no external dependencies. Structural risk is minimal \u2014 only smart-contract risk applies."
    ],
    "timestamp": 1784622769.623344
  },
  {
    "yield_source_name": "UNKNOWN",
    "dependency_chain": [],
    "max_chain_depth": 0,
    "effective_depth": 0,
    "total_failure_probability_pct": 0.0,
    "weakest_link": {},
    "chain_centralization_score": 0.0,
    "effective_yield_risk_multiplier": 1.0,
    "label": "ATOMIC_YIELD",
    "recommendations": [
      "Yield source has no external dependencies. Structural risk is minimal \u2014 only smart-contract risk applies."
    ],
    "timestamp": 1784622769.973879
  },
  {
    "yield_source_name": "UNKNOWN",
    "dependency_chain": [],
    "max_chain_depth": 0,
    "effective_depth": 0,
    "total_failure_probability_pct": 0.0,
    "weakest_link": {},
    "chain_centralization_score": 0.0,
    "effective_yield_risk_multiplier": 1.0,
    "label": "ATOMIC_YIELD",
    "recommendations": [
      "Yield source has no external dependencies. Structural risk is minimal \u2014 only smart-contract risk applies."
    ],
    "timestamp": 1784622773.5126948
  },
  {
    "yield_source_name": "UNKNOWN",
    "dependency_chain": [],
    "max_chain_depth": 0,
    "effective_depth": 0,
    "total_failure_probability_pct": 0.0,
    "weakest_link": {},
    "chain_centralization_score": 0.0,
    "effective_yield_risk_multiplier": 1.0,
    "label": "ATOMIC_YIELD",
    "recommendations": [
      "Yield source has no external dependencies. Structural risk is minimal \u2014 only smart-contract risk applies."
    ],
    "timestamp": 1784622773.905125
  },
  {
    "yield_source_name": "UNKNOWN",
    "dependency_chain": [],
    "max_chain_depth": 0,
    "effective_depth": 0,
    "total_failure_probability_pct": 0.0,
    "weakest_link": {},
    "chain_centralization_score": 0.0,
    "effective_yield_risk_multiplier": 1.0,
    "label": "ATOMIC_YIELD",
    "recommendations": [
      "Yield source has no external dependencies. Structural risk is minimal \u2014 only smart-contract risk applies."
    ],
    "timestamp": 1784622774.2690713
  },
  {
    "yield_source_name": "UNKNOWN",
    "dependency_chain": [],
    "max_chain_depth": 0,
    "effective_depth": 0,
    "total_failure_probability_pct": 0.0,
    "weakest_link": {},
    "chain_centralization_score": 0.0,
    "effective_yield_risk_multiplier": 1.0,
    "label": "ATOMIC_YIELD",
    "recommendations": [
      "Yield source has no external dependencies. Structural risk is minimal \u2014 only smart-contract risk applies."
    ],
    "timestamp": 1784622774.6333516
  },
  {
    "yield_source_name": "UNKNOWN",
    "dependency_chain": [],
    "max_chain_depth": 0,
    "effective_depth": 0,
    "total_failure_probability_pct": 0.0,
    "weakest_link": {},
    "chain_centralization_score": 0.0,
    "effective_yield_risk_multiplier": 1.0,
    "label": "ATOMIC_YIELD",
    "recommendations": [
      "Yield source has no external dependencies. Structural risk is minimal \u2014 only smart-contract risk applies."
    ],
    "timestamp": 1784622774.999169
  },
  {
    "yield_source_name": "UNKNOWN",
    "dependency_chain": [],
    "max_chain_depth": 0,
    "effective_depth": 0,
    "total_failure_probability_pct": 0.0,
    "weakest_link": {},
    "chain_centralization_score": 0.0,
    "effective_yield_risk_multiplier": 1.0,
    "label": "ATOMIC_YIELD",
    "recommendations": [
      "Yield source has no external dependencies. Structural risk is minimal \u2014 only smart-contract risk applies."
    ],
    "timestamp": 1784622775.3598742
  },
  {
    "yield_source_name": "UNKNOWN",
    "dependency_chain": [],
    "max_chain_depth": 0,
    "effective_depth": 0,
    "total_failure_probability_pct": 0.0,
    "weakest_link": {},
    "chain_centralization_score": 0.0,
    "effective_yield_risk_multiplier": 1.0,
    "label": "ATOMIC_YIELD",
    "recommendations": [
      "Yield source has no external dependencies. Structural risk is minimal \u2014 only smart-contract risk applies."
    ],
    "timestamp": 1784622775.7438385
  },
  {
    "yield_source_name": "UNKNOWN",
    "dependency_chain": [],
    "max_chain_depth": 0,
    "effective_depth": 0,
    "total_failure_probability_pct": 0.0,
    "weakest_link": {},
    "chain_centralization_score": 0.0,
    "effective_yield_risk_multiplier": 1.0,
    "label": "ATOMIC_YIELD",
    "recommendations": [
      "Yield source has no external dependencies. Structural risk is minimal \u2014 only smart-contract risk applies."
    ],
    "timestamp": 1784622776.1129603
  },
  {
    "yield_source_name": "UNKNOWN",
    "dependency_chain": [],
    "max_chain_depth": 0,
    "effective_depth": 0,
    "total_failure_probability_pct": 0.0,
    "weakest_link": {},
    "chain_centralization_score": 0.0,
    "effective_yield_risk_multiplier": 1.0,
    "label": "ATOMIC_YIELD",
    "recommendations": [
      "Yield source has no external dependencies. Structural risk is minimal \u2014 only smart-contract risk applies."
    ],
    "timestamp": 1784622779.1011984
  },
  {
    "yield_source_name": "UNKNOWN",
    "dependency_chain": [],
    "max_chain_depth": 0,
    "effective_depth": 0,
    "total_failure_probability_pct": 0.0,
    "weakest_link": {},
    "chain_centralization_score": 0.0,
    "effective_yield_risk_multiplier": 1.0,
    "label": "ATOMIC_YIELD",
    "recommendations": [
      "Yield source has no external dependencies. Structural risk is minimal \u2014 only smart-contract risk applies."
    ],
    "timestamp": 1784622779.4449828
  },
  {
    "yield_source_name": "UNKNOWN",
    "dependency_chain": [],
    "max_chain_depth": 0,
    "effective_depth": 0,
    "total_failure_probability_pct": 0.0,
    "weakest_link": {},
    "chain_centralization_score": 0.0,
    "effective_yield_risk_multiplier": 1.0,
    "label": "ATOMIC_YIELD",
    "recommendations": [
      "Yield source has no external dependencies. Structural risk is minimal \u2014 only smart-contract risk applies."
    ],
    "timestamp": 1784622779.8060236
  },
  {
    "yield_source_name": "UNKNOWN",
    "dependency_chain": [],
    "max_chain_depth": 0,
    "effective_depth": 0,
    "total_failure_probability_pct": 0.0,
    "weakest_link": {},
    "chain_centralization_score": 0.0,
    "effective_yield_risk_multiplier": 1.0,
    "label": "ATOMIC_YIELD",
    "recommendations": [
      "Yield source has no external dependencies. Structural risk is minimal \u2014 only smart-contract risk applies."
    ],
    "timestamp": 1784622780.163967
  },
  {
    "yield_source_name": "UNKNOWN",
    "dependency_chain": [],
    "max_chain_depth": 0,
    "effective_depth": 0,
    "total_failure_probability_pct": 0.0,
    "weakest_link": {},
    "chain_centralization_score": 0.0,
    "effective_yield_risk_multiplier": 1.0,
    "label": "ATOMIC_YIELD",
    "recommendations": [
      "Yield source has no external dependencies. Structural risk is minimal \u2014 only smart-contract risk applies."
    ],
    "timestamp": 1784622780.5378501
  },
  {
    "yield_source_name": "UNKNOWN",
    "dependency_chain": [],
    "max_chain_depth": 0,
    "effective_depth": 0,
    "total_failure_probability_pct": 0.0,
    "weakest_link": {},
    "chain_centralization_score": 0.0,
    "effective_yield_risk_multiplier": 1.0,
    "label": "ATOMIC_YIELD",
    "recommendations": [
      "Yield source has no external dependencies. Structural risk is minimal \u2014 only smart-contract risk applies."
    ],
    "timestamp": 1784622780.9044425
  },
  {
    "yield_source_name": "UNKNOWN",
    "dependency_chain": [],
    "max_chain_depth": 0,
    "effective_depth": 0,
    "total_failure_probability_pct": 0.0,
    "weakest_link": {},
    "chain_centralization_score": 0.0,
    "effective_yield_risk_multiplier": 1.0,
    "label": "ATOMIC_YIELD",
    "recommendations": [
      "Yield source has no external dependencies. Structural risk is minimal \u2014 only smart-contract risk applies."
    ],
    "timestamp": 1784622781.2667081
  },
  {
    "yield_source_name": "UNKNOWN",
    "dependency_chain": [],
    "max_chain_depth": 0,
    "effective_depth": 0,
    "total_failure_probability_pct": 0.0,
    "weakest_link": {},
    "chain_centralization_score": 0.0,
    "effective_yield_risk_multiplier": 1.0,
    "label": "ATOMIC_YIELD",
    "recommendations": [
      "Yield source has no external dependencies. Structural risk is minimal \u2014 only smart-contract risk applies."
    ],
    "timestamp": 1784622781.6235228
  },
  {
    "yield_source_name": "UNKNOWN",
    "dependency_chain": [],
    "max_chain_depth": 0,
    "effective_depth": 0,
    "total_failure_probability_pct": 0.0,
    "weakest_link": {},
    "chain_centralization_score": 0.0,
    "effective_yield_risk_multiplier": 1.0,
    "label": "ATOMIC_YIELD",
    "recommendations": [
      "Yield source has no external dependencies. Structural risk is minimal \u2014 only smart-contract risk applies."
    ],
    "timestamp": 1784622785.1153007
  },
  {
    "yield_source_name": "UNKNOWN",
    "dependency_chain": [],
    "max_chain_depth": 0,
    "effective_depth": 0,
    "total_failure_probability_pct": 0.0,
    "weakest_link": {},
    "chain_centralization_score": 0.0,
    "effective_yield_risk_multiplier": 1.0,
    "label": "ATOMIC_YIELD",
    "recommendations": [
      "Yield source has no external dependencies. Structural risk is minimal \u2014 only smart-contract risk applies."
    ],
    "timestamp": 1784622785.4730225
  },
  {
    "yield_source_name": "UNKNOWN",
    "dependency_chain": [],
    "max_chain_depth": 0,
    "effective_depth": 0,
    "total_failure_probability_pct": 0.0,
    "weakest_link": {},
    "chain_centralization_score": 0.0,
    "effective_yield_risk_multiplier": 1.0,
    "label": "ATOMIC_YIELD",
    "recommendations": [
      "Yield source has no external dependencies. Structural risk is minimal \u2014 only smart-contract risk applies."
    ],
    "timestamp": 1784622785.846361
  },
  {
    "yield_source_name": "UNKNOWN",
    "dependency_chain": [],
    "max_chain_depth": 0,
    "effective_depth": 0,
    "total_failure_probability_pct": 0.0,
    "weakest_link": {},
    "chain_centralization_score": 0.0,
    "effective_yield_risk_multiplier": 1.0,
    "label": "ATOMIC_YIELD",
    "recommendations": [
      "Yield source has no external dependencies. Structural risk is minimal \u2014 only smart-contract risk applies."
    ],
    "timestamp": 1784622786.2105234
  },
  {
    "yield_source_name": "UNKNOWN",
    "dependency_chain": [],
    "max_chain_depth": 0,
    "effective_depth": 0,
    "total_failure_probability_pct": 0.0,
    "weakest_link": {},
    "chain_centralization_score": 0.0,
    "effective_yield_risk_multiplier": 1.0,
    "label": "ATOMIC_YIELD",
    "recommendations": [
      "Yield source has no external dependencies. Structural risk is minimal \u2014 only smart-contract risk applies."
    ],
    "timestamp": 1784622786.557876
  },
  {
    "yield_source_name": "UNKNOWN",
    "dependency_chain": [],
    "max_chain_depth": 0,
    "effective_depth": 0,
    "total_failure_probability_pct": 0.0,
    "weakest_link": {},
    "chain_centralization_score": 0.0,
    "effective_yield_risk_multiplier": 1.0,
    "label": "ATOMIC_YIELD",
    "recommendations": [
      "Yield source has no external dependencies. Structural risk is minimal \u2014 only smart-contract risk applies."
    ],
    "timestamp": 1784622786.9627216
  },
  {
    "yield_source_name": "UNKNOWN",
    "dependency_chain": [],
    "max_chain_depth": 0,
    "effective_depth": 0,
    "total_failure_probability_pct": 0.0,
    "weakest_link": {},
    "chain_centralization_score": 0.0,
    "effective_yield_risk_multiplier": 1.0,
    "label": "ATOMIC_YIELD",
    "recommendations": [
      "Yield source has no external dependencies. Structural risk is minimal \u2014 only smart-contract risk applies."
    ],
    "timestamp": 1784622787.3344762
  },
  {
    "yield_source_name": "UNKNOWN",
    "dependency_chain": [],
    "max_chain_depth": 0,
    "effective_depth": 0,
    "total_failure_probability_pct": 0.0,
    "weakest_link": {},
    "chain_centralization_score": 0.0,
    "effective_yield_risk_multiplier": 1.0,
    "label": "ATOMIC_YIELD",
    "recommendations": [
      "Yield source has no external dependencies. Structural risk is minimal \u2014 only smart-contract risk applies."
    ],
    "timestamp": 1784622787.6910067
  },
  {
    "yield_source_name": "UNKNOWN",
    "dependency_chain": [],
    "max_chain_depth": 0,
    "effective_depth": 0,
    "total_failure_probability_pct": 0.0,
    "weakest_link": {},
    "chain_centralization_score": 0.0,
    "effective_yield_risk_multiplier": 1.0,
    "label": "ATOMIC_YIELD",
    "recommendations": [
      "Yield source has no external dependencies. Structural risk is minimal \u2014 only smart-contract risk applies."
    ],
    "timestamp": 1784622790.7284422
  },
  {
    "yield_source_name": "UNKNOWN",
    "dependency_chain": [],
    "max_chain_depth": 0,
    "effective_depth": 0,
    "total_failure_probability_pct": 0.0,
    "weakest_link": {},
    "chain_centralization_score": 0.0,
    "effective_yield_risk_multiplier": 1.0,
    "label": "ATOMIC_YIELD",
    "recommendations": [
      "Yield source has no external dependencies. Structural risk is minimal \u2014 only smart-contract risk applies."
    ],
    "timestamp": 1784622791.1287258
  },
  {
    "yield_source_name": "UNKNOWN",
    "dependency_chain": [],
    "max_chain_depth": 0,
    "effective_depth": 0,
    "total_failure_probability_pct": 0.0,
    "weakest_link": {},
    "chain_centralization_score": 0.0,
    "effective_yield_risk_multiplier": 1.0,
    "label": "ATOMIC_YIELD",
    "recommendations": [
      "Yield source has no external dependencies. Structural risk is minimal \u2014 only smart-contract risk applies."
    ],
    "timestamp": 1784622791.5422885
  },
  {
    "yield_source_name": "UNKNOWN",
    "dependency_chain": [],
    "max_chain_depth": 0,
    "effective_depth": 0,
    "total_failure_probability_pct": 0.0,
    "weakest_link": {},
    "chain_centralization_score": 0.0,
    "effective_yield_risk_multiplier": 1.0,
    "label": "ATOMIC_YIELD",
    "recommendations": [
      "Yield source has no external dependencies. Structural risk is minimal \u2014 only smart-contract risk applies."
    ],
    "timestamp": 1784622791.9058437
  },
  {
    "yield_source_name": "UNKNOWN",
    "dependency_chain": [],
    "max_chain_depth": 0,
    "effective_depth": 0,
    "total_failure_probability_pct": 0.0,
    "weakest_link": {},
    "chain_centralization_score": 0.0,
    "effective_yield_risk_multiplier": 1.0,
    "label": "ATOMIC_YIELD",
    "recommendations": [
      "Yield source has no external dependencies. Structural risk is minimal \u2014 only smart-contract risk applies."
    ],
    "timestamp": 1784622792.272471
  },
  {
    "yield_source_name": "UNKNOWN",
    "dependency_chain": [],
    "max_chain_depth": 0,
    "effective_depth": 0,
    "total_failure_probability_pct": 0.0,
    "weakest_link": {},
    "chain_centralization_score": 0.0,
    "effective_yield_risk_multiplier": 1.0,
    "label": "ATOMIC_YIELD",
    "recommendations": [
      "Yield source has no external dependencies. Structural risk is minimal \u2014 only smart-contract risk applies."
    ],
    "timestamp": 1784622792.623597
  },
  {
    "yield_source_name": "UNKNOWN",
    "dependency_chain": [],
    "max_chain_depth": 0,
    "effective_depth": 0,
    "total_failure_probability_pct": 0.0,
    "weakest_link": {},
    "chain_centralization_score": 0.0,
    "effective_yield_risk_multiplier": 1.0,
    "label": "ATOMIC_YIELD",
    "recommendations": [
      "Yield source has no external dependencies. Structural risk is minimal \u2014 only smart-contract risk applies."
    ],
    "timestamp": 1784622792.9758875
  },
  {
    "yield_source_name": "UNKNOWN",
    "dependency_chain": [],
    "max_chain_depth": 0,
    "effective_depth": 0,
    "total_failure_probability_pct": 0.0,
    "weakest_link": {},
    "chain_centralization_score": 0.0,
    "effective_yield_risk_multiplier": 1.0,
    "label": "ATOMIC_YIELD",
    "recommendations": [
      "Yield source has no external dependencies. Structural risk is minimal \u2014 only smart-contract risk applies."
    ],
    "timestamp": 1784622793.3495083
  },
  {
    "yield_source_name": "UNKNOWN",
    "dependency_chain": [],
    "max_chain_depth": 0,
    "effective_depth": 0,
    "total_failure_probability_pct": 0.0,
    "weakest_link": {},
    "chain_centralization_score": 0.0,
    "effective_yield_risk_multiplier": 1.0,
    "label": "ATOMIC_YIELD",
    "recommendations": [
      "Yield source has no external dependencies. Structural risk is minimal \u2014 only smart-contract risk applies."
    ],
    "timestamp": 1784622797.244921
  },
  {
    "yield_source_name": "UNKNOWN",
    "dependency_chain": [],
    "max_chain_depth": 0,
    "effective_depth": 0,
    "total_failure_probability_pct": 0.0,
    "weakest_link": {},
    "chain_centralization_score": 0.0,
    "effective_yield_risk_multiplier": 1.0,
    "label": "ATOMIC_YIELD",
    "recommendations": [
      "Yield source has no external dependencies. Structural risk is minimal \u2014 only smart-contract risk applies."
    ],
    "timestamp": 1784622797.6361318
  },
  {
    "yield_source_name": "UNKNOWN",
    "dependency_chain": [],
    "max_chain_depth": 0,
    "effective_depth": 0,
    "total_failure_probability_pct": 0.0,
    "weakest_link": {},
    "chain_centralization_score": 0.0,
    "effective_yield_risk_multiplier": 1.0,
    "label": "ATOMIC_YIELD",
    "recommendations": [
      "Yield source has no external dependencies. Structural risk is minimal \u2014 only smart-contract risk applies."
    ],
    "timestamp": 1784622798.0155804
  },
  {
    "yield_source_name": "UNKNOWN",
    "dependency_chain": [],
    "max_chain_depth": 0,
    "effective_depth": 0,
    "total_failure_probability_pct": 0.0,
    "weakest_link": {},
    "chain_centralization_score": 0.0,
    "effective_yield_risk_multiplier": 1.0,
    "label": "ATOMIC_YIELD",
    "recommendations": [
      "Yield source has no external dependencies. Structural risk is minimal \u2014 only smart-contract risk applies."
    ],
    "timestamp": 1784622798.3876195
  },
  {
    "yield_source_name": "UNKNOWN",
    "dependency_chain": [],
    "max_chain_depth": 0,
    "effective_depth": 0,
    "total_failure_probability_pct": 0.0,
    "weakest_link": {},
    "chain_centralization_score": 0.0,
    "effective_yield_risk_multiplier": 1.0,
    "label": "ATOMIC_YIELD",
    "recommendations": [
      "Yield source has no external dependencies. Structural risk is minimal \u2014 only smart-contract risk applies."
    ],
    "timestamp": 1784622798.7440836
  },
  {
    "yield_source_name": "UNKNOWN",
    "dependency_chain": [],
    "max_chain_depth": 0,
    "effective_depth": 0,
    "total_failure_probability_pct": 0.0,
    "weakest_link": {},
    "chain_centralization_score": 0.0,
    "effective_yield_risk_multiplier": 1.0,
    "label": "ATOMIC_YIELD",
    "recommendations": [
      "Yield source has no external dependencies. Structural risk is minimal \u2014 only smart-contract risk applies."
    ],
    "timestamp": 1784622799.1087437
  },
  {
    "yield_source_name": "UNKNOWN",
    "dependency_chain": [],
    "max_chain_depth": 0,
    "effective_depth": 0,
    "total_failure_probability_pct": 0.0,
    "weakest_link": {},
    "chain_centralization_score": 0.0,
    "effective_yield_risk_multiplier": 1.0,
    "label": "ATOMIC_YIELD",
    "recommendations": [
      "Yield source has no external dependencies. Structural risk is minimal \u2014 only smart-contract risk applies."
    ],
    "timestamp": 1784622799.4756777
  },
  {
    "yield_source_name": "UNKNOWN",
    "dependency_chain": [],
    "max_chain_depth": 0,
    "effective_depth": 0,
    "total_failure_probability_pct": 0.0,
    "weakest_link": {},
    "chain_centralization_score": 0.0,
    "effective_yield_risk_multiplier": 1.0,
    "label": "ATOMIC_YIELD",
    "recommendations": [
      "Yield source has no external dependencies. Structural risk is minimal \u2014 only smart-contract risk applies."
    ],
    "timestamp": 1784622799.8409474
  },
  {
    "yield_source_name": "UNKNOWN",
    "dependency_chain": [],
    "max_chain_depth": 0,
    "effective_depth": 0,
    "total_failure_probability_pct": 0.0,
    "weakest_link": {},
    "chain_centralization_score": 0.0,
    "effective_yield_risk_multiplier": 1.0,
    "label": "ATOMIC_YIELD",
    "recommendations": [
      "Yield source has no external dependencies. Structural risk is minimal \u2014 only smart-contract risk applies."
    ],
    "timestamp": 1784622802.9927542
  },
  {
    "yield_source_name": "UNKNOWN",
    "dependency_chain": [],
    "max_chain_depth": 0,
    "effective_depth": 0,
    "total_failure_probability_pct": 0.0,
    "weakest_link": {},
    "chain_centralization_score": 0.0,
    "effective_yield_risk_multiplier": 1.0,
    "label": "ATOMIC_YIELD",
    "recommendations": [
      "Yield source has no external dependencies. Structural risk is minimal \u2014 only smart-contract risk applies."
    ],
    "timestamp": 1784622803.3834484
  },
  {
    "yield_source_name": "UNKNOWN",
    "dependency_chain": [],
    "max_chain_depth": 0,
    "effective_depth": 0,
    "total_failure_probability_pct": 0.0,
    "weakest_link": {},
    "chain_centralization_score": 0.0,
    "effective_yield_risk_multiplier": 1.0,
    "label": "ATOMIC_YIELD",
    "recommendations": [
      "Yield source has no external dependencies. Structural risk is minimal \u2014 only smart-contract risk applies."
    ],
    "timestamp": 1784622803.7686534
  },
  {
    "yield_source_name": "UNKNOWN",
    "dependency_chain": [],
    "max_chain_depth": 0,
    "effective_depth": 0,
    "total_failure_probability_pct": 0.0,
    "weakest_link": {},
    "chain_centralization_score": 0.0,
    "effective_yield_risk_multiplier": 1.0,
    "label": "ATOMIC_YIELD",
    "recommendations": [
      "Yield source has no external dependencies. Structural risk is minimal \u2014 only smart-contract risk applies."
    ],
    "timestamp": 1784622804.2062397
  },
  {
    "yield_source_name": "UNKNOWN",
    "dependency_chain": [],
    "max_chain_depth": 0,
    "effective_depth": 0,
    "total_failure_probability_pct": 0.0,
    "weakest_link": {},
    "chain_centralization_score": 0.0,
    "effective_yield_risk_multiplier": 1.0,
    "label": "ATOMIC_YIELD",
    "recommendations": [
      "Yield source has no external dependencies. Structural risk is minimal \u2014 only smart-contract risk applies."
    ],
    "timestamp": 1784622804.5825272
  },
  {
    "yield_source_name": "UNKNOWN",
    "dependency_chain": [],
    "max_chain_depth": 0,
    "effective_depth": 0,
    "total_failure_probability_pct": 0.0,
    "weakest_link": {},
    "chain_centralization_score": 0.0,
    "effective_yield_risk_multiplier": 1.0,
    "label": "ATOMIC_YIELD",
    "recommendations": [
      "Yield source has no external dependencies. Structural risk is minimal \u2014 only smart-contract risk applies."
    ],
    "timestamp": 1784622804.9835696
  },
  {
    "yield_source_name": "UNKNOWN",
    "dependency_chain": [],
    "max_chain_depth": 0,
    "effective_depth": 0,
    "total_failure_probability_pct": 0.0,
    "weakest_link": {},
    "chain_centralization_score": 0.0,
    "effective_yield_risk_multiplier": 1.0,
    "label": "ATOMIC_YIELD",
    "recommendations": [
      "Yield source has no external dependencies. Structural risk is minimal \u2014 only smart-contract risk applies."
    ],
    "timestamp": 1784622805.4233
  },
  {
    "yield_source_name": "UNKNOWN",
    "dependency_chain": [],
    "max_chain_depth": 0,
    "effective_depth": 0,
    "total_failure_probability_pct": 0.0,
    "weakest_link": {},
    "chain_centralization_score": 0.0,
    "effective_yield_risk_multiplier": 1.0,
    "label": "ATOMIC_YIELD",
    "recommendations": [
      "Yield source has no external dependencies. Structural risk is minimal \u2014 only smart-contract risk applies."
    ],
    "timestamp": 1784622805.8075645
  },
  {
    "yield_source_name": "UNKNOWN",
    "dependency_chain": [],
    "max_chain_depth": 0,
    "effective_depth": 0,
    "total_failure_probability_pct": 0.0,
    "weakest_link": {},
    "chain_centralization_score": 0.0,
    "effective_yield_risk_multiplier": 1.0,
    "label": "ATOMIC_YIELD",
    "recommendations": [
      "Yield source has no external dependencies. Structural risk is minimal \u2014 only smart-contract risk applies."
    ],
    "timestamp": 1784622809.080988
  },
  {
    "yield_source_name": "UNKNOWN",
    "dependency_chain": [],
    "max_chain_depth": 0,
    "effective_depth": 0,
    "total_failure_probability_pct": 0.0,
    "weakest_link": {},
    "chain_centralization_score": 0.0,
    "effective_yield_risk_multiplier": 1.0,
    "label": "ATOMIC_YIELD",
    "recommendations": [
      "Yield source has no external dependencies. Structural risk is minimal \u2014 only smart-contract risk applies."
    ],
    "timestamp": 1784622809.4541547
  },
  {
    "yield_source_name": "UNKNOWN",
    "dependency_chain": [],
    "max_chain_depth": 0,
    "effective_depth": 0,
    "total_failure_probability_pct": 0.0,
    "weakest_link": {},
    "chain_centralization_score": 0.0,
    "effective_yield_risk_multiplier": 1.0,
    "label": "ATOMIC_YIELD",
    "recommendations": [
      "Yield source has no external dependencies. Structural risk is minimal \u2014 only smart-contract risk applies."
    ],
    "timestamp": 1784622809.821061
  },
  {
    "yield_source_name": "UNKNOWN",
    "dependency_chain": [],
    "max_chain_depth": 0,
    "effective_depth": 0,
    "total_failure_probability_pct": 0.0,
    "weakest_link": {},
    "chain_centralization_score": 0.0,
    "effective_yield_risk_multiplier": 1.0,
    "label": "ATOMIC_YIELD",
    "recommendations": [
      "Yield source has no external dependencies. Structural risk is minimal \u2014 only smart-contract risk applies."
    ],
    "timestamp": 1784622810.1860356
  },
  {
    "yield_source_name": "UNKNOWN",
    "dependency_chain": [],
    "max_chain_depth": 0,
    "effective_depth": 0,
    "total_failure_probability_pct": 0.0,
    "weakest_link": {},
    "chain_centralization_score": 0.0,
    "effective_yield_risk_multiplier": 1.0,
    "label": "ATOMIC_YIELD",
    "recommendations": [
      "Yield source has no external dependencies. Structural risk is minimal \u2014 only smart-contract risk applies."
    ],
    "timestamp": 1784622810.6203017
  },
  {
    "yield_source_name": "UNKNOWN",
    "dependency_chain": [],
    "max_chain_depth": 0,
    "effective_depth": 0,
    "total_failure_probability_pct": 0.0,
    "weakest_link": {},
    "chain_centralization_score": 0.0,
    "effective_yield_risk_multiplier": 1.0,
    "label": "ATOMIC_YIELD",
    "recommendations": [
      "Yield source has no external dependencies. Structural risk is minimal \u2014 only smart-contract risk applies."
    ],
    "timestamp": 1784622811.0856886
  },
  {
    "yield_source_name": "UNKNOWN",
    "dependency_chain": [],
    "max_chain_depth": 0,
    "effective_depth": 0,
    "total_failure_probability_pct": 0.0,
    "weakest_link": {},
    "chain_centralization_score": 0.0,
    "effective_yield_risk_multiplier": 1.0,
    "label": "ATOMIC_YIELD",
    "recommendations": [
      "Yield source has no external dependencies. Structural risk is minimal \u2014 only smart-contract risk applies."
    ],
    "timestamp": 1784622811.6149075
  },
  {
    "yield_source_name": "UNKNOWN",
    "dependency_chain": [],
    "max_chain_depth": 0,
    "effective_depth": 0,
    "total_failure_probability_pct": 0.0,
    "weakest_link": {},
    "chain_centralization_score": 0.0,
    "effective_yield_risk_multiplier": 1.0,
    "label": "ATOMIC_YIELD",
    "recommendations": [
      "Yield source has no external dependencies. Structural risk is minimal \u2014 only smart-contract risk applies."
    ],
    "timestamp": 1784622812.121921
  },
  {
    "yield_source_name": "UNKNOWN",
    "dependency_chain": [],
    "max_chain_depth": 0,
    "effective_depth": 0,
    "total_failure_probability_pct": 0.0,
    "weakest_link": {},
    "chain_centralization_score": 0.0,
    "effective_yield_risk_multiplier": 1.0,
    "label": "ATOMIC_YIELD",
    "recommendations": [
      "Yield source has no external dependencies. Structural risk is minimal \u2014 only smart-contract risk applies."
    ],
    "timestamp": 1784622815.8950424
  },
  {
    "yield_source_name": "UNKNOWN",
    "dependency_chain": [],
    "max_chain_depth": 0,
    "effective_depth": 0,
    "total_failure_probability_pct": 0.0,
    "weakest_link": {},
    "chain_centralization_score": 0.0,
    "effective_yield_risk_multiplier": 1.0,
    "label": "ATOMIC_YIELD",
    "recommendations": [
      "Yield source has no external dependencies. Structural risk is minimal \u2014 only smart-contract risk applies."
    ],
    "timestamp": 1784622816.3014064
  },
  {
    "yield_source_name": "UNKNOWN",
    "dependency_chain": [],
    "max_chain_depth": 0,
    "effective_depth": 0,
    "total_failure_probability_pct": 0.0,
    "weakest_link": {},
    "chain_centralization_score": 0.0,
    "effective_yield_risk_multiplier": 1.0,
    "label": "ATOMIC_YIELD",
    "recommendations": [
      "Yield source has no external dependencies. Structural risk is minimal \u2014 only smart-contract risk applies."
    ],
    "timestamp": 1784622816.6796515
  },
  {
    "yield_source_name": "UNKNOWN",
    "dependency_chain": [],
    "max_chain_depth": 0,
    "effective_depth": 0,
    "total_failure_probability_pct": 0.0,
    "weakest_link": {},
    "chain_centralization_score": 0.0,
    "effective_yield_risk_multiplier": 1.0,
    "label": "ATOMIC_YIELD",
    "recommendations": [
      "Yield source has no external dependencies. Structural risk is minimal \u2014 only smart-contract risk applies."
    ],
    "timestamp": 1784622817.0433753
  },
  {
    "yield_source_name": "UNKNOWN",
    "dependency_chain": [],
    "max_chain_depth": 0,
    "effective_depth": 0,
    "total_failure_probability_pct": 0.0,
    "weakest_link": {},
    "chain_centralization_score": 0.0,
    "effective_yield_risk_multiplier": 1.0,
    "label": "ATOMIC_YIELD",
    "recommendations": [
      "Yield source has no external dependencies. Structural risk is minimal \u2014 only smart-contract risk applies."
    ],
    "timestamp": 1784622817.4731119
  },
  {
    "yield_source_name": "UNKNOWN",
    "dependency_chain": [],
    "max_chain_depth": 0,
    "effective_depth": 0,
    "total_failure_probability_pct": 0.0,
    "weakest_link": {},
    "chain_centralization_score": 0.0,
    "effective_yield_risk_multiplier": 1.0,
    "label": "ATOMIC_YIELD",
    "recommendations": [
      "Yield source has no external dependencies. Structural risk is minimal \u2014 only smart-contract risk applies."
    ],
    "timestamp": 1784622817.8617573
  },
  {
    "yield_source_name": "UNKNOWN",
    "dependency_chain": [],
    "max_chain_depth": 0,
    "effective_depth": 0,
    "total_failure_probability_pct": 0.0,
    "weakest_link": {},
    "chain_centralization_score": 0.0,
    "effective_yield_risk_multiplier": 1.0,
    "label": "ATOMIC_YIELD",
    "recommendations": [
      "Yield source has no external dependencies. Structural risk is minimal \u2014 only smart-contract risk applies."
    ],
    "timestamp": 1784622818.2108572
  },
  {
    "yield_source_name": "UNKNOWN",
    "dependency_chain": [],
    "max_chain_depth": 0,
    "effective_depth": 0,
    "total_failure_probability_pct": 0.0,
    "weakest_link": {},
    "chain_centralization_score": 0.0,
    "effective_yield_risk_multiplier": 1.0,
    "label": "ATOMIC_YIELD",
    "recommendations": [
      "Yield source has no external dependencies. Structural risk is minimal \u2014 only smart-contract risk applies."
    ],
    "timestamp": 1784622819.1338136
  },
  {
    "yield_source_name": "UNKNOWN",
    "dependency_chain": [],
    "max_chain_depth": 0,
    "effective_depth": 0,
    "total_failure_probability_pct": 0.0,
    "weakest_link": {},
    "chain_centralization_score": 0.0,
    "effective_yield_risk_multiplier": 1.0,
    "label": "ATOMIC_YIELD",
    "recommendations": [
      "Yield source has no external dependencies. Structural risk is minimal \u2014 only smart-contract risk applies."
    ],
    "timestamp": 1784622822.7013514
  },
  {
    "yield_source_name": "UNKNOWN",
    "dependency_chain": [],
    "max_chain_depth": 0,
    "effective_depth": 0,
    "total_failure_probability_pct": 0.0,
    "weakest_link": {},
    "chain_centralization_score": 0.0,
    "effective_yield_risk_multiplier": 1.0,
    "label": "ATOMIC_YIELD",
    "recommendations": [
      "Yield source has no external dependencies. Structural risk is minimal \u2014 only smart-contract risk applies."
    ],
    "timestamp": 1784622823.0647697
  }
]